Workbook
Name Slicer_Building_Age: #N/A
Name Slicer_Building_Age1: #N/A
Name Slicer_Outlier: #N/A
Name Slicer_Outlier1: #N/A
Name Slicer_Size_Bracket: #N/A
Name Slicer_Size_Bracket1: #N/A
Name Slicer_Verdict: #N/A
Name Slicer_Verdict1: #N/A
Name Slicer_Year: #N/A
Name Slicer_Year1: #N/A

Sheet Dashboard
B1: CENTRAL FLORIDA HCRE SALES REPORT | AF1: Year | AG1: (All) | AJ1: Verdict | AK1: (All) | AN1: Year | AO1: (All) | AR1: Year | AS1: (All) | AX1: Year | AY1: (All)
B2: Medical Office Building Sales | Orange, Seminole, Osceola & Lake Counties | 2020-2025 | X2: Year | Y2: (All) | AF2: County | AG2: (All) | AJ2: County | AK2: (All) | AN2: Verdict | AO2: (All) | AR2: Verdict | AS2: (All) | AX2: County | AY2: (All)
X3: Verdict | Y3: (All) | AF3: Size Bracket | AG3: (All) | AJ3: Size Bracket | AK3: (All) | AN3: Size Bracket | AO3: (All) | AR3: Size Bracket | AS3: (All) | AX3: Size Bracket | AY3: (All)
X4: Size Bracket | Y4: (All) | AF4: Building Age | AG4: (All) | AJ4: Building Age | AK4: (All) | AN4: Building Age | AO4: (All) | AR4: Building Age | AS4: (All) | AX4: Building Age | AY4: (All)
L5: AVG $/SF | N5: AVG SALE PRICE | X5: Building Age | Y5: (All) | AF5: Outlier | AG5: (Multiple Items) | AJ5: Outlier | AK5: (Multiple Items) | AN5: County | AO5: (All) | AR5: Outlier | AS5: (Multiple Items) | AX5: Outlier | AY5: (Multiple Items)
H6: =GETPIVOTDATA("Total Sales",X27) -> 195 | J6: =GETPIVOTDATA("Total Volume",X27) -> 497397799 | L6: =GETPIVOTDATA("Avg $/SF",AB27) -> 303.31751 | N6: =GETPIVOTDATA("Avg Price",AB27) -> 2550757.9 | P6: COUNTY PRICING COMPARISON | X6: Outlier | Y6: (Multiple Items) | AN6: Outlier | AO6: (Multiple Items)
H7: TOTAL SALES | J7: TOTAL VOLUME | L7: MEDIAN $/SF | N7: MEDIAN SALE PRICE | P7: County | Q7: # Sales | R7: Avg $/SF | S7: Avg Size | T7: Min Price | U7: Max Price | V7: Total Volume | AF7: Row Labels | AG7: # Sales | AJ7: Row Labels | AK7: Avg $/SF | AL7: # Sales | AR7: County | AS7: Min Price | AT7: Max Price | AU7: Avg Size | AV7: Total Volume | AX7: Verdict | AY7: Min Price | AZ7: Max Price | BA7: Avg Size | BB7: Total Volume | BC7: Avg $/SF
B8: Powered by: Lee & Associates | L8: =MEDIAN(SalesData[$/SF]) -> 252.32803 | N8: =MEDIAN(SalesData[Price]) -> 1270100 | P8: Orange | Q8: =IFERROR(GETPIVOTDATA("# Sales",$X$7,"County",P8),0) -> 68 | R8: =IFERROR(GETPIVOTDATA("Avg $/SF",$X$7,"County",P8),0) -> 313.9641 | S8: =IFERROR(GETPIVOTDATA("Avg Size",$AR$7,"County",P8),0) -> 11020.603 | T8: =IFERROR(GETPIVOTDATA("Min Price",$AR$7,"County",P8),0) -> 344600 | U8: =IFERROR(GETPIVOTDATA("Max Price",$AR$7,"County",P8),0) -> 15500000 | V8: =IFERROR(GETPIVOTDATA("Total Volume",$AR$7,"County",P8),0) -> 232837900 | X8: Row Labels | Y8: Avg $/SF | Z8: # Sales | AF8: Hospitals | AG8: 9 | AJ8: 2020 | AK8: 268.56028 | AL8: 23 | AN8: Prpty Addr | AO8: Price | AP8: $/SF | AQ8: Size | AR8: Lake | AS8: 210000 | AT8: 5272900 | AU8: 5066.4286 | AV8: 24059200 | AX8: Hospitals | AY8: 1340800 | AZ8: 15500000 | BA8: 14056 | BB8: 67023500 | BC8: 542.79918
B9: Created by: Nico Bañez | P9: Seminole | Q9: =IFERROR(GETPIVOTDATA("# Sales",$X$7,"County",P9),0) -> 53 | R9: =IFERROR(GETPIVOTDATA("Avg $/SF",$X$7,"County",P9),0) -> 245.16936 | S9: =IFERROR(GETPIVOTDATA("Avg Size",$AR$7,"County",P9),0) -> 5938.2453 | T9: =IFERROR(GETPIVOTDATA("Min Price",$AR$7,"County",P9),0) -> 250100 | U9: =IFERROR(GETPIVOTDATA("Max Price",$AR$7,"County",P9),0) -> 9998200 | V9: =IFERROR(GETPIVOTDATA("Total Volume",$AR$7,"County",P9),0) -> 78592500 | X9: Lake | Y9: 209.55388 | Z9: 21 | AF9: Medical | AG9: 125 | AJ9: 2021 | AK9: 285.97428 | AL9: 47 | AN9: 7208 Sand Lake Rd W | AO9: 15500000 | AP9: 386.9969 | AQ9: 40052 | AR9: Orange | AS9: 344600 | AT9: 15500000 | AU9: 11020.603 | AV9: 232837900 | AX9: Medical | AY9: 210000 | AZ9: 5050000 | BA9: 4442.52 | BB9: 141398100 | BC9: 253.64941
P10: Osceola | Q10: =IFERROR(GETPIVOTDATA("# Sales",$X$7,"County",P10),0) -> 23 | R10: =IFERROR(GETPIVOTDATA("Avg $/SF",$X$7,"County",P10),0) -> 291.34205 | S10: =IFERROR(GETPIVOTDATA("Avg Size",$AR$7,"County",P10),0) -> 5727 | T10: =IFERROR(GETPIVOTDATA("Min Price",$AR$7,"County",P10),0) -> 530000 | U10: =IFERROR(GETPIVOTDATA("Max Price",$AR$7,"County",P10),0) -> 5150000 | V10: =IFERROR(GETPIVOTDATA("Total Volume",$AR$7,"County",P10),0) -> 37585900 | X10: Orange | Y10: 313.9641 | Z10: 68 | AF10: Multi-Tenant Medical | AG10: 31 | AJ10: 2022 | AK10: 257.13098 | AL10: 32 | AN10: 9401 Summit Centre Wa | AO10: 15500000 | AP10: 1500.3388 | AQ10: 10331 | AR10: Osceola | AS10: 530000 | AT10: 5150000 | AU10: 5727 | AV10: 37585900 | AX10: Multi-Tenant Medical | AY10: 1600000 | AZ10: 15500000 | BA10: 20013.71 | BB10: 164653900 | BC10: 285.60207
P11: Lake | Q11: =IFERROR(GETPIVOTDATA("# Sales",$X$7,"County",P11),0) -> 21 | R11: =IFERROR(GETPIVOTDATA("Avg $/SF",$X$7,"County",P11),0) -> 209.55388 | S11: =IFERROR(GETPIVOTDATA("Avg Size",$AR$7,"County",P11),0) -> 5066.4286 | T11: =IFERROR(GETPIVOTDATA("Min Price",$AR$7,"County",P11),0) -> 210000 | U11: =IFERROR(GETPIVOTDATA("Max Price",$AR$7,"County",P11),0) -> 5272900 | V11: =IFERROR(GETPIVOTDATA("Total Volume",$AR$7,"County",P11),0) -> 24059200 | X11: Osceola | Y11: 291.34205 | Z11: 23 | AJ11: 2023 | AK11: 249.3862 | AL11: 26 | AN11: 7009 Dr Phillips Bl | AO11: 15000000 | AP11: 634.16903 | AQ11: 23653 | AR11: Seminole | AS11: 250100 | AT11: 9998200 | AU11: 5938.2453 | AV11: 78592500
X12: Seminole | Y12: 245.16936 | Z12: 53 | AJ12: 2024 | AK12: 263.12592 | AL12: 20 | AN12: 1745 Mills Av N | AO12: 13200000 | AP12: 470.42053 | AQ12: 28060
AJ13: 2025 | AK13: 344.27083 | AL13: 17 | AN13: 2909 Orange Av N | AO13: 10221900 | AP13: 651.90689 | AQ13: 15680
AN14: 658 Oviedo Medical Dr | AO14: 9998200 | AP14: 587.19681 | AQ14: 17027
P15: CATEGORY BREAKDOWN | AN15: 100 Sybelia Av E | AO15: 7750000 | AP15: 179.94799 | AQ15: 43068
H16: $/SF RANGE | J16: SALE PRICE RANGE | P16: Category | Q16: # Sales | R16: Avg $/SF | S16: Avg Size | T16: Min Price | U16: Max Price | V16: Total Volume | AN16: 12200 Colonial Dr W | AO16: 7600000 | AP16: 246.90556 | AQ16: 30781
H17: ="$"&TEXT(GETPIVOTDATA("Min $/SF",AB27),"#,##0")&" – $"&TEXT(GETPIVOTDATA("Max $/SF",AB27),"#,##0") -> $45 – $1,500 | J17: =TEXT(GETPIVOTDATA("Min Price",AB27),IF(GETPIVOTDATA("Min Price",AB27)>=1000000,"$#,##0,,""M""","$#,##0,""K"""))&" – "&TEXT(GETPIVOTDATA("Max Price",AB27),IF(GETPIVOTDATA("Max Price",AB27)>=1000000,"$#,##0,,""M""","$#,##0,""K""")) -> $210K – $33M | P17: Medical | Q17: =IFERROR(GETPIVOTDATA("# Sales",$AF$7,"Verdict",P17),0) -> 125 | R17: =IFERROR(GETPIVOTDATA("Avg $/SF",$AX$7,"Verdict",P17),0) -> 253.64941 | S17: =IFERROR(GETPIVOTDATA("Avg Size",$AX$7,"Verdict",P17),0) -> 4442.52 | T17: =IFERROR(GETPIVOTDATA("Min Price",$AX$7,"Verdict",P17),0) -> 210000 | U17: =IFERROR(GETPIVOTDATA("Max Price",$AX$7,"Verdict",P17),0) -> 5050000 | V17: =IFERROR(GETPIVOTDATA("Total Volume",$AX$7,"Verdict",P17),0) -> 141398100 | AN17: 7232 Sand Lake Rd W | AO17: 7500000 | AP17: 441.82622 | AQ17: 16975
P18: Multi-Tenant Medical | Q18: =IFERROR(GETPIVOTDATA("# Sales",$AF$7,"Verdict",P18),0) -> 31 | R18: =IFERROR(GETPIVOTDATA("Avg $/SF",$AX$7,"Verdict",P18),0) -> 285.60207 | S18: =IFERROR(GETPIVOTDATA("Avg Size",$AX$7,"Verdict",P18),0) -> 20013.71 | T18: =IFERROR(GETPIVOTDATA("Min Price",$AX$7,"Verdict",P18),0) -> 1600000 | U18: =IFERROR(GETPIVOTDATA("Max Price",$AX$7,"Verdict",P18),0) -> 15500000 | V18: =IFERROR(GETPIVOTDATA("Total Volume",$AX$7,"Verdict",P18),0) -> 164653900 | AN18: 1505 Colonial Dr E | AO18: 7125000 | AP18: 184.85847 | AQ18: 38543
P19: Hospitals | Q19: =IFERROR(GETPIVOTDATA("# Sales",$AF$7,"Verdict",P19),0) -> 9 | R19: =IFERROR(GETPIVOTDATA("Avg $/SF",$AX$7,"Verdict",P19),0) -> 542.79918 | S19: =IFERROR(GETPIVOTDATA("Avg Size",$AX$7,"Verdict",P19),0) -> 14056 | T19: =IFERROR(GETPIVOTDATA("Min Price",$AX$7,"Verdict",P19),0) -> 1340800 | U19: =IFERROR(GETPIVOTDATA("Max Price",$AX$7,"Verdict",P19),0) -> 15500000 | V19: =IFERROR(GETPIVOTDATA("Total Volume",$AX$7,"Verdict",P19),0) -> 67023500 | AN19: 1511 SR 434 # 1001 E | AO19: 7000000 | AP19: 176.76768 | AQ19: 39600
X20: Year | Y20: (All) | AN20: 341 Maitland Av N | AO20: 7000000 | AP20: 152.45894 | AQ20: 45914
X21: Verdict | Y21: (All) | AN21: 954 Orlando Av S | AO21: 6349400 | AP21: 424 | AQ21: 14975
X22: County | Y22: (All) | AN22: 1781 Park Center Dr | AO22: 5913600 | AP22: 238.42277 | AQ22: 24803
X23: Size Bracket | Y23: (All) | AN23: 770 Concourse Pk | AO23: 5610000 | AP23: 395.90685 | AQ23: 14170
X24: Building Age | Y24: (All) | AN24: 1701 Park Center Dr | AO24: 5600000 | AP24: 171.09163 | AQ24: 32731
P25: TOP SALES | X25: Outlier | Y25: (All) | AN25: 600 North Blvd W | AO25: 5272900 | AP25: 263.645 | AQ25: 20000
P26: Address | Q26: County | R26: Price | S26: Size | T26: $/SF | U26: Category | V26: Tenant | AN26: 3480 Polynesian Isle Blvd | AO26: 5150000 | AP26: 412.66026 | AQ26: 12480
P27: =AN9 -> 7208 Sand Lake Rd W | Q27: =INDEX(SalesData[County],MATCH(P27,SalesData[Prpty Addr],0)) -> Orange | R27: =AO9 -> 15500000 | S27: =AQ9 -> 40052 | T27: =AP9 -> 386.9969 | U27: =INDEX(SalesData[Verdict],MATCH(P27,SalesData[Prpty Addr],0)) -> Multi-Tenant Medical | V27: =INDEX(SalesData[Current Tenant],MATCH(P27,SalesData[Prpty Addr],0)) -> 7208 Sand Lake - Office Complex | X27: Total Volume | Y27: Avg $/SF | Z27: Avg Price | AA27: Min Price | AB27: Max Price | AC27: Min $/SF | AD27: Max $/SF | AE27: Avg Size | AF27: Total Sales | AN27: 780 Concourse Pk | AO27: 5100000 | AP27: 389.31298 | AQ27: 13100
P28: =AN10 -> 9401 Summit Centre Wa | Q28: =INDEX(SalesData[County],MATCH(P28,SalesData[Prpty Addr],0)) -> Orange | R28: =AO10 -> 15500000 | S28: =AQ10 -> 10331 | T28: =AP10 -> 1500.3388 | U28: =INDEX(SalesData[Verdict],MATCH(P28,SalesData[Prpty Addr],0)) -> Hospitals | V28: =INDEX(SalesData[Current Tenant],MATCH(P28,SalesData[Prpty Addr],0)) -> **HCA Florida Maitland Emergency (Freestanding ER)** MEDICAL CENTER | X28: 497397799 | Y28: 303.31751 | Z28: 2550757.9 | AA28: 210000 | AB28: 33444697 | AC28: 45.304778 | AD28: 1500.3388 | AE28: 8917.5641 | AF28: 195 | AN28: 106 Boston # 100 Ave | AO28: 5050000 | AP28: 202.46161 | AQ28: 24943
P29: =AN11 -> 7009 Dr Phillips Bl | Q29: =INDEX(SalesData[County],MATCH(P29,SalesData[Prpty Addr],0)) -> Orange | R29: =AO11 -> 15000000 | S29: =AQ11 -> 23653 | T29: =AP11 -> 634.16903 | U29: =INDEX(SalesData[Verdict],MATCH(P29,SalesData[Prpty Addr],0)) -> Multi-Tenant Medical | V29: =INDEX(SalesData[Current Tenant],MATCH(P29,SalesData[Prpty Addr],0)) -> Belmart LLC Dr Phillips | AN29: 1605 Fairbanks Av W | AO29: 5000000 | AP29: 405.28492 | AQ29: 12337
P30: =AN12 -> 1745 Mills Av N | Q30: =INDEX(SalesData[County],MATCH(P30,SalesData[Prpty Addr],0)) -> Orange | R30: =AO12 -> 13200000 | S30: =AQ12 -> 28060 | T30: =AP12 -> 470.42053 | U30: =INDEX(SalesData[Verdict],MATCH(P30,SalesData[Prpty Addr],0)) -> Hospitals | V30: =INDEX(SalesData[Current Tenant],MATCH(P30,SalesData[Prpty Addr],0)) -> Central Florida Cardiology Group MEDICAL CENTER | AN30: 10131 Colonial Dr W | AO30: 4918100 | AP30: 281.58136 | AQ30: 17466
AN31: 1803 Park Center Dr | AO31: 4875000 | AP31: 221.49023 | AQ31: 22010
AN32: 1071 Sun Dr S | AO32: 4500000 | AP32: 247.25275 | AQ32: 18200
AN33: 2233 Lee Rd | AO33: 4216800 | AP33: 200.81913 | AQ33: 20998
AN34: 100 Waymont Ct | AO34: 4100000 | AP34: 227.77778 | AQ34: 18000
AN35: 2940 Maguire Rd | AO35: 4030000 | AP35: 494.5999 | AQ35: 8148
AN36: 1400 Orlando Av S | AO36: 3900000 | AP36: 185.51111 | AQ36: 21023
AN37: 750 Concourse Pk | AO37: 3570000 | AP37: 399.41821 | AQ37: 8938
AN38: 1000 E Irlo Bronson Memorial | AO38: 3552600 | AP38: 466.95584 | AQ38: 7608
AN39: 1301 Colonial Dr W | AO39: 3518200 | AP39: 396.64036 | AQ39: 8870
AN40: 788 Montgomery Av | AO40: 3499900 | AP40: 251.91823 | AQ40: 13893
AN41: 1000 Executive Dr | AO41: 3425000 | AP41: 267.82921 | AQ41: 12788
AN42: 9582 Colonial Dr W | AO42: 3400000 | AP42: 356.24476 | AQ42: 9544
... AN173: 32629 Blossom Ln | AO173: 210000 | AP173: 108.63942 | AQ173: 1933

Sheet Market Trends
A1: CENTRAL FLORIDA HEALTHCARE REAL ESTATE — MARKET TRENDS (2020–2025)
A3: 1. INTEREST RATE ENVIRONMENT
B5: 2020 | C5: 2021 | D5: 2022 | E5: 2023 | F5: 2024 | G5: 2025 YTD
A6: Fed Funds Rate (Avg %) | B6: 0.0036 | C6: 0.0008 | D6: 0.0168 | E6: 0.0503 | F6: 0.0458 | G6: 0.0398
A7: 10-Year Treasury (Avg %) | B7: 0.0089 | C7: 0.0145 | D7: 0.0295 | E7: 0.0396 | F7: 0.0425 | G7: 0.0425
A10: 2. POPULATION GROWTH BY COUNTY
B12: 2020 | C12: 2021 | D12: 2022 | E12: 2023 | F12: 2024 | G12: 2025 Est.
A13: Orange County | B13: 1429908 | C13: 1458500 | D13: 1481321 | E13: 1492951 | F13: 1511568 | G13: 1536045
A14: Seminole County | B14: 470856 | C14: 473500 | D14: 476200 | E14: 478800 | F14: 481470 | G14: 484200
A15: Osceola County | B15: 388656 | C15: 406540 | D15: 424946 | E15: 439225 | F15: 451231 | G15: 484915
A16: Lake County | B16: 383956 | C16: 393600 | D16: 410090 | E16: 424462 | F16: 432000 | G16: 425000
A17: 4-County Total | B17: =SUM(B13:B16) -> 2673376 | C17: =SUM(C13:C16) -> 2732140 | D17: =SUM(D13:D16) -> 2792557 | E17: =SUM(E13:E16) -> 2835438 | F17: =SUM(F13:F16) -> 2876269 | G17: =SUM(G13:G16) -> 2930160
A19: Orange YoY Growth | C19: =(C13-B13)/B13 -> 0.019995692 | D19: =(D13-C13)/C13 -> 0.015646897 | E19: =(E13-D13)/D13 -> 0.0078511005 | F19: =(F13-E13)/E13 -> 0.012469934 | G19: =(G13-F13)/F13 -> 0.016193119
A20: Seminole YoY Growth | C20: =(C14-B14)/B14 -> 0.0056153049 | D20: =(D14-C14)/C14 -> 0.0057022175 | E20: =(E14-D14)/D14 -> 0.0054598908 | F20: =(F14-E14)/E14 -> 0.0055764411 | G20: =(G14-F14)/F14 -> 0.0056701352
A21: Osceola YoY Growth | C21: =(C15-B15)/B15 -> 0.046014985 | D21: =(D15-C15)/C15 -> 0.045274758 | E21: =(E15-D15)/D15 -> 0.033601916 | F21: =(F15-E15)/E15 -> 0.02733451 | G21: =(G15-F15)/F15 -> 0.074649127
A22: Lake YoY Growth | C22: =(C16-B16)/B16 -> 0.025117461 | D22: =(D16-C16)/C16 -> 0.041895325 | E22: =(E16-D16)/D16 -> 0.035045966 | F22: =(F16-E16)/E16 -> 0.017758951 | G22: =(G16-F16)/F16 -> -0.016203704
A25: 3. MEDICAL OFFICE CONSTRUCTION COSTS
B27: 2020 | C27: 2021 | D27: 2022 | E27: 2023 | F27: 2024 | G27: 2025
A28: Construction Cost ($/SF) | B28: N/A | C28: N/A | D28: N/A | E28: N/A | F28: N/A | G28: N/A
A29: ⚠️ Data behind paywall — requires RSMeans, Gordian, or Cumming construction cost reports. Enter your data above.
A32: 4. HEALTHCARE REAL ESTATE CAP RATES
B34: 2020 | C34: 2021 | D34: 2022 | E34: 2023 | F34: 2024 | G34: 2025
A35: Medical Office Cap Rate (%) | B35: N/A | C35: N/A | D35: N/A | E35: N/A | F35: N/A | G35: N/A
A36: ⚠️ Data behind paywall — requires CBRE, JLL, or RCA cap rate surveys. Enter your data above.
A38: SOURCES & REFERENCES
A39: Interest Rate Data
A40: Board of Governors of the Federal Reserve System. "Federal Funds Effective Rate [FEDFUNDS]." FRED, Federal Reserve Bank of St. Louis. Retrieved April 2025. https://fred.stlouisfed.org/series/FEDFUNDS
A41: Board of Governors of the Federal Reserve System. "Market Yield on U.S. Treasury Securities at 10-Year Constant Maturity [DGS10]." FRED, Federal Reserve Bank of St. Louis. Retrieved April 2025. https://fred.stlouisfed.org/series/DGS10
A43: Population Data
A44: Florida Legislature, Office of Economic & Demographic Research (EDR). "County Area Profiles: Orange County, Osceola County." Retrieved April 2025. https://edr.state.fl.us/content/area-profiles/
A45: U.S. Census Bureau. "QuickFacts: Seminole County, FL; Lake County, FL." Retrieved April 2025. https://www.census.gov/quickfacts/
A46: Florida-Demographics.com. "Seminole County Demographics." Census-derived population estimates. Retrieved April 2025. https://www.florida-demographics.com/seminole-county-demographics
A47: MSA Population Comparison Data
A48: U.S. Census Bureau. "Annual Estimates of the Resident Population for Metropolitan Statistical Areas." Vintage 2024. Retrieved via FRED, Federal Reserve Bank of St. Louis, April 2025. Series: ORLPOP, DFWPOP, CGRPOP, SATPOP, TMAPOP, NVLPOP, PHXPOP, MIMPOP. https://fred.stlouisfed.org/release?rid=111
A50: Construction Cost & Cap Rate Data (Not Yet Populated)
... A54: Interest rates reflect annual averages of daily observations; 2025 figures represent January–April year-to-date averages. Population estimates for Seminole County (2021–2023) and Lake County (2021–2023) are linear interpolations between U.S. Census 2020 decennial counts and the latest available annual estimate. MSA population estimates are July 1 estimates from the Census Bureau's Vintage 2024 series. All other population figures are sourced directly from FL EDR or U.S. Census Bureau releases.
A56: Report prepared using data retrieved April 2025. All figures are subject to revision upon release of updated government estimates. | B56: =C12 -> 2021 | C56: =D12 -> 2022 | D56: =E12 -> 2023 | E56: =F12 -> 2024 | F56: =G12 -> 2025 Est.
A57: Orange County | B57: =C19 -> 0.019995692 | C57: =D19 -> 0.015646897 | D57: =E19 -> 0.0078511005 | E57: =F19 -> 0.012469934 | F57: =G19 -> 0.016193119
A58: Seminole County | B58: =C20 -> 0.0056153049 | C58: =D20 -> 0.0057022175 | D58: =E20 -> 0.0054598908 | E58: =F20 -> 0.0055764411 | F58: =G20 -> 0.0056701352
A59: Osceola County | B59: =C21 -> 0.046014985 | C59: =D21 -> 0.045274758 | D59: =E21 -> 0.033601916 | E59: =F21 -> 0.02733451 | F59: =G21 -> 0.074649127
A60: Lake County | B60: =C22 -> 0.025117461 | C60: =D22 -> 0.041895325 | D60: =E22 -> 0.035045966 | E60: =F22 -> 0.017758951 | F60: =G22 -> -0.016203704
A62: County | B62: =B12 -> 2020 | C62: =C12 -> 2021 | D62: =D12 -> 2022 | E62: =E12 -> 2023 | F62: =F12 -> 2024 | G62: =G12 -> 2025 Est.
A63: Orange County | B63: =B13 -> 1429908 | C63: =C13 -> 1458500 | D63: =D13 -> 1481321 | E63: =E13 -> 1492951 | F63: =F13 -> 1511568 | G63: =G13 -> 1536045
A64: Seminole County | B64: =B14 -> 470856 | C64: =C14 -> 473500 | D64: =D14 -> 476200 | E64: =E14 -> 478800 | F64: =F14 -> 481470 | G64: =G14 -> 484200
A65: Osceola County | B65: =B15 -> 388656 | C65: =C15 -> 406540 | D65: =D15 -> 424946 | E65: =E15 -> 439225 | F65: =F15 -> 451231 | G65: =G15 -> 484915
A66: Lake County | B66: =B16 -> 383956 | C66: =C16 -> 393600 | D66: =D16 -> 410090 | E66: =E16 -> 424462 | F66: =F16 -> 432000 | G66: =G16 -> 425000
A67: 4-County Total | B67: =B17 -> 2673376 | C67: =C17 -> 2732140 | D67: =D17 -> 2792557 | E67: =E17 -> 2835438 | F67: =F17 -> 2876269 | G67: =G17 -> 2930160
A69: 5. MSA POPULATION COMPARISON (2020–2024)
A70: Population in thousands. Source: U.S. Census Bureau via FRED, Vintage 2024 estimates (July 1 of each year).
A71: Metro Area (MSA) | B71: 2020 | C71: 2021 | D71: 2022 | E71: 2023 | F71: 2024 | G71: 4-Year Growth
A72: Orlando-Kissimmee-Sanford, FL ★ | B72: 2680.593 | C72: 2699.313 | D72: 2783.767 | E72: 2864.544 | F72: 2940.513 | G72: =F72/B72-1 -> 0.09696362 | H72: Orlando ★
A73: Dallas-Fort Worth-Arlington, TX | B73: 7667.594 | C73: 7776.611 | D73: 7973.603 | E73: 8166.11 | F73: 8344.032 | G73: =F73/B73-1 -> 0.088220373 | H73: Dallas-Fort Worth
A74: Charlotte-Concord-Gastonia, NC-SC | B74: 2668.301 | C74: 2706.093 | D74: 2758.749 | E74: 2818.271 | F74: 2884.708 | G74: =F74/B74-1 -> 0.081102919 | H74: Charlotte
A75: San Antonio-New Braunfels, TX | B75: 2568.935 | C75: 2605.783 | D75: 2660.228 | E75: 2715.709 | F75: 2763.006 | G75: =F75/B75-1 -> 0.075545314 | H75: San Antonio
A76: Tampa-St. Petersburg-Clearwater, FL | B76: 3187.97 | C76: 3230.564 | D76: 3306.285 | E76: 3374.078 | F76: 3424.56 | G76: =F76/B76-1 -> 0.074213371 | H76: Tampa
A77: Nashville-Davidson-Murfreesboro-Franklin, TN | B77: 2021.825 | C77: 2033.685 | D77: 2077.922 | E77: 2113.986 | F77: 2150.553 | G77: =F77/B77-1 -> 0.06366921 | H77: Nashville
A78: Phoenix-Mesa-Scottsdale, AZ | B78: 4875.628 | C78: 4949.233 | D78: 5029.933 | E78: 5102.02 | F78: 5186.958 | G78: =F78/B78-1 -> 0.063854338 | H78: Phoenix
A79: Miami-Fort Lauderdale-West Palm Beach, FL | B79: 6133.502 | C79: 6109.257 | D79: 6211.194 | E79: 6334.517 | F79: 6457.988 | G79: =F79/B79-1 -> 0.052903871 | H79: Miami
A81: MSA | B81: 4-Year Growth (2020-2024)
A82: Orlando ★ | B82: =G72 -> 0.09696362
A83: Dallas-Fort Worth | B83: =G73 -> 0.088220373
A84: Charlotte | B84: =G74 -> 0.081102919
A85: San Antonio | B85: =G75 -> 0.075545314
A86: Tampa | B86: =G76 -> 0.074213371
A87: Nashville | B87: =G77 -> 0.06366921
A88: Phoenix | B88: =G78 -> 0.063854338
A89: Miami | B89: =G79 -> 0.052903871

Sheet Copy Dashboard
B1: CENTRAL FLORIDA HCRE SALES REPORT | AF1: Year | AG1: (All) | AJ1: Verdict | AK1: (All) | AN1: Year | AO1: (All) | AR1: Year | AS1: (All) | AX1: Year | AY1: (All)
B2: Medical Office Building Sales | Orange, Seminole, Osceola & Lake Counties | 2020-2025 | X2: Year | Y2: (All) | AF2: County | AG2: (All) | AJ2: County | AK2: (All) | AN2: Verdict | AO2: (All) | AR2: Verdict | AS2: (All) | AX2: County | AY2: (All)
X3: Verdict | Y3: (All) | AF3: Size Bracket | AG3: (All) | AJ3: Size Bracket | AK3: (All) | AN3: Size Bracket | AO3: (All) | AR3: Size Bracket | AS3: (All) | AX3: Size Bracket | AY3: (All)
X4: Size Bracket | Y4: (All) | AF4: Building Age | AG4: (All) | AJ4: Building Age | AK4: (All) | AN4: Building Age | AO4: (All) | AR4: Building Age | AS4: (All) | AX4: Building Age | AY4: (All)
L5: AVG $/SF | N5: AVG SALE PRICE | X5: Building Age | Y5: (All) | AF5: Outlier | AG5: (Multiple Items) | AJ5: Outlier | AK5: (Multiple Items) | AN5: County | AO5: (All) | AR5: Outlier | AS5: (Multiple Items) | AX5: Outlier | AY5: (Multiple Items)
H6: =GETPIVOTDATA("Total Sales",X27) -> 195 | J6: =GETPIVOTDATA("Total Volume",X27) -> 497397799 | L6: =GETPIVOTDATA("Avg $/SF",AB27) -> 303.31751 | N6: =GETPIVOTDATA("Avg Price",AB27) -> 2550757.9 | P6: COUNTY PRICING COMPARISON | X6: Outlier | Y6: (Multiple Items) | AN6: Outlier | AO6: (Multiple Items)
H7: TOTAL SALES | J7: TOTAL VOLUME | L7: MEDIAN $/SF | N7: MEDIAN SALE PRICE | P7: County | Q7: # Sales | R7: Avg $/SF | S7: Avg Size | T7: Min Price | U7: Max Price | V7: Total Volume | AF7: Row Labels | AG7: # Sales | AJ7: Row Labels | AK7: Avg $/SF | AL7: # Sales | AR7: County | AS7: Min Price | AT7: Max Price | AU7: Avg Size | AV7: Total Volume | AX7: Verdict | AY7: Min Price | AZ7: Max Price | BA7: Avg Size | BB7: Total Volume | BC7: Avg $/SF
B8: Powered by: Lee & Associates | L8: =MEDIAN(SalesData[$/SF]) -> 252.32803 | N8: =MEDIAN(SalesData[Price]) -> 1270100 | P8: Orange | Q8: =IFERROR(GETPIVOTDATA("# Sales",$X$7,"County",P8),0) -> 68 | R8: =IFERROR(GETPIVOTDATA("Avg $/SF",$X$7,"County",P8),0) -> 313.9641 | S8: =IFERROR(GETPIVOTDATA("Avg Size",$AR$7,"County",P8),0) -> 11020.603 | T8: =IFERROR(GETPIVOTDATA("Min Price",$AR$7,"County",P8),0) -> 344600 | U8: =IFERROR(GETPIVOTDATA("Max Price",$AR$7,"County",P8),0) -> 15500000 | V8: =IFERROR(GETPIVOTDATA("Total Volume",$AR$7,"County",P8),0) -> 232837900 | X8: Row Labels | Y8: Avg $/SF | Z8: # Sales | AF8: Hospitals | AG8: 9 | AJ8: 2020 | AK8: 268.56028 | AL8: 23 | AN8: Prpty Addr | AO8: Price | AP8: $/SF | AQ8: Size | AR8: Lake | AS8: 210000 | AT8: 5272900 | AU8: 5066.4286 | AV8: 24059200 | AX8: Hospitals | AY8: 1340800 | AZ8: 15500000 | BA8: 14056 | BB8: 67023500 | BC8: 542.79918
B9: Created by: Nico Bañez | P9: Seminole | Q9: =IFERROR(GETPIVOTDATA("# Sales",$X$7,"County",P9),0) -> 53 | R9: =IFERROR(GETPIVOTDATA("Avg $/SF",$X$7,"County",P9),0) -> 245.16936 | S9: =IFERROR(GETPIVOTDATA("Avg Size",$AR$7,"County",P9),0) -> 5938.2453 | T9: =IFERROR(GETPIVOTDATA("Min Price",$AR$7,"County",P9),0) -> 250100 | U9: =IFERROR(GETPIVOTDATA("Max Price",$AR$7,"County",P9),0) -> 9998200 | V9: =IFERROR(GETPIVOTDATA("Total Volume",$AR$7,"County",P9),0) -> 78592500 | X9: Lake | Y9: 209.55388 | Z9: 21 | AF9: Medical | AG9: 125 | AJ9: 2021 | AK9: 285.97428 | AL9: 47 | AN9: 7208 Sand Lake Rd W | AO9: 15500000 | AP9: 386.9969 | AQ9: 40052 | AR9: Orange | AS9: 344600 | AT9: 15500000 | AU9: 11020.603 | AV9: 232837900 | AX9: Medical | AY9: 210000 | AZ9: 5050000 | BA9: 4442.52 | BB9: 141398100 | BC9: 253.64941
P10: Osceola | Q10: =IFERROR(GETPIVOTDATA("# Sales",$X$7,"County",P10),0) -> 23 | R10: =IFERROR(GETPIVOTDATA("Avg $/SF",$X$7,"County",P10),0) -> 291.34205 | S10: =IFERROR(GETPIVOTDATA("Avg Size",$AR$7,"County",P10),0) -> 5727 | T10: =IFERROR(GETPIVOTDATA("Min Price",$AR$7,"County",P10),0) -> 530000 | U10: =IFERROR(GETPIVOTDATA("Max Price",$AR$7,"County",P10),0) -> 5150000 | V10: =IFERROR(GETPIVOTDATA("Total Volume",$AR$7,"County",P10),0) -> 37585900 | X10: Orange | Y10: 313.9641 | Z10: 68 | AF10: Multi-Tenant Medical | AG10: 31 | AJ10: 2022 | AK10: 257.13098 | AL10: 32 | AN10: 9401 Summit Centre Wa | AO10: 15500000 | AP10: 1500.3388 | AQ10: 10331 | AR10: Osceola | AS10: 530000 | AT10: 5150000 | AU10: 5727 | AV10: 37585900 | AX10: Multi-Tenant Medical | AY10: 1600000 | AZ10: 15500000 | BA10: 20013.71 | BB10: 164653900 | BC10: 285.60207
P11: Lake | Q11: =IFERROR(GETPIVOTDATA("# Sales",$X$7,"County",P11),0) -> 21 | R11: =IFERROR(GETPIVOTDATA("Avg $/SF",$X$7,"County",P11),0) -> 209.55388 | S11: =IFERROR(GETPIVOTDATA("Avg Size",$AR$7,"County",P11),0) -> 5066.4286 | T11: =IFERROR(GETPIVOTDATA("Min Price",$AR$7,"County",P11),0) -> 210000 | U11: =IFERROR(GETPIVOTDATA("Max Price",$AR$7,"County",P11),0) -> 5272900 | V11: =IFERROR(GETPIVOTDATA("Total Volume",$AR$7,"County",P11),0) -> 24059200 | X11: Osceola | Y11: 291.34205 | Z11: 23 | AJ11: 2023 | AK11: 249.3862 | AL11: 26 | AN11: 7009 Dr Phillips Bl | AO11: 15000000 | AP11: 634.16903 | AQ11: 23653 | AR11: Seminole | AS11: 250100 | AT11: 9998200 | AU11: 5938.2453 | AV11: 78592500
X12: Seminole | Y12: 245.16936 | Z12: 53 | AJ12: 2024 | AK12: 263.12592 | AL12: 20 | AN12: 1745 Mills Av N | AO12: 13200000 | AP12: 470.42053 | AQ12: 28060
AJ13: 2025 | AK13: 344.27083 | AL13: 17 | AN13: 2909 Orange Av N | AO13: 10221900 | AP13: 651.90689 | AQ13: 15680
AN14: 658 Oviedo Medical Dr | AO14: 9998200 | AP14: 587.19681 | AQ14: 17027
P15: CATEGORY BREAKDOWN | AN15: 100 Sybelia Av E | AO15: 7750000 | AP15: 179.94799 | AQ15: 43068
H16: $/SF RANGE | J16: SALE PRICE RANGE | P16: Category | Q16: # Sales | R16: Avg $/SF | S16: Avg Size | T16: Min Price | U16: Max Price | V16: Total Volume | AN16: 12200 Colonial Dr W | AO16: 7600000 | AP16: 246.90556 | AQ16: 30781
H17: ="$"&TEXT(GETPIVOTDATA("Min $/SF",AB27),"#,##0")&" – $"&TEXT(GETPIVOTDATA("Max $/SF",AB27),"#,##0") -> $45 – $1,500 | J17: =TEXT(GETPIVOTDATA("Min Price",AB27),IF(GETPIVOTDATA("Min Price",AB27)>=1000000,"$#,##0,,""M""","$#,##0,""K"""))&" – "&TEXT(GETPIVOTDATA("Max Price",AB27),IF(GETPIVOTDATA("Max Price",AB27)>=1000000,"$#,##0,,""M""","$#,##0,""K""")) -> $210K – $33M | P17: Medical | Q17: =IFERROR(GETPIVOTDATA("# Sales",$AF$7,"Verdict",P17),0) -> 125 | R17: =IFERROR(GETPIVOTDATA("Avg $/SF",$AX$7,"Verdict",P17),0) -> 253.64941 | S17: =IFERROR(GETPIVOTDATA("Avg Size",$AX$7,"Verdict",P17),0) -> 4442.52 | T17: =IFERROR(GETPIVOTDATA("Min Price",$AX$7,"Verdict",P17),0) -> 210000 | U17: =IFERROR(GETPIVOTDATA("Max Price",$AX$7,"Verdict",P17),0) -> 5050000 | V17: =IFERROR(GETPIVOTDATA("Total Volume",$AX$7,"Verdict",P17),0) -> 141398100 | AN17: 7232 Sand Lake Rd W | AO17: 7500000 | AP17: 441.82622 | AQ17: 16975
P18: Multi-Tenant Medical | Q18: =IFERROR(GETPIVOTDATA("# Sales",$AF$7,"Verdict",P18),0) -> 31 | R18: =IFERROR(GETPIVOTDATA("Avg $/SF",$AX$7,"Verdict",P18),0) -> 285.60207 | S18: =IFERROR(GETPIVOTDATA("Avg Size",$AX$7,"Verdict",P18),0) -> 20013.71 | T18: =IFERROR(GETPIVOTDATA("Min Price",$AX$7,"Verdict",P18),0) -> 1600000 | U18: =IFERROR(GETPIVOTDATA("Max Price",$AX$7,"Verdict",P18),0) -> 15500000 | V18: =IFERROR(GETPIVOTDATA("Total Volume",$AX$7,"Verdict",P18),0) -> 164653900 | AN18: 1505 Colonial Dr E | AO18: 7125000 | AP18: 184.85847 | AQ18: 38543
P19: Hospitals | Q19: =IFERROR(GETPIVOTDATA("# Sales",$AF$7,"Verdict",P19),0) -> 9 | R19: =IFERROR(GETPIVOTDATA("Avg $/SF",$AX$7,"Verdict",P19),0) -> 542.79918 | S19: =IFERROR(GETPIVOTDATA("Avg Size",$AX$7,"Verdict",P19),0) -> 14056 | T19: =IFERROR(GETPIVOTDATA("Min Price",$AX$7,"Verdict",P19),0) -> 1340800 | U19: =IFERROR(GETPIVOTDATA("Max Price",$AX$7,"Verdict",P19),0) -> 15500000 | V19: =IFERROR(GETPIVOTDATA("Total Volume",$AX$7,"Verdict",P19),0) -> 67023500 | AN19: 1511 SR 434 # 1001 E | AO19: 7000000 | AP19: 176.76768 | AQ19: 39600
X20: Year | Y20: (All) | AN20: 341 Maitland Av N | AO20: 7000000 | AP20: 152.45894 | AQ20: 45914
X21: Verdict | Y21: (All) | AN21: 954 Orlando Av S | AO21: 6349400 | AP21: 424 | AQ21: 14975
X22: County | Y22: (All) | AN22: 1781 Park Center Dr | AO22: 5913600 | AP22: 238.42277 | AQ22: 24803
X23: Size Bracket | Y23: (All) | AN23: 770 Concourse Pk | AO23: 5610000 | AP23: 395.90685 | AQ23: 14170
X24: Building Age | Y24: (All) | AN24: 1701 Park Center Dr | AO24: 5600000 | AP24: 171.09163 | AQ24: 32731
P25: TOP SALES | X25: Outlier | Y25: (All) | AN25: 600 North Blvd W | AO25: 5272900 | AP25: 263.645 | AQ25: 20000
P26: Address | Q26: County | R26: Price | S26: Size | T26: $/SF | U26: Category | V26: Tenant | AN26: 3480 Polynesian Isle Blvd | AO26: 5150000 | AP26: 412.66026 | AQ26: 12480
P27: =AN9 -> 7208 Sand Lake Rd W | Q27: =INDEX(SalesData[County],MATCH(P27,SalesData[Prpty Addr],0)) -> Orange | R27: =AO9 -> 15500000 | S27: =AQ9 -> 40052 | T27: =AP9 -> 386.9969 | U27: =INDEX(SalesData[Verdict],MATCH(P27,SalesData[Prpty Addr],0)) -> Multi-Tenant Medical | V27: =INDEX(SalesData[Current Tenant],MATCH(P27,SalesData[Prpty Addr],0)) -> 7208 Sand Lake - Office Complex | X27: Total Volume | Y27: Avg $/SF | Z27: Avg Price | AA27: Min Price | AB27: Max Price | AC27: Min $/SF | AD27: Max $/SF | AE27: Avg Size | AF27: Total Sales | AN27: 780 Concourse Pk | AO27: 5100000 | AP27: 389.31298 | AQ27: 13100
P28: =AN10 -> 9401 Summit Centre Wa | Q28: =INDEX(SalesData[County],MATCH(P28,SalesData[Prpty Addr],0)) -> Orange | R28: =AO10 -> 15500000 | S28: =AQ10 -> 10331 | T28: =AP10 -> 1500.3388 | U28: =INDEX(SalesData[Verdict],MATCH(P28,SalesData[Prpty Addr],0)) -> Hospitals | V28: =INDEX(SalesData[Current Tenant],MATCH(P28,SalesData[Prpty Addr],0)) -> **HCA Florida Maitland Emergency (Freestanding ER)** MEDICAL CENTER | X28: 497397799 | Y28: 303.31751 | Z28: 2550757.9 | AA28: 210000 | AB28: 33444697 | AC28: 45.304778 | AD28: 1500.3388 | AE28: 8917.5641 | AF28: 195 | AN28: 106 Boston # 100 Ave | AO28: 5050000 | AP28: 202.46161 | AQ28: 24943
P29: =AN11 -> 7009 Dr Phillips Bl | Q29: =INDEX(SalesData[County],MATCH(P29,SalesData[Prpty Addr],0)) -> Orange | R29: =AO11 -> 15000000 | S29: =AQ11 -> 23653 | T29: =AP11 -> 634.16903 | U29: =INDEX(SalesData[Verdict],MATCH(P29,SalesData[Prpty Addr],0)) -> Multi-Tenant Medical | V29: =INDEX(SalesData[Current Tenant],MATCH(P29,SalesData[Prpty Addr],0)) -> Belmart LLC Dr Phillips | AN29: 1605 Fairbanks Av W | AO29: 5000000 | AP29: 405.28492 | AQ29: 12337
P30: =AN12 -> 1745 Mills Av N | Q30: =INDEX(SalesData[County],MATCH(P30,SalesData[Prpty Addr],0)) -> Orange | R30: =AO12 -> 13200000 | S30: =AQ12 -> 28060 | T30: =AP12 -> 470.42053 | U30: =INDEX(SalesData[Verdict],MATCH(P30,SalesData[Prpty Addr],0)) -> Hospitals | V30: =INDEX(SalesData[Current Tenant],MATCH(P30,SalesData[Prpty Addr],0)) -> Central Florida Cardiology Group MEDICAL CENTER | AN30: 10131 Colonial Dr W | AO30: 4918100 | AP30: 281.58136 | AQ30: 17466
AN31: 1803 Park Center Dr | AO31: 4875000 | AP31: 221.49023 | AQ31: 22010
AN32: 1071 Sun Dr S | AO32: 4500000 | AP32: 247.25275 | AQ32: 18200
AN33: 2233 Lee Rd | AO33: 4216800 | AP33: 200.81913 | AQ33: 20998
AN34: 100 Waymont Ct | AO34: 4100000 | AP34: 227.77778 | AQ34: 18000
AN35: 2940 Maguire Rd | AO35: 4030000 | AP35: 494.5999 | AQ35: 8148
AN36: 1400 Orlando Av S | AO36: 3900000 | AP36: 185.51111 | AQ36: 21023
AN37: 750 Concourse Pk | AO37: 3570000 | AP37: 399.41821 | AQ37: 8938
AN38: 1000 E Irlo Bronson Memorial | AO38: 3552600 | AP38: 466.95584 | AQ38: 7608
AN39: 1301 Colonial Dr W | AO39: 3518200 | AP39: 396.64036 | AQ39: 8870
AN40: 788 Montgomery Av | AO40: 3499900 | AP40: 251.91823 | AQ40: 13893
AN41: 1000 Executive Dr | AO41: 3425000 | AP41: 267.82921 | AQ41: 12788
AN42: 9582 Colonial Dr W | AO42: 3400000 | AP42: 356.24476 | AQ42: 9544
... AN173: 32629 Blossom Ln | AO173: 210000 | AP173: 108.63942 | AQ173: 1933

Sheet Master
A1: *2020 to 2025 Office Sales Data - Sorted via Google Gemini and Claude. Manual sorting via Nico Bañez.
A2: VERIFIED VIA HUMAN (1-3 GRADE) | B2: Prpty Addr | C2: County | D2: Date Trnsfr | E2: Price | F2: $/SF | G2: Tot Ht Area | H2: Total Area | I2: Grantee | J2: Yr Built 1 | K2: Use Code | L2: Zoning | M2: Parcel ID | N2: Verdict | O2: Confidence | P2: Current Tenant | Q2: Evidence Link | R2: Google Map Link | S2: Evidence P2. | T2: Outlier? | U2: Reason | V2: Appraiser Link
A3: 3 | B3: 1049 Willa Springs Dr | C3: Seminole | D3: 2021/07 | E3: 2285000 | F3: =Table2[[#This Row],[Price]]/Table2[[#This Row],[Tot Ht Area]] -> 223.58121 | G3: 10220 | H3: 10220 | I3: 1049 Willa Springs LLC | J3: 2004 | K3: 19 | M3: 2130 24 508 0000 0060 | N3: Multi-Tenant Medical | O3: High | P3: Winter Springs Endodontics | Q3: https://www.loopnet.com/Listing/1049-Willa-Springs-Dr-Winter-Springs-FL/28712543/ | R3: https://www.google.com/maps/search/?api=1&query=1049+Willa+Springs+Dr+Seminole+FL | S3: Mixed use; figure out which unit if possible
A4: 3 | B4: 800 Fern Creek Av N | C4: Orange | D4: 2023/06 | E4: 1100000 | F4: =Table2[[#This Row],[Price]]/Table2[[#This Row],[Tot Ht Area]] -> 250.62657 | G4: 4389 | H4: 4697 | I4: Bk Realty Holding Company LLC | J4: 1956 | K4: 1700 | L4: ORLO1/ | M4: 2229 24 7060 03 010 | N4: Medical | O4: Medium | P4: Ferncreek Professional Center | Q4: https://www.tdscommercialre.com/properties | R4: https://www.google.com/maps/search/800+Fern+Creek+Av+N+Orange+FL
A5: 3 | B5: 1207 Daniels Rd | C5: Orange | D5: 2023/02 | E5: 1800000 | F5: =Table2[[#This Row],[Price]]/Table2[[#This Row],[Tot Ht Area]] -> 179.24716 | G5: 10042 | H5: 10618 | I5: Verax Daniels LLC | J5: 2024 | K5: 1900 | L5: WGC2 | M5: 2227 12 6496 28 002 | N5: Multi-Tenant Medical | O5: High | P5: Medical Office Development (Planned) | Q5: https://www.crexi.com/property-records/1207-DANIELS-WINTER-GARDEN-FL-34787/7098de1c88aa1c1be75e9a881083c5bb742ec848 | R5: https://www.google.com/maps/search/1207+Daniels+Rd,+FL
A6: 3 | B6: 54 Plant St E | C6: Orange | D6: 2025/03 | E6: 3200000 | F6: =Table2[[#This Row],[Price]]/Table2[[#This Row],[Tot Ht Area]] -> 893.85475 | G6: 3580 | H6: 4021 | I6: Anton Rx LLC | J6: 1983 | K6: 1900 | L6: WGC1 | M6: 2227 23 2888 01 040 | N6: Medical | O6: Medium | P6: Anton Rx (Pharmacy) | Q6: https://search.sunbiz.org/Inquiry/corporationsearch/SearchResultDetail?inquirytype=EntityName&directionType=Initial&searchNameOrder=ANTONRX%20L210004523910 | R6: https://www.google.com/maps/search/54+Plant+St+E,+FL | T6: Yes | U6: Extreme | V6: https://vgispublic.ocpafl.org/webmapjs/?pid=272223288801040
A7: 3 | B7: 20 Park Av S | C7: Orange | D7: 2021/06 | E7: 592000 | F7: =Table2[[#This Row],[Price]]/Table2[[#This Row],[Tot Ht Area]] -> 169.14286 | G7: 3500 | H7: 3850 | I7: Spark Office LLC | J7: 1996 | K7: 1700 | L7: APKMUD | M7: 2128 09 1972 02 591 | N7: Medical | O7: High | P7: Medical Buildout (Tenant Unconfirmed) | Q7: https://www.loopnet.com/Listing/20-S-Park-Ave-Apopka-FL/16369407/ | R7: https://www.google.com/maps/search/20+Park+Av+S,+FL
A8: 3 | B8: 404 Orange Blossom Tr W | C8: Orange | D8: 2025/05 | E8: 2000000 | F8: =Table2[[#This Row],[Price]]/Table2[[#This Row],[Tot Ht Area]] -> 351.61744 | G8: 5688 | H8: 5723 | I8: Galvan Victor M | J8: 1986 | K8: 1700 | L8: APKMUD | M8: 2128 09 7544 02 030 | N8: Medical | O8: Medium | P8: South Apopka Medical Office (Vacant/Leasing) | Q8: https://www.loopnet.com/Listing/404-W-Orange-Blossom-Tr-Apopka-FL/28471952/ | R8: https://www.google.com/maps/search/404+Orange+Blossom+Tr+W,+FL
A9: 3 | B9: 566 Ocoee Commerce Pk | C9: Orange | D9: 2025/10 | E9: 100 | F9: =Table2[[#This Row],[Price]]/Table2[[#This Row],[Tot Ht Area]] -> 0.019968051 | G9: 5008 | H9: 5182 | I9: 566 596 Ocoee Commerce Pkwy LLC | J9: 2009 | K9: 1900 | L9: OCOC2 | M9: 2228 29 6143 00 050 | N9: Medical | O9: High | P9: Vacant Medical/Professional Buildout | Q9: https://www.loopnet.com/Listing/566-Ocoee-Commerce-Pky-Ocoee-FL/38309702/ | R9: https://www.google.com/maps/search/566+Ocoee+Commerce+Pk,+FL | T9: Yes
A10: 3 | B10: 2702 Rew Ci | C10: Orange | D10: 2021/11 | E10: 1224900 | F10: =Table2[[#This Row],[Price]]/Table2[[#This Row],[Tot Ht Area]] -> 236.14806 | G10: 5187 | H10: 5571 | I10: Marcast Properties & Management LLC | J10: 2003 | K10: 1900 | L10: OCOI1 | M10: 2228 29 9158 00 020 | N10: Medical | O10: Medium | P10: Vacant Medical/Office Space | Q10: https://www.loopnet.com/Listing/2702-Rew-Cir-Ocoee-FL/20805631/ | R10: https://www.google.com/maps/search/2702+Rew+Ci,+FL
A11: 3 | B11: 5749 Westgate Dr | C11: Orange | D11: 2025/03 | E11: 6850000 | F11: =Table2[[#This Row],[Price]]/Table2[[#This Row],[Tot Ht Area]] -> 155.79158 | G11: 43969 | H11: 47089 | I11: Clarcona Land Development LLC | J11: 2008 | K11: 1800 | L11: ORLAC1 | M11: 2228 36 4949 01 000 | N11: Multi-Tenant Medical | O11: High | P11: Vacant Medical/Wellness Buildout | Q11: https://www.bosshardtrealty.com/listing/O6296860/5749-westgate-drive-orlando-fl-32835/ | R11: https://www.google.com/maps/search/5749+Westgate+Dr,+FL | T11: Yes | U11: Not all medical | V11: https://vgispublic.ocpafl.org/webmapjs/?pid=282236494901000
A12: 3 | B12: 7232 Sand Lake Rd W | C12: Orange | D12: 2025/07 | E12: 7500000 | F12: =Table2[[#This Row],[Price]]/Table2[[#This Row],[Tot Ht Area]] -> 441.82622 | G12: 16975 | H12: 17657 | I12: Andres Health Holdings LLC | J12: 1983 | K12: 1800 | L12: ORGC1 | M12: 2328 35 0000 00 016 | N12: Multi-Tenant Medical | O12: Medium | P12: Andres Health Holdings (Tenant Unconfirmed) | Q12: https://www.loopnet.com/Listing/7232-Sand-Lake-Rd-Orlando-FL/31873125/ | R12: https://www.google.com/maps/search/7232+Sand+Lake+Rd+W,+FL
A13: 3 | B13: 926 Maitland Av N | C13: Orange | D13: 2023/06 | E13: 720000 | F13: =Table2[[#This Row],[Price]]/Table2[[#This Row],[Tot Ht Area]] -> 364.37247 | G13: 1976 | H13: 2087 | I13: Dream Dental Properties LLC | J13: 1957 | K13: 1900 | L13: MTLMX | M13: 2129 25 0000 00 021 | N13: Medical | O13: High | P13: Vacant "Turnkey" Medical Buildout | Q13: https://www.ronsellsthebeach.com/property-search/detail/240/O6341577/926-n-maitland-ave-maitland-fl-32751/ | R13: https://www.google.com/maps/search/926+Maitland+Av+N,+FL
A14: 3 | B14: 2200 Lee Rd | C14: Orange | D14: 2022/03 | E14: 800000 | F14: =Table2[[#This Row],[Price]]/Table2[[#This Row],[Tot Ht Area]] -> 322.58065 | G14: 2480 | H14: 2673 | I14: Aarr Florida Investments LLC | J14: 1976 | K14: 1900 | L14: WPO1 | M14: 2229 02 8004 01 004 | N14: Medical | O14: High | P14: Vacant Medical Buildout (Former Dentist) | Q14: https://www.loopnet.com/Listing/2200-Lee-Rd-Winter-Park-FL/24836441/ | R14: https://www.google.com/maps/search/2200+Lee+Rd,+FL
A15: 3 | B15: 2306 Lee Rd | C15: Orange | D15: 2022/04 | E15: 100 | F15: =Table2[[#This Row],[Price]]/Table2[[#This Row],[Tot Ht Area]] -> 0.044326241 | G15: 2256 | H15: 2289 | I15: Naseem Bano Latif Revocable Trust & Latif Mohammad A | J15: 1984 | K15: 1900 | L15: WPO1 | M15: 2229 02 8008 01 181 | N15: Medical | O15: High | P15: Vacant Medical Buildout (Plumbed Exam Rooms) | Q15: Used to be Longwood Internal Medicine | R15: https://www.google.com/maps/search/2306+Lee+Rd,+FL | T15: Yes
A16: 3 | B16: 1010 Arthur Av | C16: Orange | D16: 2022/05 | E16: 925000 | F16: =Table2[[#This Row],[Price]]/Table2[[#This Row],[Tot Ht Area]] -> 262.41135 | G16: 3525 | H16: 3525 | I16: A Swart Properties LLC | J16: 1984 | K16: 1900 | L16: ORLMU1 | M16: 2229 10 8828 04 150 | N16: Medical | O16: High | P16: The Spa Orlando (Massage & Wellness) | Q16: Used to be https://www.tolbirth.com/ | R16: https://www.google.com/maps/search/1010+Arthur+Av+Orange+FL
A17: 3 | B17: 205 Eola Dr S | C17: Orange | D17: 2020/02 | E17: 3325000 | F17: =Table2[[#This Row],[Price]]/Table2[[#This Row],[Tot Ht Area]] -> 433.9598 | G17: 7662 | H17: 8163 | I17: Whitestone Legacy LLC | J17: 1945 | K17: 1700 | L17: ORLPD/ | M17: 2229 25 9320 01 060 | N17: Medical | O17: Medium | P17: Vacant "Office/Medical" for Sale | Q17: https://www.crexi.com/properties/2285495/florida-8000-sf-office-for-sale-in-downtown-orlando | R17: https://www.google.com/maps/search/205+Eola+Dr+S+Orange+FL
A18: 3 | B18: 1701 1st St W | C18: Seminole | D18: 2024/10 | E18: 940000 | F18: =Table2[[#This Row],[Price]]/Table2[[#This Row],[Tot Ht Area]] -> 109.98011 | G18: 8547 | H18: 8547 | I18: 1701 West First Street LLC | J18: 2005 | K18: 19 | M18: 1930 25 5AG 0320 0000 | N18: Medical | O18: Medium | P18: Vacant "2nd Gen Medical" for Lease (used to be DaVita Dialysis) | Q18: https://www.loopnet.com/Listing/1701-W-1st-St-Sanford-FL/28259426/ | R18: https://www.google.com/maps?q=1701+1st+St+W+Seminole,+FL
A19: 3 | B19: 902 25th St W | C19: Seminole | D19: 2025/07 | E19: 100 | F19: =Table2[[#This Row],[Price]]/Table2[[#This Row],[Tot Ht Area]] -> 0.047778309 | G19: 2093 | H19: 2093 | I19: Honu Molar Building LLC | J19: 1978 | K19: 19 | M19: 1930 36 524 0900 0010 | N19: Medical | O19: Medium | P19: Dr. Randall C. Brown, DMD | Q19: https://search.sunbiz.org/Inquiry/CorporationSearch/ByName | R19: https://maps.google.com/?cid=1507629469026860988&g_mp=Cidnb29nbGUubWFwcy5wbGFjZXMudjEuUGxhY2VzLlNlYXJjaFRleHQ | T19: Yes
A20: 3 | B20: 795 Primera Blvd | C20: Seminole | D20: 2020/12 | E20: 2375000 | F20: =Table2[[#This Row],[Price]]/Table2[[#This Row],[Tot Ht Area]] -> 220.33584 | G20: 10779 | H20: 10779 | I20: Medwins Realty LLC | J20: 2007 | K20: 1905 | M20: 2030 07 522 0600 0000 | N20: Multi-Tenant Medical | O20: Medium | Q20: https://www.loopnet.com/Listing/795-Primera-Blvd-Lake-Mary-FL/15799815/ | R20: https://www.google.com/maps?q=795+Primera+Blvd+Seminole,+FL
A21: 3 | B21: 261 Airport Blvd E | C21: Seminole | D21: 2021/04 | E21: 600000 | F21: =Table2[[#This Row],[Price]]/Table2[[#This Row],[Tot Ht Area]] -> 173.81228 | G21: 3452 | H21: 3452 | I21: Shephard Max Properties LLC | J21: 1980 | K21: 19 | M21: 2030 12 300 012H 0000 | N21: Medical | O21: Medium | P21: Vacant Medical Office (For Sale) | Q21: https://www.realty.com/commercial-listings/361178951/261-E-Airport-Boulevard-Sanford-FL-32773 | R21: https://www.google.com/maps?q=261+Airport+Blvd+E+Seminole,+FL
A22: 3 | B22: 32032 Burleigh Blvd W | C22: Lake | D22: 2020/09 | E22: 670000 | F22: =Table2[[#This Row],[Price]]/Table2[[#This Row],[Tot Ht Area]] -> 135.40825 | G22: 4948 | H22: 5250 | I22: Burleigh Getting Started LLC | J22: 1977 | K22: 1900 | M22: 1926 29 0700 000 00002 | N22: Medical | O22: Medium | P22: Vacant Dental Office (Built-out) | Q22: https://www.loopnet.com/Listing/320-W-Burleigh-Blvd-Tavares-FL/18724440/ | R22: https://www.google.com/maps/search/32032+Burleigh+Blvd+W+Tavares+FL
A23: 3 | B23: 6909 Old Hwy 441 | C23: Orange | D23: 2021/07 | E23: 3000000 | F23: =Table2[[#This Row],[Price]]/Table2[[#This Row],[Tot Ht Area]] -> 62.138818 | G23: 48279 | H23: 55177 | I23: Mount Fpl LLC | J23: 2008 | K23: 1900 | L23: ORGPD | M23: 2027 05 3095 01 000 | N23: Multi-Tenant Medical | O23: High | P23: Multi-Tenant (Endocrinology / Dialysis) | Q23: https://www.cityfeet.com/cont/listing/6909-old-highway-441-mount-dora-fl-32757/cs23886257 | R23: https://www.google.com/maps/search/6909+Old+Hwy+441,+FL | T23: Yes | U23: Multi tenant sale/ bad Cap Rate? | V23: https://vgispublic.ocpafl.org/webmapjs/?pid=272005309501000
A24: 3 | B24: 1200 Plant St E | C24: Orange | D24: 2022/04 | E24: 100 | F24: =Table2[[#This Row],[Price]]/Table2[[#This Row],[Tot Ht Area]] -> 0.0045390586 | G24: 22031 | H24: 26965 | I24: Hwo Holdings LLC | J24: 2020 | K24: 1800 | L24: WGCAPU | M24: 2227 12 6496 04 001 | N24: Medical | O24: High | P24: Healthy West Orange / Community Hub | Q24: https://www.cwgdn.com/666/Central-Florida-Resources | R24: https://www.google.com/maps/search/1200+Plant+St+E,+FL | T24: Yes
A25: 3 | B25: 14835 Colonial Dr W | C25: Orange | D25: 2021/05 | E25: 344600 | F25: =Table2[[#This Row],[Price]]/Table2[[#This Row],[Tot Ht Area]] -> 117.37057 | G25: 2936 | H25: 3048 | I25: Life Conduit LLC | J25: 2021 | K25: 1900 | L25: WGC2 | M25: 2227 22 7670 03 000 | N25: Medical | O25: High | P25: Wholistic Dental Care | Q25: https://search.sunbiz.org/Inquiry/corporationsearch/SearchResultDetail?inquirytype=EntityName&directionType=Initial&searchNameOrder=WHOLISTICDENTALCAREWINTERGARDE%20L210000916830 | R25: https://www.google.com/maps/search/14835+Colonial+Dr+W,+FL
A26: 3 | B26: 741 Dillard St S | C26: Orange | D26: 2021/03 | E26: 900000 | F26: =Table2[[#This Row],[Price]]/Table2[[#This Row],[Tot Ht Area]] -> 152.54237 | G26: 5900 | H26: 6304 | I26: 741 South Dillard LLC | J26: 1970 | K26: 1900 | L26: WGC2 | M26: 2227 23 6504 07 072 | N26: Medical | O26: High | P26: Ability Rehabilitation (Physical Therapy) | Q26: https://abilityrehabilitation.com/winter-garden-clinic/ | R26: https://www.google.com/maps/search/741+Dillard+St+S,+FL
A27: 3 | B27: 950 Dillard St S | C27: Orange | D27: 2021/10 | E27: 1365500 | F27: =Table2[[#This Row],[Price]]/Table2[[#This Row],[Tot Ht Area]] -> 410.30649 | G27: 3328 | H27: 4909 | I27: 950 Dillard LLC | J27: 1998 | K27: 1700 | L27: WGC2 | M27: 2227 23 7824 00 260 | N27: Medical | O27: High | P27: Gentiva Hospice | Q27: https://allianceforcareathome.org/nahc_provider/gentiva-hospice-winter-garden/ | R27: https://www.google.com/maps/search/950+Dillard+St+S,+FL
A28: 3 | B28: 12323 Colonial Dr W | C28: Orange | D28: 2021/02 | E28: 1900000 | F28: =Table2[[#This Row],[Price]]/Table2[[#This Row],[Tot Ht Area]] -> 82.691387 | G28: 22977 | H28: 25035 | I28: Verax Wg LLC | J28: 2022 | K28: 1900 | L28: WGPCD | M28: 2227 24 6747 04 000 | N28: Multi-Tenant Medical | O28: High | P28: Winter Garden ObGyn / ENT & Plastic Surgery | Q28: https://wgobgyn.com/ | R28: https://www.google.com/maps/search/12323+Colonial+Dr+W,+FL | T28: Yes | U28: You guys now here? | V28: https://vgispublic.ocpafl.org/webmapjs/?pid=272224674704000
A29: 3 | B29: 12200 Colonial Dr W | C29: Orange | D29: 2021/11 | E29: 7600000 | F29: =Table2[[#This Row],[Price]]/Table2[[#This Row],[Tot Ht Area]] -> 246.90556 | G29: 30781 | H29: 32341 | I29: 12200 Colonial LLC | J29: 2000 | K29: 1800 | L29: WGC2 | M29: 2227 25 0000 00 035 | N29: Multi-Tenant Medical | O29: High | P29: Oral Surgery Center Of West Orlando | Q29: https://www.carecredit.com/doctor-locator/winter-garden-fl/oral-surgery-center-of-west-orlando-pqr222/ | R29: https://www.google.com/maps/search/12200+Colonial+Dr+W,+FL
A30: 3 | B30: 15650 Colonial Dr W | C30: Orange | D30: 2021/03 | E30: 1725000 | F30: =Table2[[#This Row],[Price]]/Table2[[#This Row],[Tot Ht Area]] -> 347.78226 | G30: 4960 | H30: 5608 | I30: Harmony Dental Holdings LLC | J30: 2020 | K30: 1900 | L30: WGC2 | M30: 2227 28 0000 00 001 | N30: Medical | O30: High | P30: Harmony Dental Care / Oakland Pediatric Dentistry | Q30: https://www.carecredit.com/doctor-locator/winter-garden-fl/harmony-dental-care-633hqp/ | R30: https://www.google.com/maps/search/15650+Colonial+Dr+W,+FL
A31: 3 | B31: 5802 Citrus Village Bl | C31: Orange | D31: 2022/11 | E31: 900000 | F31: =Table2[[#This Row],[Price]]/Table2[[#This Row],[Tot Ht Area]] -> 253.52113 | G31: 3550 | H31: 3733 | I31: Med Consult One Properties LLC | J31: 2024 | K31: 1900 | L31: ORGPD | M31: 2327 20 2717 02 000 | N31: Medical | O31: High | P31: Horizons OBGYN & Aesthetics | Q31: https://biz.wochamber.com/list/member/horizons-obgyn-30930 | R31: https://www.google.com/maps/search/5802+Citrus+Village+Bl,+FL
A32: 3 | B32: 11625 Lachlan Ln | C32: Orange | D32: 2025/06 | E32: 3473802 | F32: =Table2[[#This Row],[Price]]/Table2[[#This Row],[Tot Ht Area]] -> 915.12171 | G32: 3796 | H32: 3922 | I32: Cl Westside Shoppes Fl LLC | J32: 2017 | K32: 1900 | L32: ORGPD | M32: 2327 25 5839 02 000 | N32: Medical | O32: High | P32: Dental Care at Westside Shoppes | Q32: https://dentalcareatwestsideshoppes.com/ | R32: https://www.google.com/maps/search/11625+Lachlan+Ln,+FL | T32: Yes | U32: Extreme | V32: https://vgispublic.ocpafl.org/webmapjs/?pid=272325583902000
A33: 3 | B33: 1112 Rock Springs Rd | C33: Orange | D33: 2020/12 | E33: 100 | F33: =Table2[[#This Row],[Price]]/Table2[[#This Row],[Tot Ht Area]] -> 0.036363636 | G33: 2750 | H33: 2876 | I33: Pta Properties LLC | J33: 2012 | K33: 1900 | L33: APKO | M33: 2028 33 0000 00 067 | N33: Medical | O33: High | P33: Arbor Dentistry | Q33: https://fun4seminolekids.com/Health-Resources/Family-Dental-Practices/Arbor-Dentistry/View-details | R33: https://www.google.com/maps/search/1112+Rock+Springs+Rd,+FL | T33: Yes
A34: 3 | B34: 450 Errol Pk | C34: Orange | D34: 2024/09 | E34: 448100 | F34: =Table2[[#This Row],[Price]]/Table2[[#This Row],[Tot Ht Area]] -> 130.79393 | G34: 3426 | H34: 3590 | I34: 6Gamms LLC | J34: 1981 | K34: 1900 | L34: APKCC | M34: 2128 05 0000 00 016 | N34: Medical | O34: High | P34: A Soft Touch in Family Dental Care | Q34: https://www.patientconnect365.com/Dentists/Florida/Apopka/32712/A_Soft_Touch_in_Family_Dental_Care__Dr_John_Gammichia_kvo8lh | R34: https://www.google.com/maps/search/450+Errol+Pk,+FL
A35: 3 | B35: 2115 Orange Blossom Tr W | C35: Orange | D35: 2024/05 | E35: 3500000 | F35: =Table2[[#This Row],[Price]]/Table2[[#This Row],[Tot Ht Area]] -> 591.01655 | G35: 5922 | H35: 6039 | I35: Fla Land Holdings Three LLC | J35: 2023 | K35: 1900 | L35: ORGC1 | M35: 2128 06 0000 00 047 | N35: Hospitals | O35: High | P35: Sanitas Medical Center | Q35: https://www.mysanitas.com/en/fl/sanitas-apopka | R35: https://www.google.com/maps/search/2115+Orange+Blossom+Tr+W,+FL | T35: Yes | U35: Hospital, but too small to go under our "large buildings category" | V35: https://vgispublic.ocpafl.org/webmapjs/?pid=282106000000047
A36: 3 | B36: 108 Park Av S | C36: Orange | D36: 2023/10 | E36: 475000 | F36: =Table2[[#This Row],[Price]]/Table2[[#This Row],[Tot Ht Area]] -> 102.81385 | G36: 4620 | H36: 4745 | I36: Dada Eyecare Holdings LLC | J36: 2024 | K36: 1900 | L36: APKMUD | M36: 2128 09 0196 20 063 | N36: Medical | O36: High | P36: Essential Eye Care & Optical | Q36: https://www.essentialeyecareoptical.com/hours-location/ | R36: https://www.google.com/maps/search/108+Park+Av+S,+FL
A37: 3 | B37: 416 Main St E | C37: Orange | D37: 2024/05 | E37: 585000 | F37: =Table2[[#This Row],[Price]]/Table2[[#This Row],[Tot Ht Area]] -> 127.45098 | G37: 4590 | H37: 5490 | I37: Collins Construction Consulting Hold | J37: 1966 | K37: 1700 | L37: APKMUD | M37: 2128 10 0000 00 051 | N37: Medical | O37: High | P37: Owner-Occupied Dental Office / Beauty Salon | Q37: https://www.kwsouthshore.com/listings/listing/416-e-main-st-apopka-fl--O6171656/ | R37: https://www.google.com/maps/search/416+Main+St+E,+FL
A38: 3 | B38: 125 Park Av S | C38: Orange | D38: 2020/07 | E38: 100 | F38: =Table2[[#This Row],[Price]]/Table2[[#This Row],[Tot Ht Area]] -> 0.031162356 | G38: 3209 | H38: 3283 | I38: Dean A Behner And Ingrid J Behner Re Dean Allen Behner Trustee | J38: 1960 | K38: 1900 | L38: APKMUD | M38: 2128 10 0198 31 740 | N38: Medical | O38: High | P38: WellMed at Apopka | Q38: https://www.tenantbase.com/us/building/217796 | R38: https://www.google.com/maps/search/125+Park+Av+S,+FL | T38: Yes
A39: 3 | B39: 175 Main St E | C39: Orange | D39: 2023/04 | E39: 2650000 | F39: =Table2[[#This Row],[Price]]/Table2[[#This Row],[Tot Ht Area]] -> 201.67428 | G39: 13140 | H39: 14276 | I39: Jareag 175 LLC | J39: 2006 | K39: 1800 | L39: APKMUD | M39: 2128 10 8643 00 030 | N39: Multi-Tenant Medical | O39: High | P39: Gentry Building | Q39: https://www.loopnet.com/Listing/175-E-Main-St-Apopka-FL/31346793/ | R39: https://www.google.com/maps/search/175+Main+St+E,+FL
A40: 3 | B40: 2605 Ocoee Apopka Rd | C40: Orange | D40: 2023/05 | E40: 1140000 | F40: =Table2[[#This Row],[Price]]/Table2[[#This Row],[Tot Ht Area]] -> 276.90066 | G40: 4117 | H40: 5455 | I40: Y&L Holdings LLC | J40: 2009 | K40: 1900 | L40: OCOPUD | M40: 2228 06 2856 01 000 | N40: Medical | O40: High | P40: Elegantly Dental | Q40: https://www.elegantlydental.com/ocoee-fl/ | R40: https://www.google.com/maps/search/2605+Ocoee+Apopka+Rd,+FL
A41: 3 | B41: 6394 Silver Star Rd | C41: Orange | D41: 2020/04 | F41: =Table2[[#This Row],[Price]]/Table2[[#This Row],[Tot Ht Area]] -> 0 | G41: 16200 | H41: 16248 | I41: 6394 Silver Star LLC | J41: 2008 | K41: 1700 | L41: ORGC1 | M41: 2228 13 5844 00 413 | N41: Medical | O41: High | P41: Octapharma Plasma | Q41: https://www.octapharmaplasma.com/plasma-donation/orlando-fl-449/ | R41: https://www.google.com/maps/search/6394+Silver+Star+Rd,+FL
A42: 3 | B42: 6388 Silver Star Rd | C42: Orange | D42: 2021/01 | E42: 100 | F42: =Table2[[#This Row],[Price]]/Table2[[#This Row],[Tot Ht Area]] -> 0.0038922622 | G42: 25692 | H42: 27809 | I42: Rupert (Bvi) Limited Partnership | J42: 1986 | K42: 1800 | L42: ORGC1 | M42: 2228 13 5844 00 420 | N42: Medical | O42: High | P42: Agape's Way Home Health Care | Q42: https://quality.healthfinder.fl.gov/Facility-Provider/Profile/?LID=484031 | R42: https://www.google.com/maps/search/6388+Silver+Star+Rd,+FL | T42: Yes
A43: 3 | B43: 11001 Colonial Dr W | C43: Orange | D43: 2021/11 | E43: 1650000 | F43: =Table2[[#This Row],[Price]]/Table2[[#This Row],[Tot Ht Area]] -> 230.06135 | G43: 7172 | H43: 7435 | I43: Ocoee Medical Developers LLC | J43: 2022 | K43: 1900 | L43: OCOC3 | M43: 2228 19 0000 00 024 | N43: Medical | O43: High | P43: AdventHealth Centra Care Ocoee | Q43: https://biz.wochamber.com/list/member/adventhealth-centra-care-ocoee-30983 | R43: https://www.google.com/maps/search/11001+Colonial+Dr+W,+FL
A44: 3 | B44: 788 Montgomery Av | C44: Orange | D44: 2021/01 | E44: 3499900 | F44: =Table2[[#This Row],[Price]]/Table2[[#This Row],[Tot Ht Area]] -> 251.91823 | G44: 13893 | H44: 16012 | I44: Greater Vision Investment Group LLC | J44: 2011 | K44: 1800 | L44: OCOPUD | M44: 2228 20 6148 05 000 | N44: Multi-Tenant Medical | O44: Medium | P44: GREATER VISION HEALTHCARE SERVICES LLC | Q44: https://quality.healthfinder.fl.gov/Facility-Provider/Profile/?LID=411051 | R44: https://www.google.com/maps/search/788+Montgomery+Av,+FL
A45: 3 | B45: 9582 Colonial Dr W | C45: Orange | D45: 2024/12 | E45: 3400000 | F45: =Table2[[#This Row],[Price]]/Table2[[#This Row],[Tot Ht Area]] -> 356.24476 | G45: 9544 | H45: 10056 | I45: Optima Imaging Centers Of Florida Ll | J45: 2007 | K45: 1900 | L45: OCOPS | M45: 2228 21 6328 00 020 | N45: Multi-Tenant Medical | O45: High | P45: Optima Diagnostic Imaging | Q45: https://search.sunbiz.org/Inquiry/CorporationSearch/SearchResults?InquiryType=EntityName&InquiryDirectionType=ForwardRecord&SearchTerm=OPTIMA%20HOME%20INSPECTIONS%2C%20LLC&SearchNameOrder=OPTIMAILLABORATORIES%20G821190&ListNameOrder=OPTIMAHOMESERVICES%20P990000974750&Detail=FL.DOS.Corporations.Shared.Contracts.FilingRecord | R45: https://www.google.com/maps/search/9582+Colonial+Dr+W,+FL
A46: 3 | B46: 724 Charles St | C46: Orange | D46: 2022/05 | E46: 649000 | F46: =Table2[[#This Row],[Price]]/Table2[[#This Row],[Tot Ht Area]] -> 224.56747 | G46: 2890 | H46: 2906 | I46: C & Jc Electrical Services Inc | J46: 2003 | K46: 1900 | L46: ORGPO | M46: 2228 24 6240 01 360 | N46: Medical | O46: High | P46: PIECAR COMMUNITY HEALTH CARE LLC | Q46: https://quality.healthfinder.fl.gov/Facility-Provider/Profile/?LID=517292 | R46: https://www.google.com/maps/search/724+Charles+St,+FL
A47: 3 | B47: 836 Paul St | C47: Orange | D47: 2022/06 | E47: 100 | F47: =Table2[[#This Row],[Price]]/Table2[[#This Row],[Tot Ht Area]] -> 0.036231884 | G47: 2760 | H47: 2760 | I47: Florida Neonatology Group Pediatric | J47: 1976 | K47: 1900 | L47: ORGPO | M47: 2228 24 6240 05 250 | N47: Medical | O47: High | P47: Pediatric Medical Center | Q47: https://pediatricmedicalcenter.org/ | R47: https://www.google.com/maps/search/836+Paul+St,+FL | T47: Yes
A48: 3 | B48: 596 Ocoee Commerce Pk | C48: Orange | D48: 2025/10 | E48: 100 | F48: =Table2[[#This Row],[Price]]/Table2[[#This Row],[Tot Ht Area]] -> 0.013974287 | G48: 7156 | H48: 7464 | I48: 566 596 Ocoee Commerce Pkwy LLC | J48: 2002 | K48: 1900 | L48: OCOC2 | M48: 2228 29 6143 00 060 | N48: Medical | O48: High | P48: West Orange Orthopaedics & Sports Medicine | Q48: https://www.westorangeorthopaedics.com/ | R48: https://www.google.com/maps/search/596+Ocoee+Commerce+Pk,+FL | T48: Yes
A49: 3 | B49: 2940 Maguire Rd | C49: Orange | D49: 2022/04 | E49: 4030000 | F49: =Table2[[#This Row],[Price]]/Table2[[#This Row],[Tot Ht Area]] -> 494.5999 | G49: 8148 | H49: 8250 | I49: 2940 Maguire Road LLC | J49: 2018 | K49: 1900 | L49: OCOPUD | M49: 2228 32 5475 00 040 | N49: Medical | O49: High | P49: PremierMED Family Practice & Sports Medicine | Q49: https://www.premierfsm.com/contact/ocoee/ | R49: https://www.google.com/maps/search/2940+Maguire+Rd,+FL
A50: 3 | B50: 6404 Old Winter Garden Rd | C50: Orange | D50: 2023/05 | E50: 965900 | F50: =Table2[[#This Row],[Price]]/Table2[[#This Row],[Tot Ht Area]] -> 148.41733 | G50: 6508 | H50: 6724 | I50: Maximized Living Health Centers LLC | J50: 2008 | K50: 1800 | L50: ORGC3 | M50: 2228 36 6416 03 010 | N50: Medical | O50: High | P50: Maximized Living Health Center (Chiropractic) | Q50: https://www.maxliving.com/clinic/maxliving-chiropractic-orlando | R50: https://www.google.com/maps/search/6404+Old+Winter+Garden+Rd,+FL
A51: 3 | B51: 1803 Park Center Dr | C51: Orange | D51: 2023/07 | E51: 4875000 | F51: =Table2[[#This Row],[Price]]/Table2[[#This Row],[Tot Ht Area]] -> 221.49023 | G51: 22010 | H51: 22046 | I51: Apoli & Javi Realty LLC | J51: 1990 | K51: 1800 | L51: ORLAC2 | M51: 2328 01 6519 00 020 | N51: Multi-Tenant Medical | O51: High | P51: SaludVIP Orlando | Q51: https://getvipcare.com/our-locations/orlando-metro-west | R51: https://www.google.com/maps/search/1803+Park+Center+Dr,+FL
A52: 3 | B52: 5940 Turkey Lake Rd | C52: Orange | D52: 2022/07 | E52: 100 | F52: =Table2[[#This Row],[Price]]/Table2[[#This Row],[Tot Ht Area]] -> 0.029824038 | G52: 3353 | H52: 3581 | I52: Rampi Richard C & Rampi Maria Patricia | J52: 2002 | K52: 1900 | L52: ORGPO | M52: 2328 23 0000 00 011 | N52: Medical | O52: High | P52: Venetian Pointe Dentistry | Q52: https://venetian-pointe-dentistry.wheree.com/ | R52: https://www.google.com/maps/search/5940+Turkey+Lake+Rd,+FL | T52: Yes
A53: 3 | B53: 7009 Dr Phillips Bl | C53: Orange | D53: 2025/07 | E53: 15000000 | F53: =Table2[[#This Row],[Price]]/Table2[[#This Row],[Tot Ht Area]] -> 634.16903 | G53: 23653 | H53: 23834 | I53: Adventist Health System/Sunbelt Inc Attn Adventhealth Accounting Dept | J53: 2005 | K53: 1800 | L53: ORGPO | M53: 2328 26 0000 00 040 | N53: Multi-Tenant Medical | O53: High | P53: Belmart LLC Dr Phillips | Q53: https://www.carecredit.com/doctor-locator/orlando-fl/belmart-llc-dr-phillips-265cdx/ | R53: https://www.google.com/maps/search/7009+Dr+Phillips+Bl,+FL
A54: 3 | B54: 8200 World Center Dr | C54: Orange | D54: 2023/02 | E54: 2000000 | F54: =Table2[[#This Row],[Price]]/Table2[[#This Row],[Tot Ht Area]] -> 301.70463 | G54: 6629 | H54: 7252 | I54: J&G Investment Group Vc I LLC | J54: 1992 | K54: 1900 | L54: ORGPD | M54: 2428 34 3857 00 011 | N54: Medical | O54: High | P54: BUENA VISTA URGENT CARE | Q54: https://quality.healthfinder.fl.gov/Facility-Provider/Profile/?LID=374972 | R54: https://www.google.com/maps/search/8200+World+Center+Dr,+FL
A55: 3 | B55: 100 Sybelia Av E | C55: Orange | D55: 2021/12 | E55: 7750000 | F55: =Table2[[#This Row],[Price]]/Table2[[#This Row],[Tot Ht Area]] -> 179.94799 | G55: 43068 | H55: 44902 | I55: Ws Properties Of Orange County LLC | J55: 1982 | K55: 1800 | L55: MTLMX | M55: 2129 25 0000 00 035 | N55: Multi-Tenant Medical | O55: High | P55: Nemours Children's Health | Q55: https://www.nemours.org/locations/florida-primary-care-pediatrician-maitland.html | R55: https://www.google.com/maps/search/100+Sybelia+Av+E,+FL
A56: 3 | B56: 238 Orlando Av S | C56: Orange | D56: 2023/12 | E56: 3000000 | F56: =Table2[[#This Row],[Price]]/Table2[[#This Row],[Tot Ht Area]] -> 713.43639 | G56: 4205 | H56: 5986 | I56: Fisher Eye Properties LLC | J56: 2007 | K56: 1900 | L56: MTLDM | M56: 2129 25 6516 03 020 | N56: Medical | O56: High | P56: Vision Source Maitland | Q56: https://www.carecredit.com/doctor-locator/maitland-fl/vision-source-maitland-876tpt/ | R56: https://www.google.com/maps/search/238+Orlando+Av+S,+FL | T56: Yes | V56: https://vgispublic.ocpafl.org/webmapjs/?pid=292125651503020
A57: 3 | B57: 541 Horatio Av E | C57: Orange | D57: 2023/07 | E57: 3080000 | F57: =Table2[[#This Row],[Price]]/Table2[[#This Row],[Tot Ht Area]] -> 283.03621 | G57: 10882 | H57: 11431 | I57: Anjali 670 LLC | J57: 1977 | K57: 1700 | L57: MTLDM | M57: 2129 25 6516 05 030 | N57: Multi-Tenant Medical | O57: High | P57: Premier Cardiology & Vascular Associates | Q57: https://www.premiercardiology.net/ | R57: https://www.google.com/maps/search/541+Horatio+Av+E,+FL
A58: 3 | B58: 543 Wymore Rd N | C58: Orange | D58: 2020/08 | E58: 100 | F58: =Table2[[#This Row],[Price]]/Table2[[#This Row],[Tot Ht Area]] -> 0.0090497738 | G58: 11050 | H58: 11580 | I58: Maitland Ob LLC 1/2 Int & Deno Dikeou Trust 1/2 Int | J58: 2007 | K58: 1700 | L58: MTLMX | M58: 2129 26 0000 00 023 | N58: Medical | O58: High | P58: Synergy HomeCare | Q58: https://web.hcaoa.org/Home-Care-Provider/SYNERGY-HomeCare-Greater-Orlando-14958 | R58: https://www.google.com/maps/search/543+Wymore+Rd+N,+FL | T58: Yes
A59: 3 | B59: 9401 Summit Centre Wa | C59: Orange | D59: 2021/10 | E59: 15500000 | F59: =Table2[[#This Row],[Price]]/Table2[[#This Row],[Tot Ht Area]] -> 1500.3388 | G59: 10331 | H59: 12626 | I59: Oviedo Medical Center LLC | J59: 2024 | K59: 1900 | L59: MTLPD | M59: 2129 28 5499 03 000 | N59: Hospitals | O59: High | P59: HCA Florida Maitland Emergency (Freestanding ER) | Q59: https://www.hcafloridahealthcare.com/locations/maitland-emergency | R59: https://www.google.com/maps/search/9401+Summit+Centre+Wa,+FL
A60: 3 | B60: 520 Maitland Av S | C60: Orange | D60: 2023/02 | E60: 100 | F60: =Table2[[#This Row],[Price]]/Table2[[#This Row],[Tot Ht Area]] -> 0.023180343 | G60: 4314 | H60: 5305 | I60: Ramal Dental Real Estate LLC | J60: 1966 | K60: 1900 | L60: MTLDM | M60: 2129 36 0000 00 059 | N60: Medical | O60: High | P60: Maitland Dentistry | Q60: https://maitland-dentistry.wheree.com/ | R60: https://www.google.com/maps/search/520+Maitland+Av+S,+FL | T60: Yes
A61: 3 | B61: 1901 Lee Rd | C61: Orange | D61: 2021/01 | E61: 1575000 | F61: =Table2[[#This Row],[Price]]/Table2[[#This Row],[Tot Ht Area]] -> 325.14451 | G61: 4844 | H61: 4916 | I61: Donegal Properties LLC | J61: 1980 | K61: 1900 | L61: WPO1 | M61: 2229 01 0060 04 120 | N61: Medical | O61: High | P61: Knight Dermatology Institute | Q61: https://knightdermatology.com/location/winter-park-fl/ | R61: https://www.google.com/maps/search/1901+Lee+Rd,+FL
A62: 3 | B62: 2233 Lee Rd | C62: Orange | D62: 2022/12 | E62: 4216800 | F62: =Table2[[#This Row],[Price]]/Table2[[#This Row],[Tot Ht Area]] -> 200.81913 | G62: 20998 | H62: 21805 | I62: Prestige Ww Holdoings LLC | J62: 1971 | K62: 1800 | L62: WPO1 | M62: 2229 01 9180 00 050 | N62: Multi-Tenant Medical | O62: High | P62: Conquest Research (Medical Research Institute) | Q62: https://www.clinicalconnection.com/research-center-profile/view-profile/476547/conquest-research | R62: https://www.google.com/maps/search/2233+Lee+Rd,+FL
A63: 3 | B63: 5165 Adanson St | C63: Orange | D63: 2025/06 | E63: 3200000 | F63: =Table2[[#This Row],[Price]]/Table2[[#This Row],[Tot Ht Area]] -> 147.50622 | G63: 21694 | H63: 22786 | I63: Tighten Down Investment Group Inc | J63: 1978 | K63: 1900 | L63: ORGC2 | M63: 2229 02 0000 00 062 | N63: Medical | O63: High | P63: Central Florida Dreamplex (Disability Therapy) | Q63: https://vgispublic.ocpafl.org/webmapjs/?pid=292202000000062 | R63: https://www.google.com/maps/search/5165+Adanson+St,+FL | T63: Yes | U63: weird building /old | V63: https://vgispublic.ocpafl.org/webmapjs/?pid=292202000000062
A64: 3 | B64: 2295 Lee Rd | C64: Orange | D64: 2023/10 | E64: 100 | F64: =Table2[[#This Row],[Price]]/Table2[[#This Row],[Tot Ht Area]] -> 0.039556962 | G64: 2528 | H64: 2583 | I64: 2295 Lee Road LLC | J64: 1925 | K64: 1900 | L64: WPO1 | M64: 2229 02 0064 04 010 | N64: Medical | O64: High | P64: Central Florida Periodontics & Implantology | Q64: https://centralfloridaperio.com/contact-us/ | R64: https://www.google.com/maps/search/2295+Lee+Rd,+FL | T64: Yes
A65: 3 | B65: 400 Wymore Rd N | C65: Orange | D65: 2023/12 | E65: 800000 | F65: =Table2[[#This Row],[Price]]/Table2[[#This Row],[Tot Ht Area]] -> 328.54209 | G65: 2435 | H65: 2435 | I65: Florida Emergency Medicine Foundatio | J65: 1945 | K65: 1700 | L65: ORGPO | M65: 2229 02 4168 00 210 | N65: Medical | O65: High | P65: Florida Emergency Medicine Foundation | Q65: https://fcep.org/contact/ | R65: https://www.google.com/maps/search/400+Wymore+Rd+N,+FL
A66: 3 | B66: 2610 Audrey Av | C66: Orange | D66: 2021/10 | E66: 366400 | F66: =Table2[[#This Row],[Price]]/Table2[[#This Row],[Tot Ht Area]] -> 127.39917 | G66: 2876 | H66: 2936 | I66: Saisaroj Realty LLC | J66: 2023 | K66: 1900 | L66: WPO2 | M66: 2229 02 4168 00 660 | N66: Medical | O66: High | P66: Desai Dental (Winter Park Family Dentist) | Q66: https://www.carecredit.com/doctor-locator/winter-park-fl/desai-dental-234dhr/ | R66: https://www.google.com/maps/search/2610+Audrey+Av,+FL
A67: 3 | B67: 2134 Kentucky Av | C67: Orange | D67: 2022/05 | E67: 1400000 | F67: =Table2[[#This Row],[Price]]/Table2[[#This Row],[Tot Ht Area]] -> 408.8785 | G67: 3424 | H67: 3468 | I67: Life Concepts Inc | J67: 1960 | K67: 1700 | L67: WPC3 | M67: 2229 11 6180 02 010 | N67: Medical | O67: High | P67: Life Concepts / Quest, Inc. (Disability Care) | Q67: https://questinc.org/quest-kids-academy/ | R67: https://www.google.com/maps/search/2134+Kentucky+Av+Orange+FL
A68: 3 | B68: 3600 Formosa Av | C68: Orange | D68: 2023/09 | E68: 850000 | F68: =Table2[[#This Row],[Price]]/Table2[[#This Row],[Tot Ht Area]] -> 332.68102 | G68: 2555 | H68: 2555 | I68: Flossophy Commercial LLC | J68: 1965 | K68: 1900 | L68: ORLO1/ | M68: 2229 11 7620 00 130 | N68: Medical | O68: High | P68: Hillcrest Dental | Q68: https://www.carecredit.com/doctor-locator/orlando-fl/hillcrest-dental-222gct/ | R68: https://www.google.com/maps/search/3600+Formosa+Av+Orange+FL
A69: 3 | B69: 1605 Fairbanks Av W | C69: Orange | D69: 2021/12 | E69: 5000000 | F69: =Table2[[#This Row],[Price]]/Table2[[#This Row],[Tot Ht Area]] -> 405.28492 | G69: 12337 | H69: 14132 | I69: Adventist Health System/Sunbelt Inc Attn: Adventhealth Accounting Dept | J69: 2005 | K69: 1900 | L69: WPO1 | M69: 2229 12 0000 00 001 | N69: Hospitals | O69: High | P69: AdventHealth Medical Group Cardiology MEDICAL CENTER | Q69: https://www.adventhealth.com/find-doctor/doctor/basiem-barsoum-md-1104099456 | R69: https://www.google.com/maps/search/1605+Fairbanks+Av+W+Orange+FL
A70: 3 | B70: 1350 Fairbanks Av W | C70: Orange | D70: 2020/12 | E70: 5300000 | F70: =Table2[[#This Row],[Price]]/Table2[[#This Row],[Tot Ht Area]] -> 903.81992 | G70: 5864 | H70: 5864 | I70: Reinhold Winter Park Properties LLC | J70: 2021 | K70: 1900 | L70: WPC3 | M70: 2229 12 0664 00 100 | N70: Medical | O70: High | P70: SimonMed Imaging - Winter Park | Q70: https://www.simonmed.com/locations/fl/winter-park-iii/ | R70: https://www.google.com/maps/search/1350+Fairbanks+Av+W+Orange+FL | T70: Yes | U70: New SimonMed | V70: https://vgispublic.ocpafl.org/webmapjs/?pid=292212066400100
A71: 3 | B71: 1110 Kentucky Av N | C71: Orange | D71: 2022/06 | E71: 100 | F71: =Table2[[#This Row],[Price]]/Table2[[#This Row],[Tot Ht Area]] -> 0.03113325 | G71: 3212 | H71: 3520 | I71: Cofresi Properties LLC | J71: 1991 | K71: 1900 | L71: WPO2 | M71: 2229 12 6012 02 090 | N71: Medical | O71: High | P71: AdventHealth Medical Group Pulmonology | Q71: https://www.adventhealth.com/find-doctor/doctor/hamel-patel-do-1831620392 | R71: https://www.google.com/maps/search/1110+Kentucky+Av+N+Orange+FL | T71: Yes
A72: 3 | B72: 954 Orlando Av S | C72: Orange | D72: 2022/12 | E72: 6349400 | F72: =Table2[[#This Row],[Price]]/Table2[[#This Row],[Tot Ht Area]] -> 424 | G72: 14975 | H72: 16422 | I72: Flagship Winter Park Verax LLC | J72: 1974 | K72: 1900 | L72: WPC3 | M72: 2229 12 6600 00 730 | N72: Multi-Tenant Medical | O72: High | P72: Flagship Healthcare Properties (Medical REIT) | Q72: https://www.loopnet.com/Listing/954-S-Orlando-Ave-Winter-Park-FL/22329340/ | R72: https://www.google.com/maps/search/954+Orlando+Av+S+Orange+FL
A73: 3 | B73: 3000 Orange Av N | C73: Orange | D73: 2020/09 | E73: 1987500 | F73: =Table2[[#This Row],[Price]]/Table2[[#This Row],[Tot Ht Area]] -> 311.08155 | G73: 6389 | H73: 6421 | I73: Adventist Health System/Sunbelt Inc Attn: Adventhealth Accounting Dept | J73: 1994 | K73: 1900 | L73: ORLMU1 | M73: 2229 13 0540 01 011 | N73: Medical | O73: High | P73: AdventHealth Medical Group Pediatric Rheumatology at Orlando | Q73: https://www.adventhealth.com/practice/adventhealth-medical-group/find-a-location?page=68 | R73: https://www.google.com/maps/search/3000+Orange+Av+N+Orange+FL
A74: 3 | B74: 2905 Mcrae Av | C74: Orange | D74: 2022/08 | E74: 4900000 | F74: =Table2[[#This Row],[Price]]/Table2[[#This Row],[Tot Ht Area]] -> 850.69444 | G74: 5760 | H74: 7120 | I74: Adventist Health System/Sunbelt Inc Attn: Adventhealth Accounting Dept | J74: 1971 | K74: 1900 | L74: ORLMU1 | M74: 2229 13 2784 01 031 | N74: Medical | O74: High | P74: AdventHealth (Hospital Support/Admin) | Q74: https://npiregistry.cms.hhs.gov/provider-view/1841680733 | R74: https://www.google.com/maps/search/2905+Mcrae+Av+Orange+FL | T74: Yes | U74: Advant Health | V74: https://vgispublic.ocpafl.org/webmapjs/?pid=292213278401031
A75: 3 | B75: 2909 Orange Av N | C75: Orange | D75: 2021/06 | E75: 10221900 | F75: =Table2[[#This Row],[Price]]/Table2[[#This Row],[Tot Ht Area]] -> 651.90689 | G75: 15680 | H75: 20440 | I75: Adventist Health System/Sunbelt Inc Attn: Adventhealth Accounting Dept | J75: 1958 | K75: 1900 | L75: ORLMU1 | M75: 2229 13 2784 02 030 | N75: Hospitals | O75: High | Q75: https://www.adventhealth.com/ | R75: https://www.google.com/maps/search/2909+Orange+Av+N+Orange+FL | U75: Advent Health
A76: 3 | B76: 1911 Mills Av N | C76: Orange | D76: 2023/12 | E76: 100 | F76: =Table2[[#This Row],[Price]]/Table2[[#This Row],[Tot Ht Area]] -> 0.0021609007 | G76: 46277 | H76: 50941 | I76: Dhc Zb Properties LLC Two Newton Place | J76: 1997 | K76: 1900 | L76: ORLMU1 | M76: 2229 13 5315 00 010 | N76: Medical | O76: High | P76: Ascend Vision Partners / Herschel Lasik | Q76: https://ascendvision.com/locations/orlando/ | R76: https://www.google.com/maps/search/1911+Mills+Av+N+Orange+FL | T76: Yes
A77: 3 | B77: 308 Groveland St | C77: Orange | D77: 2023/03 | E77: 1100000 | F77: =Table2[[#This Row],[Price]]/Table2[[#This Row],[Tot Ht Area]] -> 373.51443 | G77: 2945 | H77: 3484 | I77: Clay 3100 LLC | J77: 1980 | K77: 1900 | L77: ORLO2/ | M77: 2229 13 6652 00 050 | N77: Medical | O77: High | P77: No longer Dr. Renee J. Mueller, MD (Colon and Rectal) | Q77: https://www.orlandohealth.com/physician-finder/renee-mueller-md | R77: https://www.google.com/maps/search/308+Groveland+St+Orange+FL
A78: 3 | B78: 300 Hazel St E | C78: Orange | D78: 2023/08 | E78: 846000 | F78: =Table2[[#This Row],[Price]]/Table2[[#This Row],[Tot Ht Area]] -> 328.03412 | G78: 2579 | H78: 2609 | I78: G D & O Properties LLC | J78: 1984 | K78: 1900 | L78: ORLO2/ | M78: 2229 13 7108 01 070 | N78: Medical | O78: High | P78: The Dermatology Group PA | Q78: https://www.dermgroup.net/ | R78: https://www.google.com/maps/search/300+Hazel+St+E+Orange+FL
A79: 3 | B79: 301 Princeton St E | C79: Orange | D79: 2022/04 | E79: 100 | F79: =Table2[[#This Row],[Price]]/Table2[[#This Row],[Tot Ht Area]] -> 0.0036473721 | G79: 27417 | H79: 29722 | I79: Dover Holdings LLC The Langfan Company Attn: Mark Langf | J79: 2012 | K79: 1900 | L79: ORLAC2 | M79: 2229 13 8555 01 001 | N79: Medical | O79: High | P79: Florida Hospital Diabetes Institute | Q79: https://d2dstudy.org/florida/ | R79: https://www.google.com/maps/search/301+Princeton+St+E+Orange+FL | T79: Yes
A80: 3 | B80: 1301 Colonial Dr W | C80: Orange | D80: 2022/10 | E80: 3518200 | F80: =Table2[[#This Row],[Price]]/Table2[[#This Row],[Tot Ht Area]] -> 396.64036 | G80: 8870 | H80: 9018 | I80: Albert And Magdalena Lao Family Trus Albert L Lao And Magdelena C Lao Co | J80: 2005 | K80: 1800 | L80: ORLO1/ | M80: 2229 22 8252 06 010 | N80: Multi-Tenant Medical | O80: High | P80: CAN Community Health / Miracle of Love | Q80: https://www.cancommunityhealth.org/orlando/ | R80: https://www.google.com/maps/search/1301+Colonial+Dr+W+Orange+FL
A81: 3 | B81: 1127 Edgewater Dr | C81: Orange | D81: 2021/11 | E81: 1150000 | F81: =Table2[[#This Row],[Price]]/Table2[[#This Row],[Tot Ht Area]] -> 407.36805 | G81: 2823 | H81: 3293 | I81: Hidalgo Ignacio | J81: 1959 | K81: 1700 | L81: ORLMU1 | M81: 2229 23 2344 00 080 | N81: Medical | O81: High | P81: Evolve Aesthetics (Medical Spa) | Q81: https://www.evolveorl.com/contact-us/ | R81: https://www.google.com/maps/search/1127+Edgewater+Dr+Orange+FL
A82: 3 | B82: 707 Colonial Dr E | C82: Orange | D82: 2025/05 | E82: 1550000 | F82: =Table2[[#This Row],[Price]]/Table2[[#This Row],[Tot Ht Area]] -> 317.75318 | G82: 4878 | H82: 10005 | I82: Aids Healthcare Foundation Inc | J82: 1960 | K82: 1700 | L82: ORLMU1 | M82: 2229 24 1524 00 140 | N82: Medical | O82: High | P82: AIDS Healthcare Foundation (AHF) Pharmacy | Q82: https://www.aidshealth.org/locations/fl-orlando-rx/ | R82: https://www.google.com/maps/search/707+Colonial+Dr+E+Orange+FL
A83: 3 | B83: 609 Virginia Dr | C83: Orange | D83: 2020/06 | E83: 1270100 | F83: =Table2[[#This Row],[Price]]/Table2[[#This Row],[Tot Ht Area]] -> 257.41792 | G83: 4934 | H83: 5107 | I83: 609 Virginia LLC | J83: 1983 | K83: 1900 | L83: ORLMU1 | M83: 2229 24 4476 00 017 | N83: Medical | O83: High | P83: Optum - Lake Ivanhoe (Primary Care) | Q83: https://www.healthgrades.com/group-directory/fl-florida/orlando/optum-lake-ivanhoe-xqkhm9 | R83: https://www.google.com/maps/search/609+Virginia+Dr+Orange+FL
A84: 3 | B84: 130 Marks St E | C84: Orange | D84: 2021/01 | E84: 1200000 | F84: =Table2[[#This Row],[Price]]/Table2[[#This Row],[Tot Ht Area]] -> 309.0394 | G84: 3883 | H84: 4079 | I84: 130 East Marks LLC | J84: 1968 | K84: 1700 | L84: ORLMXD | M84: 2229 24 5440 01 140 | N84: Medical | O84: High | P84: HealthyMD (Primary Care/Wellness) | Q84: https://npin.cdc.gov/organization/healthymd-0 | R84: https://www.google.com/maps/search/130+Marks+St+E+Orange+FL
A85: 3 | B85: 1318 Mills Av N | C85: Orange | D85: 2022/04 | E85: 1200000 | F85: =Table2[[#This Row],[Price]]/Table2[[#This Row],[Tot Ht Area]] -> 353.9823 | G85: 3390 | H85: 3656 | I85: Portunol Properties LLC | J85: 1973 | K85: 1900 | L85: ORLACN | M85: 2229 24 5828 00 140 | N85: Medical | O85: High | P85: Mills Dental Group | Q85: https://www.carecredit.com/doctor-locator/orlando-fl/mills-dental-group-935wkf/ | R85: https://www.google.com/maps/search/1318+Mills+Av+N+Orange+FL
A86: 3 | B86: 1745 Mills Av N | C86: Orange | D86: 2023/07 | E86: 13200000 | F86: =Table2[[#This Row],[Price]]/Table2[[#This Row],[Tot Ht Area]] -> 470.42053 | G86: 28060 | H86: 30229 | I86: Cpf Hcre Winter Park LLC Chicago Pacific Founders Attn Cliff | J86: 2006 | K86: 1900 | L86: ORLMU1 | M86: 2229 24 5975 00 010 | N86: Hospitals | O86: High | P86: Central Florida Cardiology Group MEDICAL CENTER | Q86: https://www.cfcg.com/contact-us/ | R86: https://www.google.com/maps/search/1745+Mills+Av+N+Orange+FL
A87: 3 | B87: 1505 Colonial Dr E | C87: Orange | D87: 2022/04 | E87: 7125000 | F87: =Table2[[#This Row],[Price]]/Table2[[#This Row],[Tot Ht Area]] -> 184.85847 | G87: 38543 | H87: 40718 | I87: Salud Integral En La Montana Inc Carr 153 Km 12 4 | J87: 1960 | K87: 1800 | L87: ORLPD/ | M87: 2229 24 7060 01 030 | N87: Multi-Tenant Medical | O87: High | P87: Salud Integral En La Montana (Medical Clinic) | Q87: https://www.myfloridalicense.com/LicenseDetail.asp?SID=&id=1278E296699828CDB1BCDAEB825BA730 | R87: https://vgispublic.ocpafl.org/webmapjs/?pid=292224706001030
A88: 3 | B88: 823 Mills Av N | C88: Orange | D88: 2022/05 | E88: 100 | F88: =Table2[[#This Row],[Price]]/Table2[[#This Row],[Tot Ht Area]] -> 0.043917435 | G88: 2277 | H88: 2295 | I88: Phd Venture LLC | J88: 1993 | K88: 1700 | L88: ORLMU1 | M88: 2229 24 7782 00 010 | N88: Medical | O88: High | P88: Orlando Health Clinic (Family Medicine) | Q88: https://www.zocdoc.com/doctor/angel-ho-md-115642 | R88: https://www.google.com/maps/search/823+Mills+Av+N+Orange+FL | T88: Yes
A89: 3 | B89: 214 Marks St E | C89: Orange | D89: 2020/04 | E89: 1410000 | F89: =Table2[[#This Row],[Price]]/Table2[[#This Row],[Tot Ht Area]] -> 206.29115 | G89: 6835 | H89: 7058 | I89: Kslb LLC | J89: 1954 | K89: 1900 | L89: ORLMXD | M89: 2229 24 8484 00 210 | N89: Medical | O89: High | P89: Lifeskills Orlando (Outpatient Therapy) | Q89: https://lifeskillsbehavioralhealth.com/location/orlando-outpatient/ | R89: https://www.google.com/maps/search/214+Marks+St+E+Orange+FL
A90: 3 | B90: 1724 Mills Av N | C90: Orange | D90: 2025/04 | E90: 33444697 | F90: =Table2[[#This Row],[Price]]/Table2[[#This Row],[Tot Ht Area]] -> 478.33489 | G90: 69919 | H90: 77729 | I90: Adventist Health System/Sunbelt Inc | J90: 2024 | K90: 1900 | L90: ORLPD/ | M90: 2229 24 8833 02 000 | N90: Hospitals | O90: High | P90: Charter Research (Clinical Trials) MEDICAL CENTER | Q90: https://seamless.ai/b/charter-research-6612681 | R90: https://www.google.com/maps/search/1724+Mills+Av+N+Orange+FL | T90: Yes
A91: 3 | B91: 1510 Colonial Dr E | C91: Orange | D91: 2022/04 | E91: 4411500 | F91: =Table2[[#This Row],[Price]]/Table2[[#This Row],[Tot Ht Area]] -> 83.65412 | G91: 52735 | H91: 53328 | I91: Colonialtown Investments LLC | J91: 1960 | K91: 1800 | L91: ORLMU2 | M91: 2229 25 1536 01 030 | N91: Multi-Tenant Medical | O91: High | P91: AJH Complete Care (Primary Care) | Q91: https://www.ajhcompletecarellc.org/contact-5 | R91: https://www.google.com/maps/search/1510+Colonial+Dr+E+Orange+FL | T91: Yes | U91: Multi unit deal? Bad Cap rate/ old building? | V91: https://vgispublic.ocpafl.org/webmapjs/?pid=292225153601030
A92: 3 | B92: 444 Mills Av N | C92: Orange | D92: 2021/10 | E92: 428300 | F92: =Table2[[#This Row],[Price]]/Table2[[#This Row],[Tot Ht Area]] -> 96.096029 | G92: 4457 | H92: 6461 | I92: Wynnheart LLC | J92: 1967 | K92: 1900 | L92: ORLO1/ | M92: 2229 25 2508 01 091 | N92: Medical | O92: High | P92: Newman Plastic Surgery | Q92: https://newmanplasticsurgery.com/about-us/meet-dr-newman | R92: https://www.google.com/maps/search/444+Mills+Av+N+Orange+FL | T92: Yes | U92: Sold for 1M in 2005 | V92: https://vgispublic.ocpafl.org/webmapjs/?pid=292225250801091
A93: 3 | B93: 3480 Polynesian Isle Blvd | C93: Osceola | D93: 2025/04 | E93: 5150000 | F93: =Table2[[#This Row],[Price]]/Table2[[#This Row],[Tot Ht Area]] -> 412.66026 | G93: 12480 | H93: 12720 | I93: Vitalis Mob Kissimmee LLC | J93: 2020 | K93: 1911 | L93: OPD | M93: 2528 02 5035 0001 0017 | N93: Hospitals | O93: High | P93: Florida Lung, Asthma & Sleep Specialists MEDICAL CENTER | Q93: https://floridalungdoctors.com/polynesian-office/ | R93: https://www.google.com/maps/search/3480+Polynesian+Isle+Blvd+Osceola+FL
A94: 3 | B94: 2497 Trafalgar Blvd | C94: Osceola | D94: 2020/10 | E94: 1250000 | F94: =Table2[[#This Row],[Price]]/Table2[[#This Row],[Tot Ht Area]] -> 207.95209 | G94: 6011 | H94: 6707 | I94: Ibraheem LLC | J94: 2010 | K94: 1911 | L94: OPUD | M94: 2628 14 5254 0001 0030 | N94: Medical | O94: High | P94: World of Pediatrics (Dr. Rafay Khan) | Q94: https://www.pocf.net/ | R94: https://www.google.com/maps/search/2497+Trafalgar+Blvd+Osceola+FL
A95: 3 | B95: 3016 Dyer Blvd | C95: Osceola | D95: 2021/11 | E95: 925000 | F95: =Table2[[#This Row],[Price]]/Table2[[#This Row],[Tot Ht Area]] -> 155.46218 | G95: 5950 | H95: 6440 | I95: Rispartners Kissimmee LLC | J95: 2022 | K95: 1911 | L95: KMPU | M95: 2529 05 1882 0001 0060 | N95: Medical | O95: High | P95: Radiology and Imaging Specialists (RIS) | Q95: https://www.medicai.io/medical-imaging-providers/radiology-and-imaging-specialists-kissimmee-kissimmee-florida | R95: https://www.google.com/maps/search/3016+Dyer+Blvd+Osceola+FL
A96: 3 | B96: 1611 N Main St | C96: Osceola | D96: 2023/11 | E96: 1300000 | F96: =Table2[[#This Row],[Price]]/Table2[[#This Row],[Tot Ht Area]] -> 363.73811 | G96: 3574 | H96: 3916 | I96: Rec Strategies LLC | J96: 1968 | K96: 1911 | L96: KB3 | M96: 2529 15 1050 00RL 0015 | N96: Medical | O96: High | P96: Medical | R96: https://maps.property-appraiser.org/?Pin=152529105000RL0015
A97: 3 | B97: 207 Park Place Blvd | C97: Osceola | D97: 2024/02 | F97: =Table2[[#This Row],[Price]]/Table2[[#This Row],[Tot Ht Area]] -> 0 | G97: 11440 | H97: 13100 | I97: Bhupendra M & Himaxi B Patel Revocable Trust Patel Bhupendra Tr Patel Hi | J97: 1986 | K97: 1911 | L97: OCR | M97: 2529 15 4673 0001 0010 | N97: Medical | O97: High | P97: Medical | R97: https://maps.property-appraiser.org/?Pin=152529467300010010
A98: 3 | B98: 205 Park Place Blvd | C98: Osceola | D98: 2025/10 | E98: 1800000 | F98: =Table2[[#This Row],[Price]]/Table2[[#This Row],[Tot Ht Area]] -> 300 | G98: 6000 | H98: 7257 | I98: Three Birds Investments LLC | J98: 1987 | K98: 1911 | L98: OCR | M98: 2529 15 4673 0001 0020 | N98: Medical | O98: High | P98: AdventHealth - OBGYN | Q98: https://www.adventhealth.com/find-doctor/doctor/peter-joseph-casella-md-1245200278 | R98: https://www.google.com/maps/search/205+Park+Place+Blvd+Osceola+FL
A99: 3 | B99: 1010 W Oak St | C99: Osceola | D99: 2024/06 | E99: 2002800 | F99: =Table2[[#This Row],[Price]]/Table2[[#This Row],[Tot Ht Area]] -> 302.1726 | G99: 6628 | H99: 6628 | I99: Cream Rises To The Top Real Estate Holdings LLC | J99: 2010 | K99: 1911 | L99: KB5 | M99: 2529 21 1069 0001 0010 | N99: Medical | O99: High | P99: Medical | Q99: https://www.loopnet.com/Listing/1010-1020-W-Oak-St-Kissimmee-FL/31250163/ | R99: https://www.google.com/maps/search/1010+W+Oak+St+Osceola+FL
A100: 3 | B100: 908 Mabbette St | C100: Osceola | D100: 2024/11 | E100: 840000 | F100: =Table2[[#This Row],[Price]]/Table2[[#This Row],[Tot Ht Area]] -> 271.14267 | G100: 3098 | H100: 3918 | I100: Mabbette Holdings LLC | J100: 1924 | K100: 1911 | L100: KRB2 | M100: 2529 21 1191 0001 0010 | N100: Medical | O100: High | P100: Park Place Behavioral Health | Q100: https://www.myfloridalegal.com/vicitm-services-providers/park-place-behavioral-health-care | R100: https://www.google.com/maps/search/908+Mabbette+St+Osceola+FL
...

Sheet Medical Sales
A1: *Filter data of exclusively medical office sales and excluding nominal sales ($100)*
A2: VERIFIED VIA HUMAN (1-3 GRADE) | B2: Prpty Addr | C2: County | D2: Date Trnsfr | E2: Price | F2: $/SF | G2: Tot Ht Area | H2: Total Area | I2: Grantee | J2: Yr Built 1 | K2: Use Code | L2: Zoning | M2: Parcel ID | N2: Verdict | O2: Confidence | P2: Current Tenant | Q2: Evidence Link | R2: Google Map Link | S2: Evidence P2. | T2: Building Age | U2: Outlier | V2: Year | W2: Size Bracket
A3: 3 | B3: 1605 Fairbanks Av W | C3: Orange | D3: 2021/12 | E3: 5000000 | F3: =E3/G3 -> 405.28492 | G3: 12337 | H3: 14132 | I3: AdventHealth Medical Group Cardiology MEDICAL CENTER | J3: 2005 | K3: 1900 | L3: WPO1 | M3: 2229 12 0000 00 001 | N3: Hospitals | O3: High | P3: **AdventHealth Medical Group Cardiology** MEDICAL CENTER | Q3: https://www.adventhealth.com/find-doctor/doctor/basiem-barsoum-md-1104099456 | R3: https://www.google.com/maps/search/1605+Fairbanks+Av+W+Orange+FL | T3: =IF(OR(J3="",D3=""),"Unknown",IF(LEFT(D3,4)*1-J3*1<=10,"New",IF(LEFT(D3,4)*1-J3*1<=25,"Normal","Old"))) -> Normal | U3: Yes | V3: =LEFT(D3,4)*1 -> 2021 | W3: 4. 10 - 20K SF
A4: 3 | B4: 16831 US Highway 441 | C4: Lake | D4: 2021/12 | E4: 3060000 | F4: =E4/G4 -> 278.71391 | G4: 10979 | H4: 12986 | I4: HCA Florida Eustis Emergency Room MEDICAL CENTER | J4: 2023 | K4: 1900 | M4: 1926 23 0004 000 02900 | N4: Hospitals | O4: High | P4: **HCA Florida Eustis Emergency Room** MEDICAL CENTER | Q4: https://www.hcafloridahealthcare.com/locations/mount-dora-emergency | R4: https://www.google.com/maps?q=16831+US+Highway+441+Lake,+FL | T4: =IF(OR(J4="",D4=""),"Unknown",IF(LEFT(D4,4)*1-J4*1<=10,"New",IF(LEFT(D4,4)*1-J4*1<=25,"Normal","Old"))) -> New | U4: Yes | V4: =LEFT(D4,4)*1 -> 2021 | W4: 4. 10 - 20K SF
A5: 3 | B5: 1724 Mills Av N | C5: Orange | D5: 2025/04 | E5: 33444697 | F5: =E5/G5 -> 478.33489 | G5: 69919 | H5: 77729 | I5: Adventist Health System/Sunbelt Inc | J5: 2024 | K5: 1900 | L5: ORLPD/ | M5: 2229 24 8833 02 000 | N5: Hospitals | O5: High | P5: **Charter Research (Clinical Trials)** MEDICAL CENTER | Q5: https://seamless.ai/b/charter-research-6612681 | R5: https://www.google.com/maps/search/1724+Mills+Av+N+Orange+FL | T5: =IF(OR(J5="",D5=""),"Unknown",IF(LEFT(D5,4)*1-J5*1<=10,"New",IF(LEFT(D5,4)*1-J5*1<=25,"Normal","Old"))) -> New | V5: =LEFT(D5,4)*1 -> 2025 | W5: 5. 20K+ SF
A6: 3 | B6: 2909 Orange Av N | C6: Orange | D6: 2021/06 | E6: 10221900 | F6: =E6/G6 -> 651.90689 | G6: 15680 | H6: 20440 | I6: Adventist Health System/Sunbelt Inc Attn: Adventhealth Accounting Dept | J6: 1958 | K6: 1900 | L6: ORLMU1 | M6: 2229 13 2784 02 030 | N6: Hospitals | O6: High | P6: Orlando Medical Dental Center MEDICAL CENTER | Q6: https://www.adventhealth.com/ | R6: https://www.google.com/maps/search/2909+Orange+Av+N+Orange+FL | T6: =IF(OR(J6="",D6=""),"Unknown",IF(LEFT(D6,4)*1-J6*1<=10,"New",IF(LEFT(D6,4)*1-J6*1<=25,"Normal","Old"))) -> Old | U6: Yes | V6: =LEFT(D6,4)*1 -> 2021 | W6: 4. 10 - 20K SF
A7: 3 | B7: 3200 Citrus Tower Blvd | C7: Lake | D7: 2020/07 | E7: 1340800 | F7: =E7/G7 -> 111.71471 | G7: 12002 | H7: 12360 | I7: Clermont VA Clinic (Veterans Affairs) MEDICAL CENTER | J7: 2021 | K7: 1900 | M7: 2326 05 0050 000 01300 | N7: Hospitals | O7: High | P7: **Clermont VA Clinic (Veterans Affairs)** MEDICAL CENTER | Q7: https://www.va.gov/orlando-health-care/locations/clermont-va-clinic/ | R7: https://www.google.com/maps/search/?api=1&query=3200+Citrus+Tower+Blvd+Lake+FL | T7: =IF(OR(J7="",D7=""),"Unknown",IF(LEFT(D7,4)*1-J7*1<=10,"New",IF(LEFT(D7,4)*1-J7*1<=25,"Normal","Old"))) -> New | U7: Yes | V7: =LEFT(D7,4)*1 -> 2020 | W7: 4. 10 - 20K SF
A8: 3 | B8: 3480 Polynesian Isle Blvd | C8: Osceola | D8: 2025/04 | E8: 5150000 | F8: =E8/G8 -> 412.66026 | G8: 12480 | H8: 12720 | I8: Vitalis Mob Kissimmee LLC | J8: 2020 | K8: 1911 | L8: OPD | M8: 2528 02 5035 0001 0017 | N8: Hospitals | O8: High | P8: **Florida Lung, Asthma & Sleep Specialists** MEDICAL CENTER | Q8: https://floridalungdoctors.com/polynesian-office/ | R8: https://www.google.com/maps/search/3480+Polynesian+Isle+Blvd+Osceola+FL | T8: =IF(OR(J8="",D8=""),"Unknown",IF(LEFT(D8,4)*1-J8*1<=10,"New",IF(LEFT(D8,4)*1-J8*1<=25,"Normal","Old"))) -> New | U8: Yes | V8: =LEFT(D8,4)*1 -> 2025 | W8: 4. 10 - 20K SF
A9: 3 | B9: 454 Rinehart Rd | C9: Seminole | D9: 2023/10 | E9: 3889000 | F9: =E9/G9 -> 136.42742 | G9: 28506 | H9: 28506 | I9: Orlandohealth Inc | J9: 2024 | K9: 1906 | M9: 2030 06 525 0000 00B0 | N9: Hospitals | O9: High | P9: Orlando Health Jewett Orthopedic Institute MEDICAL CENTER | Q9: https://www.orlandohealth.com/locations/orlando-health-jewett-orthopedic-institute-lake-mary-rinehart | R9: https://www.google.com/maps?q=454+Rinehart+Rd+Seminole,+FL | T9: =IF(OR(J9="",D9=""),"Unknown",IF(LEFT(D9,4)*1-J9*1<=10,"New",IF(LEFT(D9,4)*1-J9*1<=25,"Normal","Old"))) -> New | V9: =LEFT(D9,4)*1 -> 2023 | W9: 5. 20K+ SF
A10: 3 | B10: 658 Oviedo Medical Dr | C10: Seminole | D10: 2024/12 | E10: 9998200 | F10: =E10/G10 -> 587.19681 | G10: 17027 | H10: 17027 | I10: Mmof IV Mid Fl Portfolio LLC C/O Ryan LLC | J10: 2017 | K10: 19 | M10: 2131 16 5CA 0000 120A | N10: Hospitals | O10: High | P10: Hematology and Oncology MEDICAL CENTER | Q10: https://www.orlandohealth.com/physician-finder/alan-r-forbes-md | R10: https://www.google.com/maps/search/?api=1&query=658+Oviedo+Medical+Dr+Seminole+FL | T10: =IF(OR(J10="",D10=""),"Unknown",IF(LEFT(D10,4)*1-J10*1<=10,"New",IF(LEFT(D10,4)*1-J10*1<=25,"Normal","Old"))) -> New | U10: Yes | V10: =LEFT(D10,4)*1 -> 2024 | W10: 4. 10 - 20K SF
A11: 3 | B11: 750 Orienta Ave | C11: Seminole | D11: 2020/04 | E11: 550000 | F11: =E11/G11 -> 45.304778 | G11: 12140 | H11: 12140 | I11: Florida Cancer Specialists MEDICAL CENTER | J11: 2023 | K11: 19 | M11: 2129 12 5BE 0000 4660 | N11: Hospitals | O11: High | P11: **Florida Cancer Specialists** MEDICAL CENTER | Q11: https://flcancer.com/location/altamonte/ | R11: https://www.google.com/maps/search/?api=1&query=750+Orienta+Ave+Seminole+FL | T11: =IF(OR(J11="",D11=""),"Unknown",IF(LEFT(D11,4)*1-J11*1<=10,"New",IF(LEFT(D11,4)*1-J11*1<=25,"Normal","Old"))) -> New | V11: =LEFT(D11,4)*1 -> 2020 | W11: 4. 10 - 20K SF
A12: 3 | B12: 9401 Summit Centre Wa | C12: Orange | D12: 2021/10 | E12: 15500000 | F12: =E12/G12 -> 1500.3388 | G12: 10331 | H12: 12626 | I12: HCA Florida Maitland Emergency (Freestanding ER) MEDICAL CENTER | J12: 2024 | K12: 1900 | L12: MTLPD | M12: 2129 28 5499 03 000 | N12: Hospitals | O12: High | P12: **HCA Florida Maitland Emergency (Freestanding ER)** MEDICAL CENTER | Q12: https://www.hcafloridahealthcare.com/locations/maitland-emergency | R12: https://www.google.com/maps/search/9401+Summit+Centre+Wa,+FL | T12: =IF(OR(J12="",D12=""),"Unknown",IF(LEFT(D12,4)*1-J12*1<=10,"New",IF(LEFT(D12,4)*1-J12*1<=25,"Normal","Old"))) -> New | U12: Yes | V12: =LEFT(D12,4)*1 -> 2021 | W12: 4. 10 - 20K SF
A13: 3 | B13: 100 Waymont Ct | C13: Seminole | D13: 2022/11 | E13: 4100000 | F13: =E13/G13 -> 227.77778 | G13: 18000 | H13: 18000 | I13: AdventHealth Sports Medicine & Rehab | J13: 1997 | K13: 19 | M13: 2030 17 300 0140 0000 | N13: Medical | O13: High | P13: **AdventHealth Sports Medicine & Rehab** | Q13: https://www.adventhealth.com/locations/adventhealth-sports-med-and-rehab-lake-mary | R13: https://www.google.com/maps?q=100+Waymont+Ct+Seminole,+FL | T13: =IF(OR(J13="",D13=""),"Unknown",IF(LEFT(D13,4)*1-J13*1<=10,"New",IF(LEFT(D13,4)*1-J13*1<=25,"Normal","Old"))) -> Normal | U13: Yes | V13: =LEFT(D13,4)*1 -> 2022 | W13: 4. 10 - 20K SF
A14: 3 | B14: 1000 E Irlo Bronson Memorial | C14: Osceola | D14: 2021/01 | E14: 3552600 | F14: =E14/G14 -> 466.95584 | G14: 7608 | H14: 8124 | I14: MedExpress Urgent Care (Optum) MEDICAL CENTER | J14: 2020 | K14: 1911 | L14: SPUD | M14: 2631 07 0212 0001 0010 | N14: Hospitals | O14: High | P14: MedExpress Urgent Care (Optum) MEDICAL CENTER | Q14: https://www.optum.com/en/ | R14: https://www.google.com/maps?q=1000+E+Irlo+Bronson+Memorial+Osceola,+FL | T14: =IF(OR(J14="",D14=""),"Unknown",IF(LEFT(D14,4)*1-J14*1<=10,"New",IF(LEFT(D14,4)*1-J14*1<=25,"Normal","Old"))) -> New | U14: Yes | V14: =LEFT(D14,4)*1 -> 2021 | W14: 3. 6 - 10K SF
A15: 3 | B15: 1001 W Cherry St | C15: Osceola | D15: 2021/12 | E15: 1010000 | F15: =E15/G15 -> 175.49957 | G15: 5755 | H15: 5959 | I15: Acaba Properties LLC | J15: 2003 | K15: 1911 | L15: KHC | M15: 2529 21 1212 0001 0010 | N15: Medical | O15: High | P15: Sunshine Family Medical and Wellness | Q15: https://sunshinefmwc.com/ | R15: https://www.google.com/maps/search/1001+W+Cherry+St+Osceola+FL | T15: =IF(OR(J15="",D15=""),"Unknown",IF(LEFT(D15,4)*1-J15*1<=10,"New",IF(LEFT(D15,4)*1-J15*1<=25,"Normal","Old"))) -> Normal | U15: Yes | V15: =LEFT(D15,4)*1 -> 2021 | W15: 2. 3 - 6K SF
A16: 3 | B16: 101 Bellagio Cir | C16: Seminole | D16: 2020/08 | E16: 1340000 | F16: =E16/G16 -> 517.97449 | G16: 2587 | H16: 2587 | I16: American Hospitality Assn Inc | J16: 2007 | K16: 1905 | M16: 1930 28 520 0000 0330 | N16: Medical | O16: High | P16: Coastal Mental Health Center (Condo) | Q16: https://coastalmhc.com/ | R16: https://maps.google.com/?cid=8827082157455925323&g_mp=Cidnb29nbGUubWFwcy5wbGFjZXMudjEuUGxhY2VzLlNlYXJjaFRleHQ | T16: =IF(OR(J16="",D16=""),"Unknown",IF(LEFT(D16,4)*1-J16*1<=10,"New",IF(LEFT(D16,4)*1-J16*1<=25,"Normal","Old"))) -> Normal | V16: =LEFT(D16,4)*1 -> 2020 | W16: 1. < 3K SF
A17: 3 | B17: 1010 Arthur Av | C17: Orange | D17: 2022/05 | E17: 925000 | F17: =E17/G17 -> 262.41135 | G17: 3525 | H17: 3525 | I17: The Spa Orlando (Massage & Wellness) | J17: 1984 | K17: 1900 | L17: ORLMU1 | M17: 2229 10 8828 04 150 | N17: Medical | O17: High | P17: **The Spa Orlando (Massage & Wellness)** | Q17: Used to be https://www.tolbirth.com/ | R17: https://www.google.com/maps/search/5749+Westgate+Dr,+FL+R13 | T17: =IF(OR(J17="",D17=""),"Unknown",IF(LEFT(D17,4)*1-J17*1<=10,"New",IF(LEFT(D17,4)*1-J17*1<=25,"Normal","Old"))) -> Old | U17: Yes | V17: =LEFT(D17,4)*1 -> 2022 | W17: 2. 3 - 6K SF
A18: 3 | B18: 1010 W Oak St | C18: Osceola | D18: 2024/06 | E18: 2002800 | F18: =E18/G18 -> 302.1726 | G18: 6628 | H18: 6628 | I18: Cream Rises To The Top Real Estate Holdings LLC | J18: 2010 | K18: 1911 | L18: KB5 | M18: 2529 21 1069 0001 0010 | N18: Medical | O18: High | P18: Medical | Q18: https://www.loopnet.com/Listing/1010-1020-W-Oak-St-Kissimmee-FL/31250163/ | R18: https://www.google.com/maps/search/1010+W+Oak+St+Osceola+FL | T18: =IF(OR(J18="",D18=""),"Unknown",IF(LEFT(D18,4)*1-J18*1<=10,"New",IF(LEFT(D18,4)*1-J18*1<=25,"Normal","Old"))) -> Normal | U18: Yes | V18: =LEFT(D18,4)*1 -> 2024 | W18: 3. 6 - 10K SF
A19: 3 | B19: 1045 N John Young Pkwy | C19: Osceola | D19: 2025/08 | E19: 2310000 | F19: =E19/G19 -> 320.83333 | G19: 7200 | H19: 7200 | I19: Nova Health Medical Group LLC | J19: 1999 | K19: 1911 | L19: KHC | M19: 2529 21 1412 0001 0020 | N19: Medical | O19: High | P19: **Nova Health Medical Group (Primary Care)** | Q19: https://www.loopnet.com/Listing/1045-1085-N-John-Young-Pky-Kissimmee-FL/31094164/ | R19: https://www.google.com/maps/search/1045+N+John+Young+Pkwy+Osceola+FL | S19: investment sale | T19: =IF(OR(J19="",D19=""),"Unknown",IF(LEFT(D19,4)*1-J19*1<=10,"New",IF(LEFT(D19,4)*1-J19*1<=25,"Normal","Old"))) -> Old | U19: Yes | V19: =LEFT(D19,4)*1 -> 2025 | W19: 3. 6 - 10K SF
A20: 3 | B20: 106 Boston # 100 Ave | C20: Seminole | D20: 2021/12 | E20: 5050000 | F20: =E20/G20 -> 202.46161 | G20: 24943 | H20: 24943 | I20: Geneva Altamonte LLC | J20: 1976 | K20: 1900 | M20: 2129 12 5BE 0000 6000 | N20: Medical | O20: High | P20: Associates in Dermatology - Altamonte Springs | Q20: https://www.psoriasis.org/health-care-provider-directory/michael-steppie-associates-in-dermatology-altamonte-springs/ | R20: https://www.google.com/maps/search/?api=1&query=106+Boston+%23+100+Ave+Seminole+FL | T20: =IF(OR(J20="",D20=""),"Unknown",IF(LEFT(D20,4)*1-J20*1<=10,"New",IF(LEFT(D20,4)*1-J20*1<=25,"Normal","Old"))) -> Old | U20: Yes | V20: =LEFT(D20,4)*1 -> 2021 | W20: 5. 20K+ SF
A21: 3 | B21: 108 Citrus St W | C21: Seminole | D21: 2022/11 | E21: 460000 | F21: =E21/G21 -> 180.39216 | G21: 2550 | H21: 2550 | I21: Healing Psychiatry of Florida | J21: 1983 | K21: 1905 | M21: 2129 11 525 0000 00C0 | N21: Medical | O21: High | P21: **Healing Psychiatry of Florida** | Q21: https://www.healingpsychiatryflorida.com/offices/altamonte-springs/ | R21: https://www.google.com/maps/search/?api=1&query=108+Citrus+St+W+Seminole+FL | T21: =IF(OR(J21="",D21=""),"Unknown",IF(LEFT(D21,4)*1-J21*1<=10,"New",IF(LEFT(D21,4)*1-J21*1<=25,"Normal","Old"))) -> Old | U21: Yes | V21: =LEFT(D21,4)*1 -> 2022 | W21: 1. < 3K SF
A22: 3 | B22: 108 Park Av S | C22: Orange | D22: 2023/10 | E22: 475000 | F22: =E22/G22 -> 102.81385 | G22: 4620 | H22: 4745 | I22: Dada Eyecare Holdings LLC | J22: 2024 | K22: 1900 | L22: APKMUD | M22: 2128 09 0196 20 063 | N22: Medical | O22: High | P22: Essential Eye Care & Optical | Q22: https://www.essentialeyecareoptical.com/hours-location/ | R22: https://www.google.com/maps/search/108+Park+Av+S,+FL | T22: =IF(OR(J22="",D22=""),"Unknown",IF(LEFT(D22,4)*1-J22*1<=10,"New",IF(LEFT(D22,4)*1-J22*1<=25,"Normal","Old"))) -> New | U22: Yes | V22: =LEFT(D22,4)*1 -> 2023 | W22: 2. 3 - 6K SF
A23: 3 | B23: 11001 Colonial Dr W | C23: Orange | D23: 2021/11 | E23: 1650000 | F23: =E23/G23 -> 230.06135 | G23: 7172 | H23: 7435 | I23: AdventHealth Centra Care Ocoee | J23: 2022 | K23: 1900 | L23: OCOC3 | M23: 2228 19 0000 00 024 | N23: Medical | O23: High | P23: **AdventHealth Centra Care Ocoee** | Q23: https://biz.wochamber.com/list/member/adventhealth-centra-care-ocoee-30983 | R23: https://www.google.com/maps/search/11001+Colonial+Dr+W,+FL | T23: =IF(OR(J23="",D23=""),"Unknown",IF(LEFT(D23,4)*1-J23*1<=10,"New",IF(LEFT(D23,4)*1-J23*1<=25,"Normal","Old"))) -> New | U23: Yes | V23: =LEFT(D23,4)*1 -> 2021 | W23: 3. 6 - 10K SF
A24: 3 | B24: 1122 SR 434 E | C24: Seminole | D24: 2022/11 | E24: 3735000 | F24: =E24/G24 -> 647.0894 | G24: 5772 | H24: 5772 | I24: Golden Link Inv LLC | J24: 2004 | K24: 19 | M24: 2030 26 5AR 0B00 026C | N24: Multi-Tenant Medical | O24: High | P24: Smile Design Dentistry | Q24: https://www.thesmiledesign.com/locations/winter-springs/ | R24: https://www.google.com/maps/search/?api=1&query=1122+SR+434+E+Seminole+FL | T24: =IF(OR(J24="",D24=""),"Unknown",IF(LEFT(D24,4)*1-J24*1<=10,"New",IF(LEFT(D24,4)*1-J24*1<=25,"Normal","Old"))) -> Normal | V24: =LEFT(D24,4)*1 -> 2022 | W24: 2. 3 - 6K SF
A25: 3 | B25: 1127 Edgewater Dr | C25: Orange | D25: 2021/11 | E25: 1150000 | F25: =E25/G25 -> 407.36805 | G25: 2823 | H25: 3293 | I25: Evolve Aesthetics (Medical Spa) | J25: 1959 | K25: 1700 | L25: ORLMU1 | M25: 2229 23 2344 00 080 | N25: Medical | O25: High | P25: **Evolve Aesthetics (Medical Spa)** | Q25: https://www.evolveorl.com/contact-us/ | R25: https://www.google.com/maps/search/1127+Edgewater+Dr+Orange+FL | T25: =IF(OR(J25="",D25=""),"Unknown",IF(LEFT(D25,4)*1-J25*1<=10,"New",IF(LEFT(D25,4)*1-J25*1<=25,"Normal","Old"))) -> Old | U25: Yes | V25: =LEFT(D25,4)*1 -> 2021 | W25: 1. < 3K SF
A26: 3 | B26: 1132 North Blvd E | C26: Lake | D26: 2022/07 | E26: 390000 | F26: =E26/G26 -> 106.73235 | G26: 3654 | H26: 4134 | I26: Schweiger Dermatology Group | J26: 1984 | K26: 1900 | M26: 1924 25 0001 000 13400 | N26: Medical | O26: High | P26: **Schweiger Dermatology Group** | Q26: https://www.schweigerderm.com/location/florida/leesburg/ | R26: https://www.google.com/maps?q=1132+North+Blvd+E+Lake,+FL | T26: =IF(OR(J26="",D26=""),"Unknown",IF(LEFT(D26,4)*1-J26*1<=10,"New",IF(LEFT(D26,4)*1-J26*1<=25,"Normal","Old"))) -> Old | U26: Yes | V26: =LEFT(D26,4)*1 -> 2022 | W26: 2. 3 - 6K SF
A27: 3 | B27: 11625 Lachlan Ln | C27: Orange | D27: 2025/06 | E27: 3473802 | F27: =E27/G27 -> 915.12171 | G27: 3796 | H27: 3922 | I27: Cl Westside Shoppes Fl LLC | J27: 2017 | K27: 1900 | L27: ORGPD | M27: 2327 25 5839 02 000 | N27: Medical | O27: High | P27: Dental Care at Westside Shoppes | Q27: https://dentalcareatwestsideshoppes.com/ | R27: https://www.google.com/maps/search/11625+Lachlan+Ln,+FL | T27: =IF(OR(J27="",D27=""),"Unknown",IF(LEFT(D27,4)*1-J27*1<=10,"New",IF(LEFT(D27,4)*1-J27*1<=25,"Normal","Old"))) -> New | V27: =LEFT(D27,4)*1 -> 2025 | W27: 2. 3 - 6K SF
A28: 3 | B28: 1221 Fairbanks Av W | C28: Orange | D28: 2021/11 | E28: 243300 | F28: =E28/G28 -> 45.664414 | G28: 5328 | H28: 5480 | I28: Murphy Holdings LLC | J28: 1971 | K28: 1700 | L28: ORGC1 | M28: 2229 03 1000 00 060 | N28: Medical | O28: High | P28: Medi-Weightloss Center Winter Park | Q28: https://mediweightloss.com/weight-loss-clinic/winterpark/ | R28: https://www.google.com/maps/search/1221+Fairbanks+Av+W,+FL | T28: =IF(OR(J28="",D28=""),"Unknown",IF(LEFT(D28,4)*1-J28*1<=10,"New",IF(LEFT(D28,4)*1-J28*1<=25,"Normal","Old"))) -> Old | V28: =LEFT(D28,4)*1 -> 2021 | W28: 2. 3 - 6K SF
A29: 3 | B29: 129 Bellagio Cir | C29: Seminole | D29: 2020/08 | E29: 1340000 | F29: =E29/G29 -> 623.25581 | G29: 2150 | H29: 2150 | I29: Towne Center Animal Hospital (Condo) | J29: 2007 | K29: 1905 | M29: 1930 28 520 0000 0270 | N29: Medical | O29: High | P29: Towne Center Animal Hospital (Condo) | Q29: http://www.townecenteranimalhospital.com/ | R29: https://maps.google.com/?cid=12525815501440194295&g_mp=Cidnb29nbGUubWFwcy5wbGFjZXMudjEuUGxhY2VzLlNlYXJjaFRleHQ | T29: =IF(OR(J29="",D29=""),"Unknown",IF(LEFT(D29,4)*1-J29*1<=10,"New",IF(LEFT(D29,4)*1-J29*1<=25,"Normal","Old"))) -> Normal | V29: =LEFT(D29,4)*1 -> 2020 | W29: 1. < 3K SF
A30: 3 | B30: 130 Marks St E | C30: Orange | D30: 2021/01 | E30: 1200000 | F30: =E30/G30 -> 309.0394 | G30: 3883 | H30: 4079 | I30: HealthyMD (Primary Care/Wellness) | J30: 1968 | K30: 1700 | L30: ORLMXD | M30: 2229 24 5440 01 140 | N30: Medical | O30: High | P30: **HealthyMD (Primary Care/Wellness)** | Q30: https://npin.cdc.gov/organization/healthymd-0 | R30: https://www.google.com/maps/search/130+Marks+St+E+Orange+FL | T30: =IF(OR(J30="",D30=""),"Unknown",IF(LEFT(D30,4)*1-J30*1<=10,"New",IF(LEFT(D30,4)*1-J30*1<=25,"Normal","Old"))) -> Old | U30: Yes | V30: =LEFT(D30,4)*1 -> 2021 | W30: 2. 3 - 6K SF
A31: 3 | B31: 1301 Sundial Pt | C31: Seminole | D31: 2025/05 | E31: 1225000 | F31: =E31/G31 -> 360.29412 | G31: 3400 | H31: 3400 | I31: Lime To Orange Obgyn LLC | J31: 2007 | K31: 1905 | M31: 2130 24 523 0100 0000 | N31: Medical | O31: High | P31: Optum-Tuskawilla (Family Medicine) | Q31: https://www.healthgrades.com/group-directory/fl-florida/winter-springs/optum-tuskawilla-x3xdcn | R31: https://www.google.com/maps/search/?api=1&query=1301+Sundial+Pt+Seminole+FL | T31: =IF(OR(J31="",D31=""),"Unknown",IF(LEFT(D31,4)*1-J31*1<=10,"New",IF(LEFT(D31,4)*1-J31*1<=25,"Normal","Old"))) -> Normal | U31: Yes | V31: =LEFT(D31,4)*1 -> 2025 | W31: 2. 3 - 6K SF
A32: 2 | B32: 1307 International # 2051 Pkw | C32: Seminole | D32: 2021/10 | E32: 665000 | F32: =E32/G32 -> 295.81851 | G32: 2248 | H32: 2248 | I32: Badlands Properties LLC | J32: 2005 | K32: 1905 | M32: 2029 13 513 0900 00P2 | N32: Medical | O32: High | P32: Heathrow Psychology | Q32: https://heathrowpsychology.com/ | R32: https://www.google.com/maps?q=1307+International+%232051+Pkw+Seminole,+FL | T32: =IF(OR(J32="",D32=""),"Unknown",IF(LEFT(D32,4)*1-J32*1<=10,"New",IF(LEFT(D32,4)*1-J32*1<=25,"Normal","Old"))) -> Normal | U32: Yes | V32: =LEFT(D32,4)*1 -> 2021 | W32: 1. < 3K SF
A33: 3 | B33: 1314 Sumter St | C33: Lake | D33: 2021/09 | E33: 545000 | F33: =E33/G33 -> 72.860963 | G33: 7480 | H33: 7480 | I33: Family First Homecare (Pediatric) | J33: 2001 | K33: 1900 | M33: 1924 26 0003 000 01400 | N33: Medical | O33: High | P33: **Family First Homecare (Pediatric)** | Q33: https://myfamilyfirsthc.com/locations/ | R33: https://www.google.com/maps?q=1314+Sumter+St+Lake,+FL | T33: =IF(OR(J33="",D33=""),"Unknown",IF(LEFT(D33,4)*1-J33*1<=10,"New",IF(LEFT(D33,4)*1-J33*1<=25,"Normal","Old"))) -> Normal | V33: =LEFT(D33,4)*1 -> 2021 | W33: 3. 6 - 10K SF
A34: 3 | B34: 1318 Mills Av N | C34: Orange | D34: 2022/04 | E34: 1200000 | F34: =E34/G34 -> 353.9823 | G34: 3390 | H34: 3656 | I34: Mills Dental Group | J34: 1973 | K34: 1900 | L34: ORLACN | M34: 2229 24 5828 00 140 | N34: Medical | O34: High | P34: **Mills Dental Group** | Q34: https://www.carecredit.com/doctor-locator/orlando-fl/mills-dental-group-935wkf/ | R34: https://www.google.com/maps/search/1318+Mills+Av+N+Orange+FL | T34: =IF(OR(J34="",D34=""),"Unknown",IF(LEFT(D34,4)*1-J34*1<=10,"New",IF(LEFT(D34,4)*1-J34*1<=25,"Normal","Old"))) -> Old | U34: Yes | V34: =LEFT(D34,4)*1 -> 2022 | W34: 2. 3 - 6K SF
A35: 3 | B35: 1320 N Main St | C35: Osceola | D35: 2021/04 | E35: 600000 | F35: =E35/G35 -> 227.27273 | G35: 2640 | H35: 3390 | I35: Sutherland Wolf & Boroaks Property Mangement LLC | J35: 1984 | K35: 1911 | L35: KB3 | M35: 2529 22 1360 000A 0020 | N35: Medical | O35: High | P35: **Wolf Chiropractic Kissimmee** | Q35: https://hurtaid.com/directory/medical-provider/wolf-chiropractic-kissimmee/ | R35: https://www.google.com/maps/search/1320+N+Main+St+Osceola+FL | T35: =IF(OR(J35="",D35=""),"Unknown",IF(LEFT(D35,4)*1-J35*1<=10,"New",IF(LEFT(D35,4)*1-J35*1<=25,"Normal","Old"))) -> Old | U35: Yes | V35: =LEFT(D35,4)*1 -> 2021 | W35: 1. < 3K SF
A36: 3 | B36: 1325 International # 2241 Pkw | C36: Seminole | D36: 2021/09 | E36: 610000 | F36: =E36/G36 -> 271.35231 | G36: 2248 | H36: 2248 | I36: Rhythmiq LLC | J36: 2005 | K36: 1905 | M36: 2029 13 513 0600 00P2 | N36: Medical | O36: High | P36: Orlando Cardiac & Vascular Specialists (Optum) | Q36: https://orlandocardiacspecialists.com/contact-us/ | R36: https://www.google.com/maps?q=1325+International+%232241+Pkw+Seminole,+FL | T36: =IF(OR(J36="",D36=""),"Unknown",IF(LEFT(D36,4)*1-J36*1<=10,"New",IF(LEFT(D36,4)*1-J36*1<=25,"Normal","Old"))) -> Normal | U36: Yes | V36: =LEFT(D36,4)*1 -> 2021 | W36: 1. < 3K SF
A37: 3 | B37: 1325 Shelfer St | C37: Lake | D37: 2022/07 | E37: 475000 | F37: =E37/G37 -> 193.08943 | G37: 2460 | H37: 2915 | I37: Tesla Biohealing Inc | J37: 1974 | K37: 1700 | M37: 1924 23 0002 000 03708 | N37: Medical | O37: High | P37: Tesla BioHealing (MedTech Center) | Q37: https://www.teslabiohealing.com/collections/tesla-medbed-center-leesburg-fl?_gl=1*1xto5k9*_up*MQ..*_gs*MQ..&gclid=Cj0KCQiA4eHLBhCzARIsAJ2NZoJRZHoXlV2PzH6wioAFL_veuWE690gULyIChXBzgXKXzzmRF0ucLcIaAtBOEALw_wcB&gbraid=0AAAABA6AXXQfB9RTa1dJXefhwUNHr8n3u | R37: https://www.google.com/maps?q=1325+Shelfer+St+Lake,+FL | T37: =IF(OR(J37="",D37=""),"Unknown",IF(LEFT(D37,4)*1-J37*1<=10,"New",IF(LEFT(D37,4)*1-J37*1<=25,"Normal","Old"))) -> Old | U37: Yes | V37: =LEFT(D37,4)*1 -> 2022 | W37: 1. < 3K SF
A38: 3 | B38: 1343 International # 1351 Pkw | C38: Seminole | D38: 2020/06 | E38: 2900000 | F38: =E38/G38 -> 385.22848 | G38: 7528 | H38: 7528 | I38: Complete Care Lake Mary (Injury/Rehab) | J38: 2005 | K38: 1905 | M38: 2029 13 513 0300 00A1 | N38: Medical | O38: High | P38: **Complete Care Lake Mary (Injury/Rehab)** | Q38: https://www.complete-care.com/locations/complete-care-lake-mary/ | R38: https://www.google.com/maps/search/?api=1&query=1343+International+Pkwy+1351+Lake+Mary+FL | T38: =IF(OR(J38="",D38=""),"Unknown",IF(LEFT(D38,4)*1-J38*1<=10,"New",IF(LEFT(D38,4)*1-J38*1<=25,"Normal","Old"))) -> Normal | U38: Yes | V38: =LEFT(D38,4)*1 -> 2020 | W38: 3. 6 - 10K SF
A39: 3 | B39: 1350 Fairbanks Av W | C39: Orange | D39: 2020/12 | E39: 5300000 | F39: =E39/G39 -> 903.81992 | G39: 5864 | H39: 5864 | I39: SimonMed Imaging - Winter Park | J39: 2021 | K39: 1900 | L39: WPC3 | M39: 2229 12 0664 00 100 | N39: Medical | O39: High | P39: **SimonMed Imaging - Winter Park** | Q39: https://www.simonmed.com/locations/fl/winter-park-iii/ | R39: https://www.google.com/maps/search/1350+Fairbanks+Av+W+Orange+FL | T39: =IF(OR(J39="",D39=""),"Unknown",IF(LEFT(D39,4)*1-J39*1<=10,"New",IF(LEFT(D39,4)*1-J39*1<=25,"Normal","Old"))) -> New | V39: =LEFT(D39,4)*1 -> 2020 | W39: 2. 3 - 6K SF
A40: 3 | B40: 1355 International # 1481 Pkw | C40: Seminole | D40: 2021/03 | E40: 840000 | F40: =E40/G40 -> 252.32803 | G40: 3329 | H40: 3329 | I40: Caya Health (Family Medicine/Counseling) | J40: 2005 | K40: 1905 | M40: 2029 13 513 0100 00B1 | N40: Medical | O40: High | P40: **Caya Health (Family Medicine/Counseling)** | Q40: https://www.cayahealth.com/ | R40: https://maps.google.com/?cid=4875051585993840576&g_mp=Cidnb29nbGUubWFwcy5wbGFjZXMudjEuUGxhY2VzLlNlYXJjaFRleHQ | T40: =IF(OR(J40="",D40=""),"Unknown",IF(LEFT(D40,4)*1-J40*1<=10,"New",IF(LEFT(D40,4)*1-J40*1<=25,"Normal","Old"))) -> Normal | U40: Yes | V40: =LEFT(D40,4)*1 -> 2021 | W40: 2. 3 - 6K SF
A41: 3 | B41: 1403 Medical Plaza # 204 Dr | C41: Seminole | D41: 2024/07 | E41: 330000 | F41: =E41/G41 -> 165 | G41: 2000 | H41: 2000 | I41: Central Florida Regional Hospital Inc | J41: 1983 | K41: 1905 | M41: 1930 26 508 0000 2480 | N41: Medical | O41: High | P41: Seminole Neurology Associates, P.A. | Q41: https://www.healthgrades.com/group-directory/fl-florida/sanford/seminole-neurology-associates-pa-xbbyxw | R41: https://www.google.com/maps?q=1403+Medical+Plaza+%23204+Dr+Seminole,+FL | T41: =IF(OR(J41="",D41=""),"Unknown",IF(LEFT(D41,4)*1-J41*1<=10,"New",IF(LEFT(D41,4)*1-J41*1<=25,"Normal","Old"))) -> Old | U41: Yes | V41: =LEFT(D41,4)*1 -> 2024 | W41: 1. < 3K SF
A42: 3 | B42: 1445 Mitchell Hammock Rd E | C42: Seminole | D42: 2022/11 | E42: 3735000 | F42: =E42/G42 -> 772.01323 | G42: 4838 | H42: 4838 | I42: Smile Design Dentistry | J42: 2009 | K42: 19 | M42: 2131 14 516 0000 0020 | N42: Medical | O42: High | P42: Oviedo Premier Dental | Q42: https://www.dentalplans.com/dentists/florida/oviedo/32765/dr-michael-simpson-13713/ | R42: https://www.google.com/maps/search/?api=1&query=1445+Mitchell+Hammock+Rd+E+Seminole+FL | T42: =IF(OR(J42="",D42=""),"Unknown",IF(LEFT(D42,4)*1-J42*1<=10,"New",IF(LEFT(D42,4)*1-J42*1<=25,"Normal","Old"))) -> Normal | V42: =LEFT(D42,4)*1 -> 2022 | W42: 2. 3 - 6K SF
A43: 3 | B43: 1475 Mitchell Hammock Rd E | C43: Seminole | D43: 2021/04 | E43: 2305000 | F43: =E43/G43 -> 377.25041 | G43: 6110 | H43: 6110 | I43: Page Dvm Inc | J43: 1999 | K43: 1902 | M43: 2131 14 511 0000 0010 | N43: Medical | O43: High | P43: Shaffer Animal Hospital | Q43: https://https://shafferah.com/.com/ | R43: https://www.google.com/maps/search/?api=1&query=1475+Mitchell+Hammock+Rd+E+Seminole+FL | T43: =IF(OR(J43="",D43=""),"Unknown",IF(LEFT(D43,4)*1-J43*1<=10,"New",IF(LEFT(D43,4)*1-J43*1<=25,"Normal","Old"))) -> Normal | U43: Yes | V43: =LEFT(D43,4)*1 -> 2021 | W43: 3. 6 - 10K SF
A44: 3 | B44: 14835 Colonial Dr W | C44: Orange | D44: 2021/05 | E44: 344600 | F44: =E44/G44 -> 117.37057 | G44: 2936 | H44: 3048 | I44: Wholistic Dental Care | J44: 2021 | K44: 1900 | L44: WGC2 | M44: 2227 22 7670 03 000 | N44: Medical | O44: High | P44: **Wholistic Dental Care** | Q44: https://search.sunbiz.org/Inquiry/corporationsearch/SearchResultDetail?inquirytype=EntityName&directionType=Initial&searchNameOrder=WHOLISTICDENTALCAREWINTERGARDE%20L210000916830 | R44: https://www.google.com/maps/search/14835+Colonial+Dr+W,+FL | T44: =IF(OR(J44="",D44=""),"Unknown",IF(LEFT(D44,4)*1-J44*1<=10,"New",IF(LEFT(D44,4)*1-J44*1<=25,"Normal","Old"))) -> New | U44: Yes | V44: =LEFT(D44,4)*1 -> 2021 | W44: 1. < 3K SF
A45: 3 | B45: 1492 Fairbanks Av W | C45: Orange | D45: 2020/10 | E45: 625000 | F45: =E45/G45 -> 138.39681 | G45: 4516 | H45: 4724 | I45: 1492 W Fairbanks LLC | J45: 2021 | K45: 1900 | L45: WPC3 | M45: 2229 12 5004 02 010 | N45: Medical | O45: High | P45: Dr. Kapil Saigal | R45: https://www.google.com/maps/search/1492+Fairbanks+Av+W+Orange+FL | T45: =IF(OR(J45="",D45=""),"Unknown",IF(LEFT(D45,4)*1-J45*1<=10,"New",IF(LEFT(D45,4)*1-J45*1<=25,"Normal","Old"))) -> New | U45: Yes | V45: =LEFT(D45,4)*1 -> 2020 | W45: 2. 3 - 6K SF
A46: 3 | B46: 1495 Mitchell Hammock Rd E | C46: Seminole | D46: 2021/07 | E46: 621000 | F46: =E46/G46 -> 197.14286 | G46: 3150 | H46: 3150 | I46: Oviedo Care LLC | J46: 2000 | K46: 17 | M46: 2131 14 511 0000 0030 | N46: Medical | O46: High | P46: CareSpot Urgent Care (Oviedo) | Q46: https://www.carespot.com/carespot-urgent-care/oviedo-fl/ | R46: https://www.google.com/maps/search/?api=1&query=1495+Mitchell+Hammock+Rd+E+Seminole+FL | T46: =IF(OR(J46="",D46=""),"Unknown",IF(LEFT(D46,4)*1-J46*1<=10,"New",IF(LEFT(D46,4)*1-J46*1<=25,"Normal","Old"))) -> Normal | U46: Yes | V46: =LEFT(D46,4)*1 -> 2021 | W46: 2. 3 - 6K SF
A47: 3 | B47: 1501 Colonial Dr W | C47: Orange | D47: 2023/05 | E47: 1025000 | F47: =E47/G47 -> 229.97532 | G47: 4457 | H47: 5942 | I47: Lyon Counseling | J47: 1959 | K47: 1700 | L47: ORLO1/ | M47: 2229 22 1784 02 010 | N47: Medical | O47: High | P47: **Lyon Counseling** | Q47: https://lyoncounseling.care/therapist/ | R47: https://www.google.com/maps/search/1501+Colonial+Dr+W+Orange+FL | T47: =IF(OR(J47="",D47=""),"Unknown",IF(LEFT(D47,4)*1-J47*1<=10,"New",IF(LEFT(D47,4)*1-J47*1<=25,"Normal","Old"))) -> Old | U47: Yes | V47: =LEFT(D47,4)*1 -> 2023 | W47: 2. 3 - 6K SF
A48: 3 | B48: 1513 N Main St | C48: Osceola | D48: 2020/12 | E48: 400000 | F48: =E48/G48 -> 93.327112 | G48: 4286 | H48: 4581 | I48: Beaudry Animal Clinic LLC | J48: 1945 | K48: 1911 | L48: KB3 | M48: 2529 15 1350 00SL 0010 | N48: Medical | O48: High | P48: Beaudry Animal Hospital /Osceola Animal Clinic (Veterinary) | Q48: https://osceolaanimalclinic.com/ | R48: https://www.google.com/maps/search/1513+N+Main+St+Osceola+FL | T48: =IF(OR(J48="",D48=""),"Unknown",IF(LEFT(D48,4)*1-J48*1<=10,"New",IF(LEFT(D48,4)*1-J48*1<=25,"Normal","Old"))) -> Old | V48: =LEFT(D48,4)*1 -> 2020 | W48: 2. 3 - 6K SF
A49: 3 | B49: 15650 Colonial Dr W | C49: Orange | D49: 2021/03 | E49: 1725000 | F49: =E49/G49 -> 347.78226 | G49: 4960 | H49: 5608 | I49: Harmony Dental Holdings LLC | J49: 2020 | K49: 1900 | L49: WGC2 | M49: 2227 28 0000 00 001 | N49: Medical | O49: High | P49: Harmony Dental Care / Oakland Pediatric Dentistry | Q49: https://www.carecredit.com/doctor-locator/winter-garden-fl/harmony-dental-care-633hqp/ | R49: https://www.google.com/maps/search/15650+Colonial+Dr+W,+FL | T49: =IF(OR(J49="",D49=""),"Unknown",IF(LEFT(D49,4)*1-J49*1<=10,"New",IF(LEFT(D49,4)*1-J49*1<=25,"Normal","Old"))) -> New | U49: Yes | V49: =LEFT(D49,4)*1 -> 2021 | W49: 2. 3 - 6K SF
A50: 3 | B50: 1603 Main St E | C50: Lake | D50: 2023/04 | E50: 350000 | F50: =E50/G50 -> 142.33428 | G50: 2459 | H50: 2559 | I50: Leesburg 441 Animal Hospital L | J50: 1946 | K50: 1900 | M50: 1925 30 0002 000 02700 | N50: Medical | O50: High | P50: Leesburg 441 Animal Hospital (Veterinary) | Q50: https://www.myfloridalicense.com/LicenseDetail.asp?SID=&id=846B397AAE6BE1ADC895273DC593ED1F | R50: https://www.google.com/maps?q=1603+E+Main+St,+Leesburg,+FL | T50: =IF(OR(J50="",D50=""),"Unknown",IF(LEFT(D50,4)*1-J50*1<=10,"New",IF(LEFT(D50,4)*1-J50*1<=25,"Normal","Old"))) -> Old | U50: Yes | V50: =LEFT(D50,4)*1 -> 2023 | W50: 1. < 3K SF
A51: 3 | B51: 1611 N Main St | C51: Osceola | D51: 2023/11 | E51: 1300000 | F51: =E51/G51 -> 363.73811 | G51: 3574 | H51: 3916 | I51: Rec Strategies LLC | J51: 1968 | K51: 1911 | L51: KB3 | M51: 2529 15 1050 00RL 0015 | N51: Medical | O51: High | P51: Medical | R51: https://maps.property-appraiser.org/?Pin=152529105000RL0015 | T51: =IF(OR(J51="",D51=""),"Unknown",IF(LEFT(D51,4)*1-J51*1<=10,"New",IF(LEFT(D51,4)*1-J51*1<=25,"Normal","Old"))) -> Old | U51: Yes | V51: =LEFT(D51,4)*1 -> 2023 | W51: 2. 3 - 6K SF
A52: 3 | B52: 1645 Ee Williamson Rd | C52: Seminole | D52: 2022/08 | E52: 1200000 | F52: =E52/G52 -> 216.68472 | G52: 5538 | H52: 5538 | I52: J H First Enterprises LLC | J52: 1996 | K52: 1902 | M52: 2029 35 501 0000 003C | N52: Medical | O52: High | P52: Markham Woods Animal Hospital (Veterinary) | Q52: https://www.markhamwoodsanimalhospital.com/ | R52: https://www.google.com/maps?q=1645+Ee+Williamson+Rd+Seminole,+FL | T52: =IF(OR(J52="",D52=""),"Unknown",IF(LEFT(D52,4)*1-J52*1<=10,"New",IF(LEFT(D52,4)*1-J52*1<=25,"Normal","Old"))) -> Old | U52: Yes | V52: =LEFT(D52,4)*1 -> 2022 | W52: 2. 3 - 6K SF
A53: 3 | B53: 165 Montgomery Rd | C53: Seminole | D53: 2021/09 | E53: 725000 | F53: =E53/G53 -> 170.34774 | G53: 4256 | H53: 4256 | I53: Woke Wellness LLC | J53: 1977 | K53: 19 | M53: 2129 15 300 015E 0000 | N53: Medical | O53: High | P53: Tree of Life (Birth and Gyno) | Q53: https://www.tolbirth.com/ | R53: https://www.google.com/maps/search/?api=1&query=165+Montgomery+Rd+Seminole+FL | T53: =IF(OR(J53="",D53=""),"Unknown",IF(LEFT(D53,4)*1-J53*1<=10,"New",IF(LEFT(D53,4)*1-J53*1<=25,"Normal","Old"))) -> Old | U53: Yes | V53: =LEFT(D53,4)*1 -> 2021 | W53: 2. 3 - 6K SF
A54: 3 | B54: 1701 1st St W | C54: Seminole | D54: 2024/10 | E54: 940000 | F54: =E54/G54 -> 109.98011 | G54: 8547 | H54: 8547 | I54: 1701 West First Street LLC | J54: 2005 | K54: 19 | M54: 1930 25 5AG 0320 0000 | N54: Medical | O54: Medium | P54: Vacant "2nd Gen Medical" for Lease (used to be DaVita Dialysis) | Q54: https://www.loopnet.com/Listing/1701-W-1st-St-Sanford-FL/28259426/ | R54: https://www.google.com/maps?q=1701+1st+St+W+Seminole,+FL | T54: =IF(OR(J54="",D54=""),"Unknown",IF(LEFT(D54,4)*1-J54*1<=10,"New",IF(LEFT(D54,4)*1-J54*1<=25,"Normal","Old"))) -> Normal | U54: Yes | V54: =LEFT(D54,4)*1 -> 2024 | W54: 3. 6 - 10K SF
A55: 3 | B55: 1788 Fairbanks Av W | C55: Orange | D55: 2021/12 | E55: 2900000 | F55: =E55/G55 -> 402.16336 | G55: 7211 | H55: 7645 | I55: Anafais Holdings LLC | J55: 1952 | K55: 1700 | L55: WPC3 | M55: 2229 12 5000 04 011 | N55: Medical | O55: High | P55: Flourish Clinical Research | Q55: https://flourishresearch.com/locations/orlando/ | R55: https://www.google.com/maps/search/1788+Fairbanks+Av+W+Orange+FL | T55: =IF(OR(J55="",D55=""),"Unknown",IF(LEFT(D55,4)*1-J55*1<=10,"New",IF(LEFT(D55,4)*1-J55*1<=25,"Normal","Old"))) -> Old | U55: Yes | V55: =LEFT(D55,4)*1 -> 2021 | W55: 3. 6 - 10K SF
A56: 3 | B56: 1901 Lee Rd | C56: Orange | D56: 2021/01 | E56: 1575000 | F56: =E56/G56 -> 325.14451 | G56: 4844 | H56: 4916 | I56: Knight Dermatology Institute | J56: 1980 | K56: 1900 | L56: WPO1 | M56: 2229 01 0060 04 120 | N56: Medical | O56: High | P56: **Knight Dermatology Institute** | Q56: https://knightdermatology.com/location/winter-park-fl/ | R56: https://www.google.com/maps/search/1901+Lee+Rd,+FL | T56: =IF(OR(J56="",D56=""),"Unknown",IF(LEFT(D56,4)*1-J56*1<=10,"New",IF(LEFT(D56,4)*1-J56*1<=25,"Normal","Old"))) -> Old | U56: Yes | V56: =LEFT(D56,4)*1 -> 2021 | W56: 2. 3 - 6K SF
A57: 3 | B57: 1986 State Road 19 | C57: Lake | D57: 2023/10 | E57: 900000 | F57: =E57/G57 -> 214.28571 | G57: 4200 | H57: 4435 | I57: Wmg Acquisitions LLC | J57: 2024 | K57: 1900 | M57: 2026 06 1000 000 00500 | N57: Medical | O57: High | R57: https://www.google.com/maps/search/1986+State+Road+19+Tavares+FL | T57: =IF(OR(J57="",D57=""),"Unknown",IF(LEFT(D57,4)*1-J57*1<=10,"New",IF(LEFT(D57,4)*1-J57*1<=25,"Normal","Old"))) -> New | U57: Yes | V57: =LEFT(D57,4)*1 -> 2023 | W57: 2. 3 - 6K SF
A58: 3 | B58: 20 Park Av S | C58: Orange | D58: 2021/06 | E58: 592000 | F58: =E58/G58 -> 169.14286 | G58: 3500 | H58: 3850 | I58: Spark Office LLC | J58: 1996 | K58: 1700 | L58: APKMUD | M58: 2128 09 1972 02 591 | N58: Medical | O58: High | P58: Medical Buildout (Tenant Unconfirmed) | Q58: https://www.loopnet.com/Listing/20-S-Park-Ave-Apopka-FL/16369407/ | R58: https://www.google.com/maps/search/20+Park+Av+S,+FL | T58: =IF(OR(J58="",D58=""),"Unknown",IF(LEFT(D58,4)*1-J58*1<=10,"New",IF(LEFT(D58,4)*1-J58*1<=25,"Normal","Old"))) -> Normal | U58: Yes | V58: =LEFT(D58,4)*1 -> 2021 | W58: 2. 3 - 6K SF
A59: 3 | B59: 205 Eola Dr S | C59: Orange | D59: 2020/02 | E59: 3325000 | F59: =E59/G59 -> 433.9598 | G59: 7662 | H59: 8163 | I59: Whitestone Legacy LLC | J59: 1945 | K59: 1700 | L59: ORLPD/ | M59: 2229 25 9320 01 060 | N59: Medical | O59: Medium | P59: Vacant "Office/Medical" for Sale | Q59: https://www.crexi.com/properties/2285495/florida-8000-sf-office-for-sale-in-downtown-orlando | R59: https://www.google.com/maps/search/205+Eola+Dr+S+Orange+FL | T59: =IF(OR(J59="",D59=""),"Unknown",IF(LEFT(D59,4)*1-J59*1<=10,"New",IF(LEFT(D59,4)*1-J59*1<=25,"Normal","Old"))) -> Old | U59: Yes | V59: =LEFT(D59,4)*1 -> 2020 | W59: 3. 6 - 10K SF
A60: 3 | B60: 205 Park Place Blvd | C60: Osceola | D60: 2025/10 | E60: 1800000 | F60: =E60/G60 -> 300 | G60: 6000 | H60: 7257 | I60: Three Birds Investments LLC | J60: 1987 | K60: 1911 | L60: OCR | M60: 2529 15 4673 0001 0020 | N60: Medical | O60: High | P60: AdventHealth - OBGYN | Q60: https://www.adventhealth.com/find-doctor/doctor/peter-joseph-casella-md-1245200278 | R60: https://www.google.com/maps/search/205+Park+Place+Blvd+Osceola+FL | T60: =IF(OR(J60="",D60=""),"Unknown",IF(LEFT(D60,4)*1-J60*1<=10,"New",IF(LEFT(D60,4)*1-J60*1<=25,"Normal","Old"))) -> Old | U60: Yes | V60: =LEFT(D60,4)*1 -> 2025 | W60: 3. 6 - 10K SF
A61: 3 | B61: 2100 1st St W | C61: Seminole | D61: 2024/10 | E61: 1991400 | F61: =E61/G61 -> 466.58857 | G61: 4268 | H61: 3969 | I61: Mmof IV Mid Fl Portfolio LLC C/O Montecito Medical Real Estate | J61: 2004 | K61: 19 | M61: 1930 26 509 0000 0030 | N61: Medical | O61: High | P61: **Mid-Florida Cancer Centers (Oncology)** | Q61: https://midfloridacancercenters.com/locations/sanford/ | R61: https://www.google.com/maps?q=2100+1st+St+W+Seminole,+FL | T61: =IF(OR(J61="",D61=""),"Unknown",IF(LEFT(D61,4)*1-J61*1<=10,"New",IF(LEFT(D61,4)*1-J61*1<=25,"Normal","Old"))) -> Normal | U61: Yes | V61: =LEFT(D61,4)*1 -> 2024 | W61: 2. 3 - 6K SF
A62: 3 | B62: 2115 Orange Blossom Tr W | C62: Orange | D62: 2024/05 | E62: 3500000 | F62: =E62/G62 -> 591.01655 | G62: 5922 | H62: 6039 | I62: Sanitas MEDICAL CENTER | J62: 2023 | K62: 1900 | L62: ORGC1 | M62: 2128 06 0000 00 047 | N62: Hospitals | O62: High | P62: Sanitas Medical Center | Q62: https://www.mysanitas.com/en/fl/sanitas-apopka | R62: https://www.google.com/maps/search/2115+Orange+Blossom+Tr+W,+FL | T62: =IF(OR(J62="",D62=""),"Unknown",IF(LEFT(D62,4)*1-J62*1<=10,"New",IF(LEFT(D62,4)*1-J62*1<=25,"Normal","Old"))) -> New | V62: =LEFT(D62,4)*1 -> 2024 | W62: 2. 3 - 6K SF
A63: 3 | B63: 212 County Road 466 | C63: Lake | D63: 2021/09 | E63: 417500 | F63: =E63/G63 -> 224.94612 | G63: 1856 | H63: 2200 | I63: Cjz Property Holdings LLC | J63: 1986 | K63: 1700 | M63: 1824 20 0400 000 06101 | N63: Medical | O63: High | P63: Healing Touch Massage Therapy | Q63: https://healingtouch212.wixsite.com/healingtouchmassage | R63: https://www.google.com/maps?q=212+County+Road+466+Lake,+FL | T63: =IF(OR(J63="",D63=""),"Unknown",IF(LEFT(D63,4)*1-J63*1<=10,"New",IF(LEFT(D63,4)*1-J63*1<=25,"Normal","Old"))) -> Old | U63: Yes | V63: =LEFT(D63,4)*1 -> 2021 | W63: 1. < 3K SF
A64: 3 | B64: 212 SR 434 E | C64: Seminole | D64: 2025/05 | E64: 500000 | F64: =E64/G64 -> 271.2968 | G64: 1843 | H64: 2991 | I64: Longwood Vet Properties LLC | J64: 1922 | K64: 1902 | M64: 2130 05 300 003B 0000 | N64: Medical | O64: High | P64: Loving Hearts Pet Hospital | Q64: google.com/url?url=http%3A%2F%2Fwww.lovingheartspethospital.com%2F&sa=t&rct=j&source=maps&usg=AOvVaw3r9J4bidhLidNYXof3CC-y&ved=1i%3A20%2Ct%3A3443%2Ce%3A14%2Cp%3ATFmFaceUN_XW5NoPjsbYuQ0%3A32 | R64: https://www.google.com/maps/search/?api=1&query=212+SR+434+E+Seminole+FL | T64: =IF(OR(J64="",D64=""),"Unknown",IF(LEFT(D64,4)*1-J64*1<=10,"New",IF(LEFT(D64,4)*1-J64*1<=25,"Normal","Old"))) -> Old | U64: Yes | V64: =LEFT(D64,4)*1 -> 2025 | W64: 1. < 3K SF
A65: 3 | B65: 2134 Kentucky Av | C65: Orange | D65: 2022/05 | E65: 1400000 | F65: =E65/G65 -> 408.8785 | G65: 3424 | H65: 3468 | I65: Life Concepts / Quest, Inc. (Disability Care) | J65: 1960 | K65: 1700 | L65: WPC3 | M65: 2229 11 6180 02 010 | N65: Medical | O65: High | P65: **Life Concepts / Quest, Inc. (Disability Care)** | Q65: https://questinc.org/quest-kids-academy/ | R65: https://www.google.com/maps/search/2134+Kentucky+Av+Orange+FL | T65: =IF(OR(J65="",D65=""),"Unknown",IF(LEFT(D65,4)*1-J65*1<=10,"New",IF(LEFT(D65,4)*1-J65*1<=25,"Normal","Old"))) -> Old | U65: Yes | V65: =LEFT(D65,4)*1 -> 2022 | W65: 2. 3 - 6K SF
A66: 3 | B66: 214 Marks St E | C66: Orange | D66: 2020/04 | E66: 1410000 | F66: =E66/G66 -> 206.29115 | G66: 6835 | H66: 7058 | I66: Lifeskills Orlando (Outpatient Therapy) | J66: 1954 | K66: 1900 | L66: ORLMXD | M66: 2229 24 8484 00 210 | N66: Medical | O66: High | P66: **Lifeskills Orlando (Outpatient Therapy)** | Q66: https://lifeskillsbehavioralhealth.com/location/orlando-outpatient/ | R66: https://www.google.com/maps/search/214+Marks+St+E+Orange+FL | T66: =IF(OR(J66="",D66=""),"Unknown",IF(LEFT(D66,4)*1-J66*1<=10,"New",IF(LEFT(D66,4)*1-J66*1<=25,"Normal","Old"))) -> Old | U66: Yes | V66: =LEFT(D66,4)*1 -> 2020 | W66: 3. 6 - 10K SF
A67: 3 | B67: 2200 Lee Rd | C67: Orange | D67: 2022/03 | E67: 800000 | F67: =E67/G67 -> 322.58065 | G67: 2480 | H67: 2673 | I67: Aarr Florida Investments LLC | J67: 1976 | K67: 1900 | L67: WPO1 | M67: 2229 02 8004 01 004 | N67: Medical | O67: High | P67: Vacant Medical Buildout (Former Dentist) | Q67: https://www.loopnet.com/Listing/2200-Lee-Rd-Winter-Park-FL/24836441/ | R67: https://www.google.com/maps/search/2200+Lee+Rd,+FL | T67: =IF(OR(J67="",D67=""),"Unknown",IF(LEFT(D67,4)*1-J67*1<=10,"New",IF(LEFT(D67,4)*1-J67*1<=25,"Normal","Old"))) -> Old | U67: Yes | V67: =LEFT(D67,4)*1 -> 2022 | W67: 1. < 3K SF
A68: 3 | B68: 238 Orlando Av S | C68: Orange | D68: 2023/12 | E68: 3000000 | F68: =E68/G68 -> 713.43639 | G68: 4205 | H68: 5986 | I68: Fisher Eye Properties LLC | J68: 2007 | K68: 1900 | L68: MTLDM | M68: 2129 25 6516 03 020 | N68: Medical | O68: High | P68: **Vision Source Maitland** | Q68: https://www.carecredit.com/doctor-locator/maitland-fl/vision-source-maitland-876tpt/ | R68: https://www.google.com/maps/search/238+Orlando+Av+S,+FL | T68: =IF(OR(J68="",D68=""),"Unknown",IF(LEFT(D68,4)*1-J68*1<=10,"New",IF(LEFT(D68,4)*1-J68*1<=25,"Normal","Old"))) -> Normal | V68: =LEFT(D68,4)*1 -> 2023 | W68: 2. 3 - 6K SF
A69: 3 | B69: 2400 Hooks St | C69: Lake | D69: 2024/08 | E69: 3300000 | F69: =E69/G69 -> 422.53521 | G69: 7810 | H69: 8314 | I69: 2400 Hooks Street LLC | J69: 2007 | K69: 1900 | M69: 2226 28 0100 000 00600 | N69: Medical | O69: High | R69: https://www.google.com/maps?q=2400+Hooks+St+Lake,+FL | T69: =IF(OR(J69="",D69=""),"Unknown",IF(LEFT(D69,4)*1-J69*1<=10,"New",IF(LEFT(D69,4)*1-J69*1<=25,"Normal","Old"))) -> Normal | U69: Yes | V69: =LEFT(D69,4)*1 -> 2024 | W69: 3. 6 - 10K SF
A70: 3 | B70: 241 Bellagio Cir | C70: Seminole | D70: 2021/01 | E70: 250100 | F70: =E70/G70 -> 116.32558 | G70: 2150 | H70: 2150 | I70: Physical Therapy Now Sanford | J70: 2007 | K70: 1905 | M70: 1930 28 520 0000 0090 | N70: Medical | O70: High | P70: **Physical Therapy Now Sanford** | Q70: https://physicaltherapynow.com/locations/sanford-lake-mary/ | R70: https://maps.google.com/?cid=10484780260240310301&g_mp=Cidnb29nbGUubWFwcy5wbGFjZXMudjEuUGxhY2VzLlNlYXJjaFRleHQ | T70: =IF(OR(J70="",D70=""),"Unknown",IF(LEFT(D70,4)*1-J70*1<=10,"New",IF(LEFT(D70,4)*1-J70*1<=25,"Normal","Old"))) -> Normal | U70: Yes | V70: =LEFT(D70,4)*1 -> 2021 | W70: 1. < 3K SF
A71: 3 | B71: 241 Obrien Rd | C71: Seminole | D71: 2025/01 | E71: 2000000 | F71: =E71/G71 -> 244.85798 | G71: 8168 | H71: 8168 | I71: Stepping Stones Behavioral Support LLC | J71: 1999 | K71: 17 | M71: 2130 19 507 0H00 0000 | N71: Medical | O71: High | P71: Stepping Stones Behavioral Support Applied Behavior Analysis Therapy) | Q71: https://www.abaorlando.com/ | R71: https://www.google.com/maps/search/?api=1&query=241+Obrien+Rd+Seminole+FL | T71: =IF(OR(J71="",D71=""),"Unknown",IF(LEFT(D71,4)*1-J71*1<=10,"New",IF(LEFT(D71,4)*1-J71*1<=25,"Normal","Old"))) -> Old | U71: Yes | V71: =LEFT(D71,4)*1 -> 2025 | W71: 3. 6 - 10K SF
A72: 3 | B72: 2497 Trafalgar Blvd | C72: Osceola | D72: 2020/10 | E72: 1250000 | F72: =E72/G72 -> 207.95209 | G72: 6011 | H72: 6707 | I72: World of Pediatrics (Dr. Rafay Khan) | J72: 2010 | K72: 1911 | L72: OPUD | M72: 2628 14 5254 0001 0030 | N72: Medical | O72: High | P72: **World of Pediatrics (Dr. Rafay Khan)** | Q72: https://www.pocf.net/ | R72: https://www.google.com/maps/search/2497+Trafalgar+Blvd+Osceola+FL | T72: =IF(OR(J72="",D72=""),"Unknown",IF(LEFT(D72,4)*1-J72*1<=10,"New",IF(LEFT(D72,4)*1-J72*1<=25,"Normal","Old"))) -> New | U72: Yes | V72: =LEFT(D72,4)*1 -> 2020 | W72: 3. 6 - 10K SF
A73: 3 | B73: 2500 Lake Mary # 217 Blvd W | C73: Seminole | D73: 2022/10 | E73: 350000 | F73: =E73/G73 -> 171.82131 | G73: 2037 | H73: 2037 | I73: My HealthMatrix (Hormone Therapy/Wellness) | J73: 1989 | K73: 1905 | M73: 2030 09 515 0000 2170 | N73: Medical | O73: High | P73: **My HealthMatrix (Hormone Therapy/Wellness)** | Q73: https://healthmatrix.com/location/orlando-lake-mary-florida/ | R73: https://www.google.com/maps?q=2500+Lake+Mary+%23217+Blvd+W+Seminole,+FL | T73: =IF(OR(J73="",D73=""),"Unknown",IF(LEFT(D73,4)*1-J73*1<=10,"New",IF(LEFT(D73,4)*1-J73*1<=25,"Normal","Old"))) -> Old | U73: Yes | V73: =LEFT(D73,4)*1 -> 2022 | W73: 1. < 3K SF
A74: 3 | B74: 252 Plaza Dr | C74: Seminole | D74: 2025/04 | E74: 514200 | F74: =E74/G74 -> 205.68 | G74: 2500 | H74: 2500 | I74: Mindy A Hall Liv Trust & Steven M Hall S Liv Trust C/O Dr Steven Hall | J74: 1993 | K74: 19 | M74: 2131 09 509 0000 0100 | N74: Medical | O74: High | P74: **Steven M. Hall, DMD (Oviedo Smiles)** | Q74: https://www.oviedosmiles.com/our-locations | R74: https://www.google.com/maps/search/?api=1&query=252+Plaza+Dr+Seminole+FL | T74: =IF(OR(J74="",D74=""),"Unknown",IF(LEFT(D74,4)*1-J74*1<=10,"New",IF(LEFT(D74,4)*1-J74*1<=25,"Normal","Old"))) -> Old | U74: Yes | V74: =LEFT(D74,4)*1 -> 2025 | W74: 1. < 3K SF
A75: 3 | B75: 2605 Ocoee Apopka Rd | C75: Orange | D75: 2023/05 | E75: 1140000 | F75: =E75/G75 -> 276.90066 | G75: 4117 | H75: 5455 | I75: Elegantly Dental | J75: 2009 | K75: 1900 | L75: OCOPUD | M75: 2228 06 2856 01 000 | N75: Medical | O75: High | P75: **Elegantly Dental** | Q75: https://www.elegantlydental.com/ocoee-fl/ | R75: https://www.google.com/maps/search/2605+Ocoee+Apopka+Rd,+FL | T75: =IF(OR(J75="",D75=""),"Unknown",IF(LEFT(D75,4)*1-J75*1<=10,"New",IF(LEFT(D75,4)*1-J75*1<=25,"Normal","Old"))) -> Normal | U75: Yes | V75: =LEFT(D75,4)*1 -> 2023 | W75: 2. 3 - 6K SF
A76: 3 | B76: 261 Airport Blvd E | C76: Seminole | D76: 2021/04 | E76: 600000 | F76: =E76/G76 -> 173.81228 | G76: 3452 | H76: 3452 | I76: Wolf Chiropractic Kissimmee | J76: 1980 | K76: 19 | M76: 2030 12 300 012H 0000 | N76: Medical | O76: Medium | P76: Vacant Medical Office (For Sale) | Q76: https://www.realty.com/commercial-listings/361178951/261-E-Airport-Boulevard-Sanford-FL-32773 | R76: https://www.google.com/maps?q=261+Airport+Blvd+E+Seminole,+FL | T76: =IF(OR(J76="",D76=""),"Unknown",IF(LEFT(D76,4)*1-J76*1<=10,"New",IF(LEFT(D76,4)*1-J76*1<=25,"Normal","Old"))) -> Old | U76: Yes | V76: =LEFT(D76,4)*1 -> 2021 | W76: 2. 3 - 6K SF
A77: 3 | B77: 2610 Audrey Av | C77: Orange | D77: 2021/10 | E77: 366400 | F77: =E77/G77 -> 127.39917 | G77: 2876 | H77: 2936 | I77: Desai Dental (Winter Park Family Dentist) | J77: 2023 | K77: 1900 | L77: WPO2 | M77: 2229 02 4168 00 660 | N77: Medical | O77: High | P77: **Desai Dental (Winter Park Family Dentist)** | Q77: https://www.carecredit.com/doctor-locator/winter-park-fl/desai-dental-234dhr/ | R77: https://www.google.com/maps/search/2610+Audrey+Av,+FL | T77: =IF(OR(J77="",D77=""),"Unknown",IF(LEFT(D77,4)*1-J77*1<=10,"New",IF(LEFT(D77,4)*1-J77*1<=25,"Normal","Old"))) -> New | U77: Yes | V77: =LEFT(D77,4)*1 -> 2021 | W77: 1. < 3K SF
A78: 3 | B78: 2610 Orlando Dr | C78: Seminole | D78: 2024/07 | E78: 800000 | F78: =E78/G78 -> 150.48909 | G78: 5316 | H78: 6024 | I78: South Orlando Drive Land Holding LLC | J78: 1988 | K78: 1902 | M78: 2030 01 504 1800 0110 | N78: Medical | O78: High | P78: Sanford Animal Hospital (Veterinary) | Q78: https://www.loopnet.com/Listing/2670-2690-S-Orlando-Dr-Sanford-FL/35204476/ | R78: https://www.google.com/maps?q=2610+Orlando+Dr+Seminole,+FL | T78: =IF(OR(J78="",D78=""),"Unknown",IF(LEFT(D78,4)*1-J78*1<=10,"New",IF(LEFT(D78,4)*1-J78*1<=25,"Normal","Old"))) -> Old | U78: Yes | V78: =LEFT(D78,4)*1 -> 2024 | W78: 2. 3 - 6K SF
A79: 3 | B79: 2702 Rew Ci | C79: Orange | D79: 2021/11 | E79: 1224900 | F79: =E79/G79 -> 236.14806 | G79: 5187 | H79: 5571 | I79: Marcast Properties & Management LLC | J79: 2003 | K79: 1900 | L79: OCOI1 | M79: 2228 29 9158 00 020 | N79: Medical | O79: Medium | P79: Vacant Medical/Office Space | Q79: https://www.loopnet.com/Listing/2702-Rew-Cir-Ocoee-FL/20805631/ | R79: https://www.google.com/maps/search/2702+Rew+Ci,+FL | T79: =IF(OR(J79="",D79=""),"Unknown",IF(LEFT(D79,4)*1-J79*1<=10,"New",IF(LEFT(D79,4)*1-J79*1<=25,"Normal","Old"))) -> Normal | U79: Yes | V79: =LEFT(D79,4)*1 -> 2021 | W79: 2. 3 - 6K SF
A80: 3 | B80: 2721 SR 434 W | C80: Seminole | D80: 2022/03 | E80: 510000 | F80: =E80/G80 -> 202.06022 | G80: 2524 | H80: 2524 | I80: Witt Dermatology (Dr. Amy Witt) | J80: 1966 | K80: 19 | M80: 2129 04 514 0C00 0050 | N80: Medical | O80: High | P80: **Witt Dermatology (Dr. Amy Witt)** | Q80: https://www.derrowdermatology.com/our-office/ | R80: https://www.google.com/maps/search/?api=1&query=2721+SR+434+W+Seminole+FL | T80: =IF(OR(J80="",D80=""),"Unknown",IF(LEFT(D80,4)*1-J80*1<=10,"New",IF(LEFT(D80,4)*1-J80*1<=25,"Normal","Old"))) -> Old | U80: Yes | V80: =LEFT(D80,4)*1 -> 2022 | W80: 1. < 3K SF
A81: 3 | B81: 2744 N Orange Blossom Trl | C81: Osceola | D81: 2024/05 | E81: 2414000 | F81: =E81/G81 -> 134.11111 | G81: 18000 | H81: 18720 | I81: Kind Ventures LLC | J81: 1983 | K81: 1911 | L81: OCR | M81: 2529 10 0000 0160 0000 | N81: Medical | O81: High | P81: Mayfair Pet Hospital (Veterinary) | Q81: https://mayfairpetvets.com/ | R81: https://www.google.com/maps/search/2744+N+Orange+Blossom+Trl+Osceola+FL | T81: =IF(OR(J81="",D81=""),"Unknown",IF(LEFT(D81,4)*1-J81*1<=10,"New",IF(LEFT(D81,4)*1-J81*1<=25,"Normal","Old"))) -> Old | U81: Yes | V81: =LEFT(D81,4)*1 -> 2024 | W81: 4. 10 - 20K SF
A82: 3 | B82: 2905 Mcrae Av | C82: Orange | D82: 2022/08 | E82: 4900000 | F82: =E82/G82 -> 850.69444 | G82: 5760 | H82: 7120 | I82: Adventist Health System/Sunbelt Inc Attn: Adventhealth Accounting Dept | J82: 1971 | K82: 1900 | L82: ORLMU1 | M82: 2229 13 2784 01 031 | N82: Medical | O82: High | P82: **AdventHealth (Hospital Support/Admin)** | Q82: https://npiregistry.cms.hhs.gov/provider-view/1841680733 | R82: https://www.google.com/maps/search/2905+Mcrae+Av+Orange+FL | T82: =IF(OR(J82="",D82=""),"Unknown",IF(LEFT(D82,4)*1-J82*1<=10,"New",IF(LEFT(D82,4)*1-J82*1<=25,"Normal","Old"))) -> Old | V82: =LEFT(D82,4)*1 -> 2022 | W82: 2. 3 - 6K SF
A83: 3 | B83: 2940 Maguire Rd | C83: Orange | D83: 2022/04 | E83: 4030000 | F83: =E83/G83 -> 494.5999 | G83: 8148 | H83: 8250 | I83: PremierMED Family Practice & Sports Medicine | J83: 2018 | K83: 1900 | L83: OCOPUD | M83: 2228 32 5475 00 040 | N83: Medical | O83: High | P83: **PremierMED Family Practice & Sports Medicine** | Q83: https://www.premierfsm.com/contact/ocoee/ | R83: https://www.google.com/maps/search/2940+Maguire+Rd,+FL | T83: =IF(OR(J83="",D83=""),"Unknown",IF(LEFT(D83,4)*1-J83*1<=10,"New",IF(LEFT(D83,4)*1-J83*1<=25,"Normal","Old"))) -> New | U83: Yes | V83: =LEFT(D83,4)*1 -> 2022 | W83: 3. 6 - 10K SF
A84: 3 | B84: 300 Hazel St E | C84: Orange | D84: 2023/08 | E84: 846000 | F84: =E84/G84 -> 328.03412 | G84: 2579 | H84: 2609 | I84: The Dermatology Group PA | J84: 1984 | K84: 1900 | L84: ORLO2/ | M84: 2229 13 7108 01 070 | N84: Medical | O84: High | P84: **The Dermatology Group PA** | Q84: https://www.dermgroup.net/ | R84: https://www.google.com/maps/search/300+Hazel+St+E+Orange+FL | T84: =IF(OR(J84="",D84=""),"Unknown",IF(LEFT(D84,4)*1-J84*1<=10,"New",IF(LEFT(D84,4)*1-J84*1<=25,"Normal","Old"))) -> Old | U84: Yes | V84: =LEFT(D84,4)*1 -> 2023 | W84: 1. < 3K SF
A85: 3 | B85: 3000 Orange Av N | C85: Orange | D85: 2020/09 | E85: 1987500 | F85: =E85/G85 -> 311.08155 | G85: 6389 | H85: 6421 | I85: Adventist Health System/Sunbelt Inc Attn: Adventhealth Accounting Dept | J85: 1994 | K85: 1900 | L85: ORLMU1 | M85: 2229 13 0540 01 011 | N85: Medical | O85: High | P85: AdventHealth Medical Group Pediatric Rheumatology at Orlando | Q85: https://www.adventhealth.com/practice/adventhealth-medical-group/find-a-location?page=68 | R85: https://www.google.com/maps/search/3000+Orange+Av+N+Orange+FL | T85: =IF(OR(J85="",D85=""),"Unknown",IF(LEFT(D85,4)*1-J85*1<=10,"New",IF(LEFT(D85,4)*1-J85*1<=25,"Normal","Old"))) -> Old | U85: Yes | V85: =LEFT(D85,4)*1 -> 2020 | W85: 3. 6 - 10K SF
A86: 3 | B86: 3016 Dyer Blvd | C86: Osceola | D86: 2021/11 | E86: 925000 | F86: =E86/G86 -> 155.46218 | G86: 5950 | H86: 6440 | I86: Radiology and Imaging Specialists (RIS) | J86: 2022 | K86: 1911 | L86: KMPU | M86: 2529 05 1882 0001 0060 | N86: Medical | O86: High | P86: **Radiology and Imaging Specialists (RIS)** | Q86: https://www.medicai.io/medical-imaging-providers/radiology-and-imaging-specialists-kissimmee-kissimmee-florida | R86: https://www.google.com/maps/search/3016+Dyer+Blvd+Osceola+FL | T86: =IF(OR(J86="",D86=""),"Unknown",IF(LEFT(D86,4)*1-J86*1<=10,"New",IF(LEFT(D86,4)*1-J86*1<=25,"Normal","Old"))) -> New | U86: Yes | V86: =LEFT(D86,4)*1 -> 2021 | W86: 2. 3 - 6K SF
A87: 3 | B87: 305 Childs St S | C87: Lake | D87: 2022/07 | E87: 399000 | F87: =E87/G87 -> 199.5 | G87: 2000 | H87: 2355 | I87: Center for Ankle & Foot Care (Podiatry) | J87: 2008 | K87: 1900 | M87: 1924 26 3900 056 00101 | N87: Medical | O87: High | P87: **Center for Ankle & Foot Care (Podiatry)** | Q87: https://www.centeranklefootcare.com/ | R87: https://www.google.com/maps?q=305+Childs+St+S+Lake,+FL | T87: =IF(OR(J87="",D87=""),"Unknown",IF(LEFT(D87,4)*1-J87*1<=10,"New",IF(LEFT(D87,4)*1-J87*1<=25,"Normal","Old"))) -> Normal | U87: Yes | V87: =LEFT(D87,4)*1 -> 2022 | W87: 1. < 3K SF
A88: 3 | B88: 307 Lagrande Blvd | C88: Lake | D88: 2020/08 | E88: 810000 | F88: =E88/G88 -> 322.96651 | G88: 2508 | H88: 2603 | I88: 307 Lagrande LLC | J88: 1988 | K88: 1900 | M88: 1824 07 0001 000 00105 | N88: Medical | O88: High | P88: Lady Lake Dentist - Universal Smiles Dentistry Villages | Q88: https://www.universalsmilesdentistry.com/The-Villages | R88: https://www.google.com/maps?q=307+Lagrande+Blvd+Lake,+FL | T88: =IF(OR(J88="",D88=""),"Unknown",IF(LEFT(D88,4)*1-J88*1<=10,"New",IF(LEFT(D88,4)*1-J88*1<=25,"Normal","Old"))) -> Old | U88: Yes | V88: =LEFT(D88,4)*1 -> 2020 | W88: 1. < 3K SF
A89: 3 | B89: 308 Groveland St | C89: Orange | D89: 2023/03 | E89: 1100000 | F89: =E89/G89 -> 373.51443 | G89: 2945 | H89: 3484 | I89: No longer Dr. Renee J. Mueller, MD (Colon and Rectal) | J89: 1980 | K89: 1900 | L89: ORLO2/ | M89: 2229 13 6652 00 050 | N89: Medical | O89: High | P89: No longer Dr. Renee J. Mueller, MD (Colon and Rectal)** | Q89: https://www.orlandohealth.com/physician-finder/renee-mueller-md | R89: https://www.google.com/maps/search/308+Groveland+St+Orange+FL | T89: =IF(OR(J89="",D89=""),"Unknown",IF(LEFT(D89,4)*1-J89*1<=10,"New",IF(LEFT(D89,4)*1-J89*1<=25,"Normal","Old"))) -> Old | U89: Yes | V89: =LEFT(D89,4)*1 -> 2023 | W89: 1. < 3K SF
A90: 3 | B90: 309 Orange St | C90: Lake | D90: 2022/12 | E90: 650000 | F90: =E90/G90 -> 135.41667 | G90: 4800 | H90: 4832 | I90: Davis Family Hearing Inc | J90: 1996 | K90: 1800 | M90: 1824 21 0003 000 05000 | N90: Medical | O90: High | P90: Davis Family Hearing | Q90: https://davisfamilyhearing.com/ | R90: https://www.google.com/maps?q=309+Orange+St+Lake,+FL | T90: =IF(OR(J90="",D90=""),"Unknown",IF(LEFT(D90,4)*1-J90*1<=10,"New",IF(LEFT(D90,4)*1-J90*1<=25,"Normal","Old"))) -> Old | U90: Yes | V90: =LEFT(D90,4)*1 -> 2022 | W90: 2. 3 - 6K SF
A91: 3 | B91: 32032 Burleigh Blvd W | C91: Lake | D91: 2020/09 | E91: 670000 | F91: =E91/G91 -> 135.40825 | G91: 4948 | H91: 5250 | I91: Burleigh Getting Started LLC | J91: 1977 | K91: 1900 | M91: 1926 29 0700 000 00002 | N91: Medical | O91: Medium | P91: Vacant Dental Office (Built-out) | Q91: https://www.loopnet.com/Listing/320-W-Burleigh-Blvd-Tavares-FL/18724440/ | R91: https://www.google.com/maps/search/32032+Burleigh+Blvd+W+Tavares+FL | T91: =IF(OR(J91="",D91=""),"Unknown",IF(LEFT(D91,4)*1-J91*1<=10,"New",IF(LEFT(D91,4)*1-J91*1<=25,"Normal","Old"))) -> Old | U91: Yes | V91: =LEFT(D91,4)*1 -> 2020 | W91: 2. 3 - 6K SF
A92: 3 | B92: 321 Maitland # 1000 Ave | C92: Seminole | D92: 2021/12 | E92: 486500 | F92: =E92/G92 -> 112.61574 | G92: 4320 | H92: 4320 | I92: 321 Maitland Avenue LLC & Healthventures Etal | J92: 1976 | K92: 19 | M92: 2129 13 506 0E00 0050 | N92: Medical | O92: High | P92: Kidz and Family Care LLC | Q92: https://www.kidzandfamilykare.com/ | R92: https://www.google.com/maps/search/?api=1&query=321+Maitland+%23+1000+Ave+Seminole+FL | T92: =IF(OR(J92="",D92=""),"Unknown",IF(LEFT(D92,4)*1-J92*1<=10,"New",IF(LEFT(D92,4)*1-J92*1<=25,"Normal","Old"))) -> Old | U92: Yes | V92: =LEFT(D92,4)*1 -> 2021 | W92: 2. 3 - 6K SF
A93: 3 | B93: 32629 Blossom Ln | C93: Lake | D93: 2020/07 | E93: 210000 | F93: =E93/G93 -> 108.63942 | G93: 1933 | H93: 2665 | I93: Lake Square Chiropractic Pa | J93: 1955 | K93: 1700 | M93: 1925 23 0002 000 02200 | N93: Medical | O93: High | P93: Lake Square Chiropractic | Q93: https://lake-square-chiropractic-p-a.wheree.com/ | R93: https://maps.google.com/?cid=2331465531235136251&g_mp=Cidnb29nbGUubWFwcy5wbGFjZXMudjEuUGxhY2VzLlNlYXJjaFRleHQ | T93: =IF(OR(J93="",D93=""),"Unknown",IF(LEFT(D93,4)*1-J93*1<=10,"New",IF(LEFT(D93,4)*1-J93*1<=25,"Normal","Old"))) -> Old | U93: Yes | V93: =LEFT(D93,4)*1 -> 2020 | W93: 1. < 3K SF
A94: 3 | B94: 3352 US Hwy 17 92 S | C94: Seminole | D94: 2020/03 | E94: 780000 | F94: =E94/G94 -> 87.847731 | G94: 8879 | H94: 8879 | I94: Casselberry Vec LLC | J94: 2023 | K94: 1902 | M94: 2130 08 510 EA00 0200 | N94: Medical | O94: High | P94: Veterinary Emergency Clinic of Central Florida | Q94: https://veconline.com/locations/casselberry/ | R94: https://www.google.com/maps/search/?api=1&query=3352+US+Hwy+17+92+S+Seminole+FL | T94: =IF(OR(J94="",D94=""),"Unknown",IF(LEFT(D94,4)*1-J94*1<=10,"New",IF(LEFT(D94,4)*1-J94*1<=25,"Normal","Old"))) -> New | V94: =LEFT(D94,4)*1 -> 2020 | W94: 3. 6 - 10K SF
A95: 3 | B95: 3600 Formosa Av | C95: Orange | D95: 2023/09 | E95: 850000 | F95: =E95/G95 -> 332.68102 | G95: 2555 | H95: 2555 | I95: Flossophy Commercial LLC | J95: 1965 | K95: 1900 | L95: ORLO1/ | M95: 2229 11 7620 00 130 | N95: Medical | O95: High | P95: Hillcrest Dental | Q95: https://www.carecredit.com/doctor-locator/orlando-fl/hillcrest-dental-222gct/ | R95: https://www.google.com/maps/search/3600+Formosa+Av+Orange+FL | T95: =IF(OR(J95="",D95=""),"Unknown",IF(LEFT(D95,4)*1-J95*1<=10,"New",IF(LEFT(D95,4)*1-J95*1<=25,"Normal","Old"))) -> Old | U95: Yes | V95: =LEFT(D95,4)*1 -> 2023 | W95: 1. < 3K SF
A96: 3 | B96: 3615 Lake Center Dr | C96: Lake | D96: 2025/04 | E96: 2050000 | F96: =E96/G96 -> 341.66667 | G96: 6000 | H96: 7100 | I96: Deukmedjian Armen And Robin De | J96: 2007 | K96: 1900 | M96: 1926 26 0701 000 00600 | N96: Medical | O96: High | P96: **Deuk Spine Institute (Dr. Deukmedjian)** | Q96: https://physiciansimaging.com/locations/mount-dora/ | R96: https://www.google.com/maps?q=3615+Lake+Center+Dr+Lake,+FL | T96: =IF(OR(J96="",D96=""),"Unknown",IF(LEFT(D96,4)*1-J96*1<=10,"New",IF(LEFT(D96,4)*1-J96*1<=25,"Normal","Old"))) -> Normal | U96: Yes | V96: =LEFT(D96,4)*1 -> 2025 | W96: 3. 6 - 10K SF
A97: 3 | B97: 400 Wymore Rd N | C97: Orange | D97: 2023/12 | E97: 800000 | F97: =E97/G97 -> 328.54209 | G97: 2435 | H97: 2435 | I97: Florida Emergency Medicine Foundation | J97: 1945 | K97: 1700 | L97: ORGPO | M97: 2229 02 4168 00 210 | N97: Medical | O97: High | P97: **Florida Emergency Medicine Foundation** | Q97: https://fcep.org/contact/ | R97: https://www.google.com/maps/search/400+Wymore+Rd+N,+FL | T97: =IF(OR(J97="",D97=""),"Unknown",IF(LEFT(D97,4)*1-J97*1<=10,"New",IF(LEFT(D97,4)*1-J97*1<=25,"Normal","Old"))) -> Old | U97: Yes | V97: =LEFT(D97,4)*1 -> 2023 | W97: 1. < 3K SF
A98: 3 | B98: 4020 Edgewater Dr | C98: Orange | D98: 2025/08 | E98: 830900 | F98: =E98/G98 -> 136.21311 | G98: 6100 | H98: 6330 | I98: 4020 Edgewater LLC | J98: 2024 | K98: 1700 | L98: ORGRST | M98: 2229 10 8828 06 130 | N98: Medical | O98: High | P98: Vacant / New Construction (Office/Medical Shell) | Q98: https://www.crexi.com/properties/1749832/florida-4020-edgewater-dr-orlando-fl-32804 | R98: https://www.google.com/maps/search/4020+Edgewater+Dr+Orange+FL | T98: =IF(OR(J98="",D98=""),"Unknown",IF(LEFT(D98,4)*1-J98*1<=10,"New",IF(LEFT(D98,4)*1-J98*1<=25,"Normal","Old"))) -> New | V98: =LEFT(D98,4)*1 -> 2025 | W98: 3. 6 - 10K SF
A99: 3 | B99: 404 Orange Blossom Tr W | C99: Orange | D99: 2025/05 | E99: 2000000 | F99: =E99/G99 -> 351.61744 | G99: 5688 | H99: 5723 | I99: Galvan Victor M | J99: 1986 | K99: 1700 | L99: APKMUD | M99: 2128 09 7544 02 030 | N99: Medical | O99: Medium | P99: South Apopka Medical Office (Vacant/Leasing) | Q99: https://www.loopnet.com/Listing/404-W-Orange-Blossom-Tr-Apopka-FL/28471952/ | R99: https://www.google.com/maps/search/404+Orange+Blossom+Tr+W,+FL | T99: =IF(OR(J99="",D99=""),"Unknown",IF(LEFT(D99,4)*1-J99*1<=10,"New",IF(LEFT(D99,4)*1-J99*1<=25,"Normal","Old"))) -> Old | U99: Yes | V99: =LEFT(D99,4)*1 -> 2025 | W99: 2. 3 - 6K SF
A100: 3 | B100: 405 Waymont Ct | C100: Seminole | D100: 2024/08 | E100: 725000 | F100: =E100/G100 -> 241.66667 | G100: 3000 | H100: 3000 | I100: Metricsmed Pr LLC | J100: 1999 | K100: 19 | M100: 2030 17 507 0000 0140 | N100: Medical | O100: High | P100: Rejuve Health Clinics Inc | Q100: https://www.bbb.org/us/fl/lake-mary/profile/hormone-replacement-therapy/rejuve-health-clinics-inc-0733-90335543 | R100: https://www.google.com/maps?q=405+Waymont+Ct+Seminole,+FL | T100: =IF(OR(J100="",D100=""),"Unknown",IF(LEFT(D100,4)*1-J100*1<=10,"New",IF(LEFT(D100,4)*1-J100*1<=25,"Normal","Old"))) -> Normal | U100: Yes | V100: =LEFT(D100,4)*1 -> 2024 | W100: 2. 3 - 6K SF
...

Sheet Outliers
A1: CENTRAL FLORIDA MEDICAL REAL ESTATE — FLAGGED OUTLIERS
A2: Properties flagged as outliers across 2020–2025 sales | Excluded from core comp set
A4: Property Address | B4: County | C4: Date | D4: Price | E4: $/SF | F4: Size (SF) | G4: Category | H4: Current Tenant | I4: Yr Built | J4: Building Age | K4: Reason | L4: Appraiser Link | M4: Year
A5: 750 Orienta Ave | B5: Seminole | C5: 2020/04 | D5: 550000 | E5: 45.3 | F5: 12140 | G5: Hospitals | H5: Florida Cancer Specialists MEDICAL CENTER | I5: 2023 | J5: New | K5: Bought before built (2023) | L5: https://www.scpafl.org/search/parcels/details/?APPRID=5333656 | M5: 2020
A6: 3352 US Hwy 17 92 S | B6: Seminole | C6: 2020/03 | D6: 780000 | E6: 87.85 | F6: 8879 | G6: Medical | H6: Veterinary Emergency Clinic of Central Florida | I6: 2023 | J6: New | K6: Bought before built (2023) | L6: https://www.scpafl.org/search/parcels/details/?APPRID=5189374 | M6: 2020
A7: 1513 N Main St | B7: Osceola | C7: 2020/12 | D7: 400000 | E7: 93.33 | F7: 4286 | G7: Medical | H7: Beaudry Animal Hospital /Osceola Animal Clinic (Veterinary) | I7: 1945 | J7: Old | K7: Super old | L7: https://search.property-appraiser.org/Search/MainSearch?pin=152529135000SL0010 | M7: 2020
A8: 101 Bellagio Cir | B8: Seminole | C8: 2020/08 | D8: 1340000 | E8: 517.97 | F8: 2587 | G8: Medical | H8: Coastal Mental Health Center (Condo) | I8: 2007 | J8: Normal | K8: Condo | L8: https://www.scpafl.org/search/parcels/details/?APPRID=5270636 | M8: 2020
A9: 129 Bellagio Cir | B9: Seminole | C9: 2020/08 | D9: 1340000 | E9: 623.26 | F9: 2150 | G9: Medical | H9: Towne Center Animal Hospital (Condo) | I9: 2007 | J9: Normal | K9: Condo | L9: https://www.scpafl.org/search/parcels/details/?APPRID=5270651 | M9: 2020
A10: 701 E Oak St | B10: Osceola | C10: 2020/10 | D10: 2450000 | E10: 714.7 | F10: 3428 | G10: Medical | H10: Yes! Dental Associates | I10: 1989 | J10: Old | K10: Extreme | L10: https://search.property-appraiser.org/Search/MainSearch?pin=222529149600010030 | M10: 2020
A11: 1350 Fairbanks Av W | B11: Orange | C11: 2020/12 | D11: 5300000 | E11: 903.82 | F11: 5864 | G11: Medical | H11: SimonMed Imaging - Winter Park | I11: 2021 | J11: New | K11: New SimonMed | L11: https://vgispublic.ocpafl.org/webmapjs/?pid=292212066400100 | M11: 2020
A12: 1221 Fairbanks Av W | B12: Orange | C12: 2021/11 | D12: 243300 | E12: 45.66 | F12: 5328 | G12: Medical | H12: Medi-Weightloss Center Winter Park | I12: 1971 | J12: Old | K12: Low Grade building | L12: https://vgispublic.ocpafl.org/webmapjs/?pid=292203100000060 | M12: 2021
A13: 6909 Old Hwy 441 | B13: Orange | C13: 2021/07 | D13: 3000000 | E13: 62.14 | F13: 48279 | G13: Multi-Tenant Medical | H13: Multi-Tenant (Endocrinology / Dialysis) | I13: 2008 | J13: Normal | K13: Multi tenant sale/ bad Cap Rate? | L13: https://vgispublic.ocpafl.org/webmapjs/?pid=272005309501000 | M13: 2021
A14: 1314 Sumter St | B14: Lake | C14: 2021/09 | D14: 545000 | E14: 72.86 | F14: 7480 | G14: Medical | H14: Family First Homecare (Pediatric) | I14: 2001 | J14: Normal | K14: Low Grade building | L14: https://lakecopropappr.com/property-details.aspx?AltKey=1239371 | M14: 2021
A15: 12323 Colonial Dr W | B15: Orange | C15: 2021/02 | D15: 1900000 | E15: 82.69 | F15: 22977 | G15: Multi-Tenant Medical | H15: Winter Garden ObGyn / ENT & Plastic Surgery | I15: 2022 | J15: New | K15: You guys know here? | L15: https://vgispublic.ocpafl.org/webmapjs/?pid=272224674704000 | M15: 2021
A16: 444 Mills Av N | B16: Orange | C16: 2021/10 | D16: 428300 | E16: 96.1 | F16: 4457 | G16: Medical | H16: Newman Plastic Surgery | I16: 1967 | J16: Old | K16: Sold for 1M in 2005 | L16: https://vgispublic.ocpafl.org/webmapjs/?pid=292225250801091 | M16: 2021
... A19: 1510 Colonial Dr E | B19: Orange | C19: 2022/04 | D19: 4411500 | E19: 83.65 | F19: 52735 | G19: Multi-Tenant Medical | H19: AJH Complete Care (Primary Care) | I19: 1960 | J19: Old | K19: Multi unit deal? Bad Cap rate/ old building? | L19: https://vgispublic.ocpafl.org/webmapjs/?pid=292225153601030 | M19: 2022
A20: 1122 SR 434 E | B20: Seminole | C20: 2022/11 | D20: 3735000 | E20: 647.09 | F20: 5772 | G20: Multi-Tenant Medical | H20: Smile Design Dentistry | I20: 2004 | J20: Normal | L20: https://www.scpafl.org/search/parcels/details/?APPRID=5329157 | M20: 2022
A21: 1445 Mitchell Hammock Rd E | B21: Seminole | C21: 2022/11 | D21: 3735000 | E21: 772.01 | F21: 4838 | G21: Medical | H21: Oviedo Premier Dental | I21: 2009 | J21: Normal | L21: https://www.scpafl.org/search/parcels/details/?APPRID=5296890 | M21: 2022
A22: 2905 Mcrae Av | B22: Orange | C22: 2022/08 | D22: 4900000 | E22: 850.69 | F22: 5760 | G22: Medical | H22: AdventHealth (Hospital Support/Admin) | I22: 1971 | J22: Old | K22: Advant Health | L22: https://vgispublic.ocpafl.org/webmapjs/?pid=292213278401031 | M22: 2022
A23: 454 Rinehart Rd | B23: Seminole | C23: 2023/10 | D23: 3889000 | E23: 136.43 | F23: 28506 | G23: Hospitals | H23: Orlando Health Jewett Orthopedic Institute MEDICAL CENTER | I23: 2024 | J23: New | K23: Built it | L23: https://www.scpafl.org/search/parcels/details/?APPRID=5367522 | M23: 2023
A24: 238 Orlando Av S | B24: Orange | C24: 2023/12 | D24: 3000000 | E24: 713.44 | F24: 4205 | G24: Medical | H24: Vision Source Maitland | I24: 2007 | J24: Normal | L24: https://vgispublic.ocpafl.org/webmapjs/?pid=292125651603020 | M24: 2023
A25: 126 Colonial Dr E | B25: Orange | C25: 2024/02 | D25: 3200000 | E25: 119.7 | F25: 26734 | G25: Multi-Tenant Medical | H25: Colonial Marketplace (Lifetime Eyecare) | I25: 1958 | J25: Old | K25: Old building and investment sale | L25: https://vgispublic.ocpafl.org/webmapjs/?pid=292225506400240 | M25: 2024
A26: 917 Rinehart # 1051 Rd | B26: Seminole | C26: 2024/07 | D26: 4225000 | E26: 479.57 | F26: 8810 | G26: Medical | H26: SimonMed Imaging (Lake Mary II) | I26: 2005 | J26: Normal | K26: Condo | L26: https://www.scpafl.org/search/parcels/details/?APPRID=5224560 | M26: 2024
A27: 2115 Orange Blossom Tr W | B27: Orange | C27: 2024/05 | D27: 3500000 | E27: 591.02 | F27: 5922 | G27: Hospitals | H27: Sanitas MEDICAL CENTER | I27: 2023 | J27: New | K27: Hospital, but too small to go under our "large buildings category" | L27: https://vgispublic.ocpafl.org/webmapjs/?pid=282106000000047 | M27: 2024
A28: 4020 Edgewater Dr | B28: Orange | C28: 2025/08 | D28: 830900 | E28: 136.21 | F28: 6100 | G28: Medical | H28: Vacant / New Construction (Office/Medical Shell) | I28: 2024 | J28: New | K28: New build up | L28: https://vgispublic.ocpafl.org/webmapjs/?pid=292210882806130 | M28: 2025
A29: 5165 Adanson St | B29: Orange | C29: 2025/06 | D29: 3200000 | E29: 147.51 | F29: 21694 | G29: Medical | H29: Central Florida Dreamplex (Disability Therapy) | I29: 1978 | J29: Old | K29: weird building /old | L29: https://vgispublic.ocpafl.org/webmapjs/?pid=292202000000062 | M29: 2025
A30: 5749 Westgate Dr | B30: Orange | C30: 2025/03 | D30: 6850000 | E30: 155.79 | F30: 43969 | G30: Multi-Tenant Medical | H30: Vacant Medical/Wellness Buildout | I30: 2008 | J30: Normal | K30: Not all medical | L30: https://vgispublic.ocpafl.org/webmapjs/?pid=282236494901000 | M30: 2025
A31: 54 Plant St E | B31: Orange | C31: 2025/03 | D31: 3200000 | E31: 893.85 | F31: 3580 | G31: Medical | H31: Anton Rx (Pharmacy) | I31: 1983 | J31: Old | K31: Extreme | L31: https://vgispublic.ocpafl.org/webmapjs/?pid=272223288801040 | M31: 2025
A32: 11625 Lachlan Ln | B32: Orange | C32: 2025/06 | D32: 3473802 | E32: 915.12 | F32: 3796 | G32: Medical | H32: Dental Care at Westside Shoppes | I32: 2017 | J32: New | K32: Extreme | L32: https://vgispublic.ocpafl.org/webmapjs/?pid=272325583902000 | M32: 2025
A33: 723 Virginia Dr | B33: Orange | C33: 2025/04 | D33: 2097400 | E33: 1048.7 | F33: 2000 | G33: Medical | H33: Radiance Health Rx (Pharmacy & Wellness) | I33: 1973 | J33: Old | K33: Extreme | L33: https://vgispublic.ocpafl.org/webmapjs/?pid=292213942902310 | M33: 2025
A35: Total Outliers: | B35: =COUNTA(A5:A33) -> 29

Sheet 2020
A1: CENTRAL FLORIDA MEDICAL REAL ESTATE — 2020 ANNUAL REPORT
A2: Medical Office Building Sales | January–December 2020 | Orange, Seminole, Osceola & Lake Counties
A4: 2020 SNAPSHOT SUMMARY | M4: Category | N4: # Sales
A5: Category | B5: # Sales | C5: Total Volume | D5: Avg Price | E5: Median Price | F5: Avg $/SF | G5: Median $/SF | H5: Avg Size (SF) | I5: Min Price | J5: Max Price | M5: Medical | N5: =B6 -> 6
A6: Medical | B6: {=SUMPRODUCT(('Medical Sales'!N3:N196="Medical")*(LEFT('Medical Sales'!D3:D196,4)="2020")*('Medical Sales'!U3:U196<>"Yes"))} -> 6 | C6: {=SUMPRODUCT(('Medical Sales'!N3:N196="Medical")*(LEFT('Medical Sales'!D3:D196,4)="2020")*('Medical Sales'!U3:U196<>"Yes")*('Medical Sales'!E3:E196))} -> 11610000 | D6: =IF(B6=0,"-",C6/B6) -> 1935000 | E6: {=MEDIAN(IF(('Medical Sales'!N3:N196="Medical")*(LEFT('Medical Sales'!D3:D196,4)="2020")*('Medical Sales'!U3:U196<>"Yes"),'Medical Sales'!E3:E196))} -> 1340000 | F6: {=IF(B6=0,"-",SUMPRODUCT(('Medical Sales'!N3:N196="Medical")*(LEFT('Medical Sales'!D3:D196,4)="2020")*('Medical Sales'!U3:U196<>"Yes")*('Medical Sales'!F3:F196))/B6)} -> 490.15459 | G6: {=MEDIAN(IF(('Medical Sales'!N3:N196="Medical")*(LEFT('Medical Sales'!D3:D196,4)="2020")*('Medical Sales'!U3:U196<>"Yes"),'Medical Sales'!F3:F196))} -> 570.61515 | H6: {=IF(B6=0,"-",SUMPRODUCT(('Medical Sales'!N3:N196="Medical")*(LEFT('Medical Sales'!D3:D196,4)="2020")*('Medical Sales'!U3:U196<>"Yes")*('Medical Sales'!G3:G196))/B6)} -> 4532.3333 | I6: {=MIN(IF(('Medical Sales'!N3:N196="Medical")*(LEFT('Medical Sales'!D3:D196,4)="2020")*('Medical Sales'!U3:U196<>"Yes"),'Medical Sales'!E3:E196))} -> 400000 | J6: {=MAX(IF(('Medical Sales'!N3:N196="Medical")*(LEFT('Medical Sales'!D3:D196,4)="2020")*('Medical Sales'!U3:U196<>"Yes"),'Medical Sales'!E3:E196))} -> 5300000 | M6: Multi-Tenant | N6: =B7 -> 0 | O6: =C7 -> 0
A7: Multi-Tenant Medical | B7: {=SUMPRODUCT(('Medical Sales'!N3:N196="Multi-Tenant Medical")*(LEFT('Medical Sales'!D3:D196,4)="2020")*('Medical Sales'!U3:U196<>"Yes"))} -> 0 | C7: {=SUMPRODUCT(('Medical Sales'!N3:N196="Multi-Tenant Medical")*(LEFT('Medical Sales'!D3:D196,4)="2020")*('Medical Sales'!U3:U196<>"Yes")*('Medical Sales'!E3:E196))} -> 0 | D7: =IF(B7=0,"-",C7/B7) -> - | E7: {=MEDIAN(IF(('Medical Sales'!N3:N196="Multi-Tenant Medical")*(LEFT('Medical Sales'!D3:D196,4)="2020")*('Medical Sales'!U3:U196<>"Yes"),'Medical Sales'!E3:E196))} -> #NUM! | F7: {=IF(B7=0,"-",SUMPRODUCT(('Medical Sales'!N3:N196="Multi-Tenant Medical")*(LEFT('Medical Sales'!D3:D196,4)="2020")*('Medical Sales'!U3:U196<>"Yes")*('Medical Sales'!F3:F196))/B7)} -> - | G7: {=MEDIAN(IF(('Medical Sales'!N3:N196="Multi-Tenant Medical")*(LEFT('Medical Sales'!D3:D196,4)="2020")*('Medical Sales'!U3:U196<>"Yes"),'Medical Sales'!F3:F196))} -> #NUM! | H7: {=IF(B7=0,"-",SUMPRODUCT(('Medical Sales'!N3:N196="Multi-Tenant Medical")*(LEFT('Medical Sales'!D3:D196,4)="2020")*('Medical Sales'!U3:U196<>"Yes")*('Medical Sales'!G3:G196))/B7)} -> - | I7: {=MIN(IF(('Medical Sales'!N3:N196="Multi-Tenant Medical")*(LEFT('Medical Sales'!D3:D196,4)="2020")*('Medical Sales'!U3:U196<>"Yes"),'Medical Sales'!E3:E196))} -> 0 | J7: {=MAX(IF(('Medical Sales'!N3:N196="Multi-Tenant Medical")*(LEFT('Medical Sales'!D3:D196,4)="2020")*('Medical Sales'!U3:U196<>"Yes"),'Medical Sales'!E3:E196))} -> 0 | M7: Hospitals | N7: =B8 -> 1 | O7: =C8 -> 550000
A8: Hospitals | B8: {=SUMPRODUCT(('Medical Sales'!N3:N196="Hospitals")*(LEFT('Medical Sales'!D3:D196,4)="2020")*('Medical Sales'!U3:U196<>"Yes"))} -> 1 | C8: {=SUMPRODUCT(('Medical Sales'!N3:N196="Hospitals")*(LEFT('Medical Sales'!D3:D196,4)="2020")*('Medical Sales'!U3:U196<>"Yes")*('Medical Sales'!E3:E196))} -> 550000 | D8: =IF(B8=0,"-",C8/B8) -> 550000 | E8: {=IFERROR(MEDIAN(IF(('Medical Sales'!N3:N196="Hospitals")*(LEFT('Medical Sales'!D3:D196,4)="2020")*('Medical Sales'!U3:U196<>"Yes"),'Medical Sales'!E3:E196)),"-")} -> 550000 | F8: {=IF(B8=0,"-",SUMPRODUCT(('Medical Sales'!N3:N196="Hospitals")*(LEFT('Medical Sales'!D3:D196,4)="2020")*('Medical Sales'!U3:U196<>"Yes")*('Medical Sales'!F3:F196))/B8)} -> 45.304778 | G8: {=IFERROR(MEDIAN(IF(('Medical Sales'!N3:N196="Hospitals")*(LEFT('Medical Sales'!D3:D196,4)="2020")*('Medical Sales'!U3:U196<>"Yes"),'Medical Sales'!F3:F196)),"-")} -> 45.304778 | H8: {=IF(B8=0,"-",SUMPRODUCT(('Medical Sales'!N3:N196="Hospitals")*(LEFT('Medical Sales'!D3:D196,4)="2020")*('Medical Sales'!U3:U196<>"Yes")*('Medical Sales'!G3:G196))/B8)} -> 12140 | I8: {=IFERROR(MIN(IF(('Medical Sales'!N3:N196="Hospitals")*(LEFT('Medical Sales'!D3:D196,4)="2020")*('Medical Sales'!U3:U196<>"Yes"),'Medical Sales'!E3:E196)),"-")} -> 550000 | J8: {=IFERROR(MAX(IF(('Medical Sales'!N3:N196="Hospitals")*(LEFT('Medical Sales'!D3:D196,4)="2020")*('Medical Sales'!U3:U196<>"Yes"),'Medical Sales'!E3:E196)),"-")} -> 550000
A9: TOTAL | B9: =SUM(B6:B8) -> 7 | C9: =SUM(C6:C8) -> 12160000 | D9: =IF(B9=0,"-",C9/B9) -> 1737142.9 | E9: {=MEDIAN(IF((LEFT('Medical Sales'!D3:D196,4)="2020")*('Medical Sales'!U3:U196<>"Yes"),'Medical Sales'!E3:E196))} -> 1340000 | F9: {=IF(B9=0,"-",SUMPRODUCT((LEFT('Medical Sales'!D3:D196,4)="2020")*('Medical Sales'!U3:U196<>"Yes")*('Medical Sales'!F3:F196))/SUMPRODUCT((LEFT('Medical Sales'!D3:D196,4)="2020")*('Medical Sales'!U3:U196<>"Yes")*('Medical Sales'!F3:F196<>0)*1))} -> 426.60461 | G9: {=MEDIAN(IF((LEFT('Medical Sales'!D3:D196,4)="2020")*('Medical Sales'!U3:U196<>"Yes"),'Medical Sales'!F3:F196))} -> 517.97449 | H9: {=IF(B9=0,"-",SUMPRODUCT((LEFT('Medical Sales'!D3:D196,4)="2020")*('Medical Sales'!U3:U196<>"Yes")*('Medical Sales'!G3:G196))/B9)} -> 5619.1429 | I9: {=MIN(IF((LEFT('Medical Sales'!D3:D196,4)="2020")*('Medical Sales'!U3:U196<>"Yes"),'Medical Sales'!E3:E196))} -> 400000 | J9: {=MAX(IF((LEFT('Medical Sales'!D3:D196,4)="2020")*('Medical Sales'!U3:U196<>"Yes"),'Medical Sales'!E3:E196))} -> 5300000
M10: County | N10: # Sales | O10: Median $/SF
A11: COUNTY BREAKDOWN — 2020 | M11: Orange | N11: =B13 -> 1 | O11: =G13 -> 903.81992
A12: County | B12: # Sales | C12: Total Volume | D12: Avg Price | E12: Median Price | F12: Avg $/SF | G12: Median $/SF | H12: Avg Size (SF) | I12: Min Price | J12: Max Price | M12: Seminole | N12: =B14 -> 4 | O12: =G14 -> 302.91111
A13: Orange | B13: {=SUMPRODUCT(('Medical Sales'!C3:C196="Orange")*(LEFT('Medical Sales'!D3:D196,4)="2020")*('Medical Sales'!U3:U196<>"Yes"))} -> 1 | C13: {=SUMPRODUCT(('Medical Sales'!C3:C196="Orange")*(LEFT('Medical Sales'!D3:D196,4)="2020")*('Medical Sales'!U3:U196<>"Yes")*('Medical Sales'!E3:E196))} -> 5300000 | D13: =IF(B13=0,"-",C13/B13) -> 5300000 | E13: {=IFERROR(MEDIAN(IF(('Medical Sales'!C3:C196="Orange")*(LEFT('Medical Sales'!D3:D196,4)="2020")*('Medical Sales'!U3:U196<>"Yes"),'Medical Sales'!E3:E196)),"-")} -> 5300000 | F13: {=IF(B13=0,"-",SUMPRODUCT(('Medical Sales'!C3:C196="Orange")*(LEFT('Medical Sales'!D3:D196,4)="2020")*('Medical Sales'!U3:U196<>"Yes")*('Medical Sales'!F3:F196))/B13)} -> 903.81992 | G13: {=IFERROR(MEDIAN(IF(('Medical Sales'!C3:C196="Orange")*(LEFT('Medical Sales'!D3:D196,4)="2020")*('Medical Sales'!U3:U196<>"Yes"),'Medical Sales'!F3:F196)),"-")} -> 903.81992 | H13: {=IF(B13=0,"-",SUMPRODUCT(('Medical Sales'!C3:C196="Orange")*(LEFT('Medical Sales'!D3:D196,4)="2020")*('Medical Sales'!U3:U196<>"Yes")*('Medical Sales'!G3:G196))/B13)} -> 5864 | I13: {=IFERROR(MIN(IF(('Medical Sales'!C3:C196="Orange")*(LEFT('Medical Sales'!D3:D196,4)="2020")*('Medical Sales'!U3:U196<>"Yes"),'Medical Sales'!E3:E196)),"-")} -> 5300000 | J13: {=IFERROR(MAX(IF(('Medical Sales'!C3:C196="Orange")*(LEFT('Medical Sales'!D3:D196,4)="2020")*('Medical Sales'!U3:U196<>"Yes"),'Medical Sales'!E3:E196)),"-")} -> 5300000 | M13: Osceola | N13: =B15 -> 2 | O13: =G15 -> 404.01478
A14: Seminole | B14: {=SUMPRODUCT(('Medical Sales'!C3:C196="Seminole")*(LEFT('Medical Sales'!D3:D196,4)="2020")*('Medical Sales'!U3:U196<>"Yes"))} -> 4 | C14: {=SUMPRODUCT(('Medical Sales'!C3:C196="Seminole")*(LEFT('Medical Sales'!D3:D196,4)="2020")*('Medical Sales'!U3:U196<>"Yes")*('Medical Sales'!E3:E196))} -> 4010000 | D14: =IF(B14=0,"-",C14/B14) -> 1002500 | E14: {=IFERROR(MEDIAN(IF(('Medical Sales'!C3:C196="Seminole")*(LEFT('Medical Sales'!D3:D196,4)="2020")*('Medical Sales'!U3:U196<>"Yes"),'Medical Sales'!E3:E196)),"-")} -> 1060000 | F14: {=IF(B14=0,"-",SUMPRODUCT(('Medical Sales'!C3:C196="Seminole")*(LEFT('Medical Sales'!D3:D196,4)="2020")*('Medical Sales'!U3:U196<>"Yes")*('Medical Sales'!F3:F196))/B14)} -> 318.5957 | G14: {=IFERROR(MEDIAN(IF(('Medical Sales'!C3:C196="Seminole")*(LEFT('Medical Sales'!D3:D196,4)="2020")*('Medical Sales'!U3:U196<>"Yes"),'Medical Sales'!F3:F196)),"-")} -> 302.91111 | H14: {=IF(B14=0,"-",SUMPRODUCT(('Medical Sales'!C3:C196="Seminole")*(LEFT('Medical Sales'!D3:D196,4)="2020")*('Medical Sales'!U3:U196<>"Yes")*('Medical Sales'!G3:G196))/B14)} -> 6439 | I14: {=IFERROR(MIN(IF(('Medical Sales'!C3:C196="Seminole")*(LEFT('Medical Sales'!D3:D196,4)="2020")*('Medical Sales'!U3:U196<>"Yes"),'Medical Sales'!E3:E196)),"-")} -> 550000 | J14: {=IFERROR(MAX(IF(('Medical Sales'!C3:C196="Seminole")*(LEFT('Medical Sales'!D3:D196,4)="2020")*('Medical Sales'!U3:U196<>"Yes"),'Medical Sales'!E3:E196)),"-")} -> 1340000 | M14: Lake | N14: =B16 -> 0 | O14: =G16 -> -
A15: Osceola | B15: {=SUMPRODUCT(('Medical Sales'!C3:C196="Osceola")*(LEFT('Medical Sales'!D3:D196,4)="2020")*('Medical Sales'!U3:U196<>"Yes"))} -> 2 | C15: {=SUMPRODUCT(('Medical Sales'!C3:C196="Osceola")*(LEFT('Medical Sales'!D3:D196,4)="2020")*('Medical Sales'!U3:U196<>"Yes")*('Medical Sales'!E3:E196))} -> 2850000 | D15: =IF(B15=0,"-",C15/B15) -> 1425000 | E15: {=IFERROR(MEDIAN(IF(('Medical Sales'!C3:C196="Osceola")*(LEFT('Medical Sales'!D3:D196,4)="2020")*('Medical Sales'!U3:U196<>"Yes"),'Medical Sales'!E3:E196)),"-")} -> 1425000 | F15: {=IF(B15=0,"-",SUMPRODUCT(('Medical Sales'!C3:C196="Osceola")*(LEFT('Medical Sales'!D3:D196,4)="2020")*('Medical Sales'!U3:U196<>"Yes")*('Medical Sales'!F3:F196))/B15)} -> 404.01478 | G15: {=IFERROR(MEDIAN(IF(('Medical Sales'!C3:C196="Osceola")*(LEFT('Medical Sales'!D3:D196,4)="2020")*('Medical Sales'!U3:U196<>"Yes"),'Medical Sales'!F3:F196)),"-")} -> 404.01478 | H15: {=IF(B15=0,"-",SUMPRODUCT(('Medical Sales'!C3:C196="Osceola")*(LEFT('Medical Sales'!D3:D196,4)="2020")*('Medical Sales'!U3:U196<>"Yes")*('Medical Sales'!G3:G196))/B15)} -> 3857 | I15: {=IFERROR(MIN(IF(('Medical Sales'!C3:C196="Osceola")*(LEFT('Medical Sales'!D3:D196,4)="2020")*('Medical Sales'!U3:U196<>"Yes"),'Medical Sales'!E3:E196)),"-")} -> 400000 | J15: {=IFERROR(MAX(IF(('Medical Sales'!C3:C196="Osceola")*(LEFT('Medical Sales'!D3:D196,4)="2020")*('Medical Sales'!U3:U196<>"Yes"),'Medical Sales'!E3:E196)),"-")} -> 2450000
A16: Lake | B16: {=SUMPRODUCT(('Medical Sales'!C3:C196="Lake")*(LEFT('Medical Sales'!D3:D196,4)="2020")*('Medical Sales'!U3:U196<>"Yes"))} -> 0 | C16: {=SUMPRODUCT(('Medical Sales'!C3:C196="Lake")*(LEFT('Medical Sales'!D3:D196,4)="2020")*('Medical Sales'!U3:U196<>"Yes")*('Medical Sales'!E3:E196))} -> 0 | D16: =IF(B16=0,"-",C16/B16) -> - | E16: {=IFERROR(MEDIAN(IF(('Medical Sales'!C3:C196="Lake")*(LEFT('Medical Sales'!D3:D196,4)="2020")*('Medical Sales'!U3:U196<>"Yes"),'Medical Sales'!E3:E196)),"-")} -> - | F16: {=IF(B16=0,"-",SUMPRODUCT(('Medical Sales'!C3:C196="Lake")*(LEFT('Medical Sales'!D3:D196,4)="2020")*('Medical Sales'!U3:U196<>"Yes")*('Medical Sales'!F3:F196))/B16)} -> - | G16: {=IFERROR(MEDIAN(IF(('Medical Sales'!C3:C196="Lake")*(LEFT('Medical Sales'!D3:D196,4)="2020")*('Medical Sales'!U3:U196<>"Yes"),'Medical Sales'!F3:F196)),"-")} -> - | H16: {=IF(B16=0,"-",SUMPRODUCT(('Medical Sales'!C3:C196="Lake")*(LEFT('Medical Sales'!D3:D196,4)="2020")*('Medical Sales'!U3:U196<>"Yes")*('Medical Sales'!G3:G196))/B16)} -> - | I16: {=IFERROR(MIN(IF(('Medical Sales'!C3:C196="Lake")*(LEFT('Medical Sales'!D3:D196,4)="2020")*('Medical Sales'!U3:U196<>"Yes"),'Medical Sales'!E3:E196)),"-")} -> 0 | J16: {=IFERROR(MAX(IF(('Medical Sales'!C3:C196="Lake")*(LEFT('Medical Sales'!D3:D196,4)="2020")*('Medical Sales'!U3:U196<>"Yes"),'Medical Sales'!E3:E196)),"-")} -> 0
A18: MEDICAL ONLY (Excluding Hospitals) — Cleaner Comp Set
A19: County | B19: # Sales | C19: Total Volume | D19: Avg Price | E19: Median Price | F19: Avg $/SF | G19: Median $/SF | H19: Avg Size (SF) | I19: Min Price | J19: Max Price
A20: Orange (excl. Hospitals) | B20: {=SUMPRODUCT(('Medical Sales'!C3:C196="Orange")*(LEFT('Medical Sales'!D3:D196,4)="2020")*('Medical Sales'!N3:N196<>"Hospitals")*('Medical Sales'!U3:U196<>"Yes"))} -> 1 | C20: {=SUMPRODUCT(('Medical Sales'!C3:C196="Orange")*(LEFT('Medical Sales'!D3:D196,4)="2020")*('Medical Sales'!N3:N196<>"Hospitals")*('Medical Sales'!U3:U196<>"Yes")*('Medical Sales'!E3:E196))} -> 5300000 | D20: =IF(B20=0,"-",C20/B20) -> 5300000 | E20: {=IFERROR(MEDIAN(IF(('Medical Sales'!C3:C196="Orange")*(LEFT('Medical Sales'!D3:D196,4)="2020")*('Medical Sales'!N3:N196<>"Hospitals")*('Medical Sales'!U3:U196<>"Yes"),'Medical Sales'!E3:E196)),"-")} -> 5300000 | F20: {=IF(B20=0,"-",SUMPRODUCT(('Medical Sales'!C3:C196="Orange")*(LEFT('Medical Sales'!D3:D196,4)="2020")*('Medical Sales'!N3:N196<>"Hospitals")*('Medical Sales'!U3:U196<>"Yes")*('Medical Sales'!F3:F196))/B20)} -> 903.81992 | G20: {=IFERROR(MEDIAN(IF(('Medical Sales'!C3:C196="Orange")*(LEFT('Medical Sales'!D3:D196,4)="2020")*('Medical Sales'!N3:N196<>"Hospitals")*('Medical Sales'!U3:U196<>"Yes"),'Medical Sales'!F3:F196)),"-")} -> 903.81992 | H20: {=IF(B20=0,"-",SUMPRODUCT(('Medical Sales'!C3:C196="Orange")*(LEFT('Medical Sales'!D3:D196,4)="2020")*('Medical Sales'!N3:N196<>"Hospitals")*('Medical Sales'!U3:U196<>"Yes")*('Medical Sales'!G3:G196))/B20)} -> 5864 | I20: {=IFERROR(MIN(IF(('Medical Sales'!C3:C196="Orange")*(LEFT('Medical Sales'!D3:D196,4)="2020")*('Medical Sales'!N3:N196<>"Hospitals")*('Medical Sales'!U3:U196<>"Yes"),'Medical Sales'!E3:E196)),"-")} -> 5300000 | J20: {=IFERROR(MAX(IF(('Medical Sales'!C3:C196="Orange")*(LEFT('Medical Sales'!D3:D196,4)="2020")*('Medical Sales'!N3:N196<>"Hospitals")*('Medical Sales'!U3:U196<>"Yes"),'Medical Sales'!E3:E196)),"-")} -> 5300000
A21: All Counties (excl. Hospitals) | B21: {=SUMPRODUCT((LEFT('Medical Sales'!D3:D196,4)="2020")*('Medical Sales'!N3:N196<>"Hospitals")*('Medical Sales'!U3:U196<>"Yes"))} -> 6 | C21: {=SUMPRODUCT((LEFT('Medical Sales'!D3:D196,4)="2020")*('Medical Sales'!N3:N196<>"Hospitals")*('Medical Sales'!U3:U196<>"Yes")*('Medical Sales'!E3:E196))} -> 11610000 | D21: =IF(B21=0,"-",C21/B21) -> 1935000 | E21: {=MEDIAN(IF((LEFT('Medical Sales'!D3:D196,4)="2020")*('Medical Sales'!N3:N196<>"Hospitals")*('Medical Sales'!U3:U196<>"Yes"),'Medical Sales'!E3:E196))} -> 1340000 | F21: {=IF(B21=0,"-",SUMPRODUCT((LEFT('Medical Sales'!D3:D196,4)="2020")*('Medical Sales'!N3:N196<>"Hospitals")*('Medical Sales'!U3:U196<>"Yes")*('Medical Sales'!F3:F196))/B21)} -> 490.15459 | G21: {=MEDIAN(IF((LEFT('Medical Sales'!D3:D196,4)="2020")*('Medical Sales'!N3:N196<>"Hospitals")*('Medical Sales'!U3:U196<>"Yes"),'Medical Sales'!F3:F196))} -> 570.61515 | H21: {=IF(B21=0,"-",SUMPRODUCT((LEFT('Medical Sales'!D3:D196,4)="2020")*('Medical Sales'!N3:N196<>"Hospitals")*('Medical Sales'!U3:U196<>"Yes")*('Medical Sales'!G3:G196))/B21)} -> 4532.3333 | I21: {=MIN(IF((LEFT('Medical Sales'!D3:D196,4)="2020")*('Medical Sales'!N3:N196<>"Hospitals")*('Medical Sales'!U3:U196<>"Yes"),'Medical Sales'!E3:E196))} -> 400000 | J21: {=MAX(IF((LEFT('Medical Sales'!D3:D196,4)="2020")*('Medical Sales'!N3:N196<>"Hospitals")*('Medical Sales'!U3:U196<>"Yes"),'Medical Sales'!E3:E196))} -> 5300000
A22: NOTE: Hospitals have very different $/SF profiles ($79/SF avg in 2020) and can skew county medians. This section isolates true medical office comps.
M23: Buyer Segment | N23: Median $/SF | O23: # Sales
A24: 🏥 LOCAL BUYER GUIDE — Doctor / Practice Owner (Under 6,000 SF) | M24: Local (< 6K SF) | N24: =B30 -> 623.25581 | O24: =B26 -> 5
A25: KEY METRICS — Small Practice Buildings (< 6,000 SF) | D25: 💡 KEY TAKEAWAY FOR DOCTORS / PRACTICE OWNERS | M25: Mid-Market (6-10K SF) | N25: =B49 -> 87.847731 | O25: =B45 -> 1
A26: Total Small Practice Sales (2020) | B26: {=SUMPRODUCT((LEFT('Medical Sales'!D3:D196,4)="2020")*('Medical Sales'!G3:G196<6000)*('Medical Sales'!G3:G196>0)*('Medical Sales'!U3:U196<>"Yes"))} -> 5 | D26: In 2020, a doctor looking to buy a small practice building could expect: | M26: Institutional (10K+ SF) | N26: =B69 -> 45.304778 | O26: =B65 -> 1
A27: Total Volume | B27: {=SUMPRODUCT((LEFT('Medical Sales'!D3:D196,4)="2020")*('Medical Sales'!G3:G196<6000)*('Medical Sales'!G3:G196>0)*('Medical Sales'!U3:U196<>"Yes")*('Medical Sales'!E3:E196))} -> 10830000
A28: Median Price | B28: {=MEDIAN(IF((LEFT('Medical Sales'!D3:D196,4)="2020")*('Medical Sales'!G3:G196<6000)*('Medical Sales'!G3:G196>0)*('Medical Sales'!U3:U196<>"Yes"),'Medical Sales'!E3:E196))} -> 1340000 | D28: • Median purchase price around $740K for a ~3,600 SF building | M28: Size Bracket | N28: # Sales | O28: Avg $/SF
A29: Average Price | B29: =IF(B26=0,"-",B27/B26) -> 2166000 | D29: • Median $/SF of $242 — competitive entry point | M29: 1. < 3K SF | N29: {=SUMPRODUCT((LEFT('Medical Sales'!D3:D196,4)="2020")*('Medical Sales'!G3:G196<3000)*('Medical Sales'!G3:G196>0)*('Medical Sales'!U3:U196<>"Yes"))} -> 2 | O29: {=IF(N29=0,0,SUMPRODUCT((LEFT('Medical Sales'!D3:D196,4)="2020")*('Medical Sales'!G3:G196<3000)*('Medical Sales'!G3:G196>0)*('Medical Sales'!U3:U196<>"Yes")*('Medical Sales'!F3:F196))/N29)} -> 570.61515
A30: Median $/SF | B30: {=MEDIAN(IF((LEFT('Medical Sales'!D3:D196,4)="2020")*('Medical Sales'!G3:G196<6000)*('Medical Sales'!G3:G196>0)*('Medical Sales'!U3:U196<>"Yes"),'Medical Sales'!F3:F196))} -> 623.25581 | D30: • Lake County remained the most affordable market for small practices | M30: 2. 3 - 6K SF | N30: {=SUMPRODUCT((LEFT('Medical Sales'!D3:D196,4)="2020")*('Medical Sales'!G3:G196>=3000)*('Medical Sales'!G3:G196<6000)*('Medical Sales'!U3:U196<>"Yes"))} -> 3 | O30: {=IF(N30=0,0,SUMPRODUCT((LEFT('Medical Sales'!D3:D196,4)="2020")*('Medical Sales'!G3:G196>=3000)*('Medical Sales'!G3:G196<6000)*('Medical Sales'!U3:U196<>"Yes")*('Medical Sales'!F3:F196))/N30)} -> 570.61649
A31: Average $/SF | B31: {=IF(B26=0,"-",SUMPRODUCT((LEFT('Medical Sales'!D3:D196,4)="2020")*('Medical Sales'!G3:G196<6000)*('Medical Sales'!G3:G196>0)*('Medical Sales'!U3:U196<>"Yes")*('Medical Sales'!F3:F196))/B26)} -> 570.61596 | D31: • 12 of 24 adjusted sales (50%) were under 6K SF — half the market is small-practice product | M31: 3. 6 - 10K SF | N31: {=SUMPRODUCT((LEFT('Medical Sales'!D3:D196,4)="2020")*('Medical Sales'!G3:G196>=6000)*('Medical Sales'!G3:G196<10000)*('Medical Sales'!U3:U196<>"Yes"))} -> 1 | O31: {=IF(N31=0,0,SUMPRODUCT((LEFT('Medical Sales'!D3:D196,4)="2020")*('Medical Sales'!G3:G196>=6000)*('Medical Sales'!G3:G196<10000)*('Medical Sales'!U3:U196<>"Yes")*('Medical Sales'!F3:F196))/N31)} -> 87.847731
A32: Avg Building Size (SF) | B32: {=IF(B26=0,"-",SUMPRODUCT((LEFT('Medical Sales'!D3:D196,4)="2020")*('Medical Sales'!G3:G196<6000)*('Medical Sales'!G3:G196>0)*('Medical Sales'!U3:U196<>"Yes")*('Medical Sales'!G3:G196))/B26)} -> 3663 | D32: • Entry possible as low as $210K (Lake County) | M32: 4. 10 - 20K SF | N32: {=SUMPRODUCT((LEFT('Medical Sales'!D3:D196,4)="2020")*('Medical Sales'!G3:G196>=10000)*('Medical Sales'!G3:G196<20000)*('Medical Sales'!U3:U196<>"Yes"))} -> 1 | O32: {=IF(N32=0,0,SUMPRODUCT((LEFT('Medical Sales'!D3:D196,4)="2020")*('Medical Sales'!G3:G196>=10000)*('Medical Sales'!G3:G196<20000)*('Medical Sales'!U3:U196<>"Yes")*('Medical Sales'!F3:F196))/N32)} -> 45.304778
A33: Price Range — Lowest | B33: {=MIN(IF((LEFT('Medical Sales'!D3:D196,4)="2020")*('Medical Sales'!G3:G196<6000)*('Medical Sales'!G3:G196>0)*('Medical Sales'!U3:U196<>"Yes"),'Medical Sales'!E3:E196))} -> 400000 | D33: • After removing $/SF outliers, pricing was tightly clustered around $240-255/SF | M33: 5. 20K+ SF | N33: {=SUMPRODUCT((LEFT('Medical Sales'!D3:D196,4)="2020")*('Medical Sales'!G3:G196>=20000)*('Medical Sales'!U3:U196<>"Yes"))} -> 0 | O33: {=IF(N33=0,0,SUMPRODUCT((LEFT('Medical Sales'!D3:D196,4)="2020")*('Medical Sales'!G3:G196>=20000)*('Medical Sales'!U3:U196<>"Yes")*('Medical Sales'!F3:F196))/N33)} -> 0
A34: Price Range — Highest | B34: {=MAX(IF((LEFT('Medical Sales'!D3:D196,4)="2020")*('Medical Sales'!G3:G196<6000)*('Medical Sales'!G3:G196>0)*('Medical Sales'!U3:U196<>"Yes"),'Medical Sales'!E3:E196))} -> 5300000
A36: By County — Small Practice Buildings (< 6,000 SF)
A37: County | B37: # Sales | C37: Median Price | D37: Median $/SF | E37: Avg Size (SF) | F37: Min Price | G37: Max Price
A38: Orange | B38: {=SUMPRODUCT(('Medical Sales'!C3:C196="Orange")*(LEFT('Medical Sales'!D3:D196,4)="2020")*('Medical Sales'!G3:G196<6000)*('Medical Sales'!G3:G196>0)*('Medical Sales'!U3:U196<>"Yes"))} -> 1 | C38: {=IFERROR(MEDIAN(IF(('Medical Sales'!C3:C196="Orange")*(LEFT('Medical Sales'!D3:D196,4)="2020")*('Medical Sales'!G3:G196<6000)*('Medical Sales'!G3:G196>0)*('Medical Sales'!U3:U196<>"Yes"),'Medical Sales'!E3:E196)),"-")} -> 5300000 | D38: {=IFERROR(MEDIAN(IF(('Medical Sales'!C3:C196="Orange")*(LEFT('Medical Sales'!D3:D196,4)="2020")*('Medical Sales'!G3:G196<6000)*('Medical Sales'!G3:G196>0)*('Medical Sales'!U3:U196<>"Yes"),'Medical Sales'!F3:F196)),"-")} -> 903.81992 | E38: {=IF(B38=0,"-",SUMPRODUCT(('Medical Sales'!C3:C196="Orange")*(LEFT('Medical Sales'!D3:D196,4)="2020")*('Medical Sales'!G3:G196<6000)*('Medical Sales'!G3:G196>0)*('Medical Sales'!U3:U196<>"Yes")*('Medical Sales'!G3:G196))/B38)} -> 5864 | F38: {=IFERROR(MIN(IF(('Medical Sales'!C3:C196="Orange")*(LEFT('Medical Sales'!D3:D196,4)="2020")*('Medical Sales'!G3:G196<6000)*('Medical Sales'!G3:G196>0)*('Medical Sales'!U3:U196<>"Yes"),'Medical Sales'!E3:E196)),"-")} -> 5300000 | G38: {=IFERROR(MAX(IF(('Medical Sales'!C3:C196="Orange")*(LEFT('Medical Sales'!D3:D196,4)="2020")*('Medical Sales'!G3:G196<6000)*('Medical Sales'!G3:G196>0)*('Medical Sales'!U3:U196<>"Yes"),'Medical Sales'!E3:E196)),"-")} -> 5300000
A39: Seminole | B39: {=SUMPRODUCT(('Medical Sales'!C3:C196="Seminole")*(LEFT('Medical Sales'!D3:D196,4)="2020")*('Medical Sales'!G3:G196<6000)*('Medical Sales'!G3:G196>0)*('Medical Sales'!U3:U196<>"Yes"))} -> 2 | C39: {=IFERROR(MEDIAN(IF(('Medical Sales'!C3:C196="Seminole")*(LEFT('Medical Sales'!D3:D196,4)="2020")*('Medical Sales'!G3:G196<6000)*('Medical Sales'!G3:G196>0)*('Medical Sales'!U3:U196<>"Yes"),'Medical Sales'!E3:E196)),"-")} -> 1340000 | D39: {=IFERROR(MEDIAN(IF(('Medical Sales'!C3:C196="Seminole")*(LEFT('Medical Sales'!D3:D196,4)="2020")*('Medical Sales'!G3:G196<6000)*('Medical Sales'!G3:G196>0)*('Medical Sales'!U3:U196<>"Yes"),'Medical Sales'!F3:F196)),"-")} -> 570.61515 | E39: {=IF(B39=0,"-",SUMPRODUCT(('Medical Sales'!C3:C196="Seminole")*(LEFT('Medical Sales'!D3:D196,4)="2020")*('Medical Sales'!G3:G196<6000)*('Medical Sales'!G3:G196>0)*('Medical Sales'!U3:U196<>"Yes")*('Medical Sales'!G3:G196))/B39)} -> 2368.5 | F39: {=IFERROR(MIN(IF(('Medical Sales'!C3:C196="Seminole")*(LEFT('Medical Sales'!D3:D196,4)="2020")*('Medical Sales'!G3:G196<6000)*('Medical Sales'!G3:G196>0)*('Medical Sales'!U3:U196<>"Yes"),'Medical Sales'!E3:E196)),"-")} -> 1340000 | G39: {=IFERROR(MAX(IF(('Medical Sales'!C3:C196="Seminole")*(LEFT('Medical Sales'!D3:D196,4)="2020")*('Medical Sales'!G3:G196<6000)*('Medical Sales'!G3:G196>0)*('Medical Sales'!U3:U196<>"Yes"),'Medical Sales'!E3:E196)),"-")} -> 1340000
A40: Osceola | B40: {=SUMPRODUCT(('Medical Sales'!C3:C196="Osceola")*(LEFT('Medical Sales'!D3:D196,4)="2020")*('Medical Sales'!G3:G196<6000)*('Medical Sales'!G3:G196>0)*('Medical Sales'!U3:U196<>"Yes"))} -> 2 | C40: {=IFERROR(MEDIAN(IF(('Medical Sales'!C3:C196="Osceola")*(LEFT('Medical Sales'!D3:D196,4)="2020")*('Medical Sales'!G3:G196<6000)*('Medical Sales'!G3:G196>0)*('Medical Sales'!U3:U196<>"Yes"),'Medical Sales'!E3:E196)),"-")} -> 1425000 | D40: {=IFERROR(MEDIAN(IF(('Medical Sales'!C3:C196="Osceola")*(LEFT('Medical Sales'!D3:D196,4)="2020")*('Medical Sales'!G3:G196<6000)*('Medical Sales'!G3:G196>0)*('Medical Sales'!U3:U196<>"Yes"),'Medical Sales'!F3:F196)),"-")} -> 404.01478 | E40: {=IF(B40=0,"-",SUMPRODUCT(('Medical Sales'!C3:C196="Osceola")*(LEFT('Medical Sales'!D3:D196,4)="2020")*('Medical Sales'!G3:G196<6000)*('Medical Sales'!G3:G196>0)*('Medical Sales'!U3:U196<>"Yes")*('Medical Sales'!G3:G196))/B40)} -> 3857 | F40: {=IFERROR(MIN(IF(('Medical Sales'!C3:C196="Osceola")*(LEFT('Medical Sales'!D3:D196,4)="2020")*('Medical Sales'!G3:G196<6000)*('Medical Sales'!G3:G196>0)*('Medical Sales'!U3:U196<>"Yes"),'Medical Sales'!E3:E196)),"-")} -> 400000 | G40: {=IFERROR(MAX(IF(('Medical Sales'!C3:C196="Osceola")*(LEFT('Medical Sales'!D3:D196,4)="2020")*('Medical Sales'!G3:G196<6000)*('Medical Sales'!G3:G196>0)*('Medical Sales'!U3:U196<>"Yes"),'Medical Sales'!E3:E196)),"-")} -> 2450000
A41: Lake | B41: {=SUMPRODUCT(('Medical Sales'!C3:C196="Lake")*(LEFT('Medical Sales'!D3:D196,4)="2020")*('Medical Sales'!G3:G196<6000)*('Medical Sales'!G3:G196>0)*('Medical Sales'!U3:U196<>"Yes"))} -> 0 | C41: {=IFERROR(MEDIAN(IF(('Medical Sales'!C3:C196="Lake")*(LEFT('Medical Sales'!D3:D196,4)="2020")*('Medical Sales'!G3:G196<6000)*('Medical Sales'!G3:G196>0)*('Medical Sales'!U3:U196<>"Yes"),'Medical Sales'!E3:E196)),"-")} -> - | D41: {=IFERROR(MEDIAN(IF(('Medical Sales'!C3:C196="Lake")*(LEFT('Medical Sales'!D3:D196,4)="2020")*('Medical Sales'!G3:G196<6000)*('Medical Sales'!G3:G196>0)*('Medical Sales'!U3:U196<>"Yes"),'Medical Sales'!F3:F196)),"-")} -> - | E41: {=IF(B41=0,"-",SUMPRODUCT(('Medical Sales'!C3:C196="Lake")*(LEFT('Medical Sales'!D3:D196,4)="2020")*('Medical Sales'!G3:G196<6000)*('Medical Sales'!G3:G196>0)*('Medical Sales'!U3:U196<>"Yes")*('Medical Sales'!G3:G196))/B41)} -> - | F41: {=IFERROR(MIN(IF(('Medical Sales'!C3:C196="Lake")*(LEFT('Medical Sales'!D3:D196,4)="2020")*('Medical Sales'!G3:G196<6000)*('Medical Sales'!G3:G196>0)*('Medical Sales'!U3:U196<>"Yes"),'Medical Sales'!E3:E196)),"-")} -> 0 | G41: {=IFERROR(MAX(IF(('Medical Sales'!C3:C196="Lake")*(LEFT('Medical Sales'!D3:D196,4)="2020")*('Medical Sales'!G3:G196<6000)*('Medical Sales'!G3:G196>0)*('Medical Sales'!U3:U196<>"Yes"),'Medical Sales'!E3:E196)),"-")} -> 0
A43: 🏥 MID-MARKET GUIDE — Group Practice / Small Clinic (6,000–9,999 SF) | D43: 💡 KEY TAKEAWAY FOR GROUP PRACTICES / SMALL CLINICS
A44: KEY METRICS — Mid-Size Buildings (6,000–9,999 SF) | D44: In 2020, group practices looking for 6K–10K SF buildings found:
A45: Total Mid-Market Sales (2020) | B45: {=SUMPRODUCT((LEFT('Medical Sales'!D3:D196,4)="2020")*('Medical Sales'!G3:G196>=6000)*('Medical Sales'!G3:G196<10000)*('Medical Sales'!U3:U196<>"Yes"))} -> 1
A46: Total Volume | B46: {=SUMPRODUCT((LEFT('Medical Sales'!D3:D196,4)="2020")*('Medical Sales'!G3:G196>=6000)*('Medical Sales'!G3:G196<10000)*('Medical Sales'!U3:U196<>"Yes")*('Medical Sales'!E3:E196))} -> 780000 | D46: • 8 sales in this size bracket — 27% of total 2020 market
A47: Median Price | B47: {=MEDIAN(IF((LEFT('Medical Sales'!D3:D196,4)="2020")*('Medical Sales'!G3:G196>=6000)*('Medical Sales'!G3:G196<10000)*('Medical Sales'!U3:U196<>"Yes"),'Medical Sales'!E3:E196))} -> 780000 | D47: • Median price: $2.35M at $348/SF — highest $/SF of any size bracket
A48: Average Price | B48: =IF(B45=0,"-",B46/B45) -> 780000 | D48: • Orange County dominated (5 of 8 sales) at $399/SF median
A49: Median $/SF | B49: {=MEDIAN(IF((LEFT('Medical Sales'!D3:D196,4)="2020")*('Medical Sales'!G3:G196>=6000)*('Medical Sales'!G3:G196<10000)*('Medical Sales'!U3:U196<>"Yes"),'Medical Sales'!F3:F196))} -> 87.847731 | D49: • Zero sales in Lake County — no mid-market product available
A50: Average $/SF | B50: {=IF(B45=0,"-",SUMPRODUCT((LEFT('Medical Sales'!D3:D196,4)="2020")*('Medical Sales'!G3:G196>=6000)*('Medical Sales'!G3:G196<10000)*('Medical Sales'!U3:U196<>"Yes")*('Medical Sales'!F3:F196))/B45)} -> 87.847731 | D50: • Price range: $780K–$3.57M — wide variance by location & condition
A51: Avg Building Size (SF) | B51: {=IF(B45=0,"-",SUMPRODUCT((LEFT('Medical Sales'!D3:D196,4)="2020")*('Medical Sales'!G3:G196>=6000)*('Medical Sales'!G3:G196<10000)*('Medical Sales'!U3:U196<>"Yes")*('Medical Sales'!G3:G196))/B45)} -> 8879 | D51: • $/SF premium: Mid-market buildings traded 34% above small practices
A52: Price Range — Lowest | B52: {=MIN(IF((LEFT('Medical Sales'!D3:D196,4)="2020")*('Medical Sales'!G3:G196>=6000)*('Medical Sales'!G3:G196<10000)*('Medical Sales'!U3:U196<>"Yes"),'Medical Sales'!E3:E196))} -> 780000
A53: Price Range — Highest | B53: {=MAX(IF((LEFT('Medical Sales'!D3:D196,4)="2020")*('Medical Sales'!G3:G196>=6000)*('Medical Sales'!G3:G196<10000)*('Medical Sales'!U3:U196<>"Yes"),'Medical Sales'!E3:E196))} -> 780000
A55: By County — Mid-Size Buildings (6,000–9,999 SF)
A56: County | B56: # Sales | C56: Median Price | D56: Median $/SF | E56: Avg Size (SF) | F56: Min Price | G56: Max Price
A57: Orange | B57: {=SUMPRODUCT(('Medical Sales'!C3:C196="Orange")*(LEFT('Medical Sales'!D3:D196,4)="2020")*('Medical Sales'!G3:G196>=6000)*('Medical Sales'!G3:G196<10000)*('Medical Sales'!U3:U196<>"Yes"))} -> 0 | C57: {=IFERROR(MEDIAN(IF(('Medical Sales'!C3:C196="Orange")*(LEFT('Medical Sales'!D3:D196,4)="2020")*('Medical Sales'!G3:G196>=6000)*('Medical Sales'!G3:G196<10000)*('Medical Sales'!U3:U196<>"Yes"),'Medical Sales'!E3:E196)),"-")} -> - | D57: {=IFERROR(MEDIAN(IF(('Medical Sales'!C3:C196="Orange")*(LEFT('Medical Sales'!D3:D196,4)="2020")*('Medical Sales'!G3:G196>=6000)*('Medical Sales'!G3:G196<10000)*('Medical Sales'!U3:U196<>"Yes"),'Medical Sales'!F3:F196)),"-")} -> - | E57: {=IF(B57=0,"-",SUMPRODUCT(('Medical Sales'!C3:C196="Orange")*(LEFT('Medical Sales'!D3:D196,4)="2020")*('Medical Sales'!G3:G196>=6000)*('Medical Sales'!G3:G196<10000)*('Medical Sales'!U3:U196<>"Yes")*('Medical Sales'!G3:G196))/B57)} -> - | F57: {=IF(B57=0,"-",MIN(IF(('Medical Sales'!C3:C196="Orange")*(LEFT('Medical Sales'!D3:D196,4)="2020")*('Medical Sales'!G3:G196>=6000)*('Medical Sales'!G3:G196<10000)*('Medical Sales'!U3:U196<>"Yes"),'Medical Sales'!E3:E196)))} -> - | G57: {=IF(B57=0,"-",MAX(IF(('Medical Sales'!C3:C196="Orange")*(LEFT('Medical Sales'!D3:D196,4)="2020")*('Medical Sales'!G3:G196>=6000)*('Medical Sales'!G3:G196<10000)*('Medical Sales'!U3:U196<>"Yes"),'Medical Sales'!E3:E196)))} -> -
A58: Seminole | B58: {=SUMPRODUCT(('Medical Sales'!C3:C196="Seminole")*(LEFT('Medical Sales'!D3:D196,4)="2020")*('Medical Sales'!G3:G196>=6000)*('Medical Sales'!G3:G196<10000)*('Medical Sales'!U3:U196<>"Yes"))} -> 1 | C58: {=IFERROR(MEDIAN(IF(('Medical Sales'!C3:C196="Seminole")*(LEFT('Medical Sales'!D3:D196,4)="2020")*('Medical Sales'!G3:G196>=6000)*('Medical Sales'!G3:G196<10000)*('Medical Sales'!U3:U196<>"Yes"),'Medical Sales'!E3:E196)),"-")} -> 780000 | D58: {=IFERROR(MEDIAN(IF(('Medical Sales'!C3:C196="Seminole")*(LEFT('Medical Sales'!D3:D196,4)="2020")*('Medical Sales'!G3:G196>=6000)*('Medical Sales'!G3:G196<10000)*('Medical Sales'!U3:U196<>"Yes"),'Medical Sales'!F3:F196)),"-")} -> 87.847731 | E58: {=IF(B58=0,"-",SUMPRODUCT(('Medical Sales'!C3:C196="Seminole")*(LEFT('Medical Sales'!D3:D196,4)="2020")*('Medical Sales'!G3:G196>=6000)*('Medical Sales'!G3:G196<10000)*('Medical Sales'!U3:U196<>"Yes")*('Medical Sales'!G3:G196))/B58)} -> 8879 | F58: {=IF(B58=0,"-",MIN(IF(('Medical Sales'!C3:C196="Seminole")*(LEFT('Medical Sales'!D3:D196,4)="2020")*('Medical Sales'!G3:G196>=6000)*('Medical Sales'!G3:G196<10000)*('Medical Sales'!U3:U196<>"Yes"),'Medical Sales'!E3:E196)))} -> 780000 | G58: {=IF(B58=0,"-",MAX(IF(('Medical Sales'!C3:C196="Seminole")*(LEFT('Medical Sales'!D3:D196,4)="2020")*('Medical Sales'!G3:G196>=6000)*('Medical Sales'!G3:G196<10000)*('Medical Sales'!U3:U196<>"Yes"),'Medical Sales'!E3:E196)))} -> 780000
A59: Osceola | B59: {=SUMPRODUCT(('Medical Sales'!C3:C196="Osceola")*(LEFT('Medical Sales'!D3:D196,4)="2020")*('Medical Sales'!G3:G196>=6000)*('Medical Sales'!G3:G196<10000)*('Medical Sales'!U3:U196<>"Yes"))} -> 0 | C59: {=IFERROR(MEDIAN(IF(('Medical Sales'!C3:C196="Osceola")*(LEFT('Medical Sales'!D3:D196,4)="2020")*('Medical Sales'!G3:G196>=6000)*('Medical Sales'!G3:G196<10000)*('Medical Sales'!U3:U196<>"Yes"),'Medical Sales'!E3:E196)),"-")} -> - | D59: {=IFERROR(MEDIAN(IF(('Medical Sales'!C3:C196="Osceola")*(LEFT('Medical Sales'!D3:D196,4)="2020")*('Medical Sales'!G3:G196>=6000)*('Medical Sales'!G3:G196<10000)*('Medical Sales'!U3:U196<>"Yes"),'Medical Sales'!F3:F196)),"-")} -> - | E59: {=IF(B59=0,"-",SUMPRODUCT(('Medical Sales'!C3:C196="Osceola")*(LEFT('Medical Sales'!D3:D196,4)="2020")*('Medical Sales'!G3:G196>=6000)*('Medical Sales'!G3:G196<10000)*('Medical Sales'!U3:U196<>"Yes")*('Medical Sales'!G3:G196))/B59)} -> - | F59: {=IF(B59=0,"-",MIN(IF(('Medical Sales'!C3:C196="Osceola")*(LEFT('Medical Sales'!D3:D196,4)="2020")*('Medical Sales'!G3:G196>=6000)*('Medical Sales'!G3:G196<10000)*('Medical Sales'!U3:U196<>"Yes"),'Medical Sales'!E3:E196)))} -> - | G59: {=IF(B59=0,"-",MAX(IF(('Medical Sales'!C3:C196="Osceola")*(LEFT('Medical Sales'!D3:D196,4)="2020")*('Medical Sales'!G3:G196>=6000)*('Medical Sales'!G3:G196<10000)*('Medical Sales'!U3:U196<>"Yes"),'Medical Sales'!E3:E196)))} -> -
A60: Lake | B60: {=SUMPRODUCT(('Medical Sales'!C3:C196="Lake")*(LEFT('Medical Sales'!D3:D196,4)="2020")*('Medical Sales'!G3:G196>=6000)*('Medical Sales'!G3:G196<10000)*('Medical Sales'!U3:U196<>"Yes"))} -> 0 | C60: {=IFERROR(MEDIAN(IF(('Medical Sales'!C3:C196="Lake")*(LEFT('Medical Sales'!D3:D196,4)="2020")*('Medical Sales'!G3:G196>=6000)*('Medical Sales'!G3:G196<10000)*('Medical Sales'!U3:U196<>"Yes"),'Medical Sales'!E3:E196)),"-")} -> - | D60: {=IFERROR(MEDIAN(IF(('Medical Sales'!C3:C196="Lake")*(LEFT('Medical Sales'!D3:D196,4)="2020")*('Medical Sales'!G3:G196>=6000)*('Medical Sales'!G3:G196<10000)*('Medical Sales'!U3:U196<>"Yes"),'Medical Sales'!F3:F196)),"-")} -> - | E60: {=IF(B60=0,"-",SUMPRODUCT(('Medical Sales'!C3:C196="Lake")*(LEFT('Medical Sales'!D3:D196,4)="2020")*('Medical Sales'!G3:G196>=6000)*('Medical Sales'!G3:G196<10000)*('Medical Sales'!U3:U196<>"Yes")*('Medical Sales'!G3:G196))/B60)} -> - | F60: {=IF(B60=0,"-",MIN(IF(('Medical Sales'!C3:C196="Lake")*(LEFT('Medical Sales'!D3:D196,4)="2020")*('Medical Sales'!G3:G196>=6000)*('Medical Sales'!G3:G196<10000)*('Medical Sales'!U3:U196<>"Yes"),'Medical Sales'!E3:E196)))} -> - | G60: {=IF(B60=0,"-",MAX(IF(('Medical Sales'!C3:C196="Lake")*(LEFT('Medical Sales'!D3:D196,4)="2020")*('Medical Sales'!G3:G196>=6000)*('Medical Sales'!G3:G196<10000)*('Medical Sales'!U3:U196<>"Yes"),'Medical Sales'!E3:E196)))} -> -
A63: 🏢 INSTITUTIONAL BUYER GUIDE — Large Medical Buildings (10,000+ SF)
A64: KEY METRICS — Institutional-Grade Buildings (10,000+ SF) | D64: 💡 KEY TAKEAWAY FOR INSTITUTIONAL BUYERS
A65: Total Large Building Sales (2020) | B65: {=SUMPRODUCT((LEFT('Medical Sales'!D3:D196,4)="2020")*('Medical Sales'!G3:G196>=10000)*('Medical Sales'!U3:U196<>"Yes"))} -> 1 | D65: In 2020, institutional buyers targeting large medical buildings saw:
A66: Total Volume | B66: {=SUMPRODUCT((LEFT('Medical Sales'!D3:D196,4)="2020")*('Medical Sales'!G3:G196>=10000)*('Medical Sales'!U3:U196<>"Yes")*('Medical Sales'!E3:E196))} -> 550000
A67: Median Price | B67: {=IFERROR(MEDIAN(IF((LEFT('Medical Sales'!D3:D196,4)="2020")*('Medical Sales'!G3:G196>=10000)*('Medical Sales'!U3:U196<>"Yes"),'Medical Sales'!E3:E196)),"-")} -> 550000 | D67: • Only 5 adjusted deals over 10K SF — very limited supply
A68: Average Price | B68: =IF(B65=0,"-",B66/B65) -> 550000 | D68: • Median deal size: $5.1M at ~$220/SF — lower $/SF than small buildings
A69: Median $/SF | B69: {=IFERROR(MEDIAN(IF((LEFT('Medical Sales'!D3:D196,4)="2020")*('Medical Sales'!G3:G196>=10000)*('Medical Sales'!U3:U196<>"Yes"),'Medical Sales'!F3:F196)),"-")} -> 45.304778 | D69: • Multi-Tenant Medical dominated the large-building segment
A70: Average $/SF | B70: {=IF(B65=0,"-",SUMPRODUCT((LEFT('Medical Sales'!D3:D196,4)="2020")*('Medical Sales'!G3:G196>=10000)*('Medical Sales'!U3:U196<>"Yes")*('Medical Sales'!F3:F196))/B65)} -> 45.304778 | D70: • Orange County was the primary institutional market
A71: Avg Building Size (SF) | B71: {=IF(B65=0,"-",SUMPRODUCT((LEFT('Medical Sales'!D3:D196,4)="2020")*('Medical Sales'!G3:G196>=10000)*('Medical Sales'!U3:U196<>"Yes")*('Medical Sales'!G3:G196))/B65)} -> 12140 | D71: • Avg building size: ~16,600 SF — typical multi-tenant medical office
A72: Price Range — Lowest | B72: {=IFERROR(MIN(IF((LEFT('Medical Sales'!D3:D196,4)="2020")*('Medical Sales'!G3:G196>=10000)*('Medical Sales'!U3:U196<>"Yes"),'Medical Sales'!E3:E196)),"-")} -> 550000 | D72: • With outliers removed, institutional pricing was more consistent
A73: Price Range — Highest | B73: {=IFERROR(MAX(IF((LEFT('Medical Sales'!D3:D196,4)="2020")*('Medical Sales'!G3:G196>=10000)*('Medical Sales'!U3:U196<>"Yes"),'Medical Sales'!E3:E196)),"-")} -> 550000
A75: By County — Large Buildings (10,000+ SF)
A76: County | B76: # Sales | C76: Median Price | D76: Median $/SF | E76: Avg Size (SF) | F76: Min Price | G76: Max Price
A77: Orange | B77: {=SUMPRODUCT(('Medical Sales'!C3:C196="Orange")*(LEFT('Medical Sales'!D3:D196,4)="2020")*('Medical Sales'!G3:G196>=10000)*('Medical Sales'!U3:U196<>"Yes"))} -> 0 | C77: {=IFERROR(MEDIAN(IF(('Medical Sales'!C3:C196="Orange")*(LEFT('Medical Sales'!D3:D196,4)="2020")*('Medical Sales'!G3:G196>=10000)*('Medical Sales'!U3:U196<>"Yes"),'Medical Sales'!E3:E196)),"-")} -> - | D77: {=IFERROR(MEDIAN(IF(('Medical Sales'!C3:C196="Orange")*(LEFT('Medical Sales'!D3:D196,4)="2020")*('Medical Sales'!G3:G196>=10000)*('Medical Sales'!U3:U196<>"Yes"),'Medical Sales'!F3:F196)),"-")} -> - | E77: {=IF(B77=0,"-",SUMPRODUCT(('Medical Sales'!C3:C196="Orange")*(LEFT('Medical Sales'!D3:D196,4)="2020")*('Medical Sales'!G3:G196>=10000)*('Medical Sales'!U3:U196<>"Yes")*('Medical Sales'!G3:G196))/B77)} -> - | F77: {=IF(B77=0,"-",MIN(IF(('Medical Sales'!C3:C196="Orange")*(LEFT('Medical Sales'!D3:D196,4)="2020")*('Medical Sales'!G3:G196>=10000)*('Medical Sales'!U3:U196<>"Yes"),'Medical Sales'!E3:E196)))} -> - | G77: {=IF(B77=0,"-",MAX(IF(('Medical Sales'!C3:C196="Orange")*(LEFT('Medical Sales'!D3:D196,4)="2020")*('Medical Sales'!G3:G196>=10000)*('Medical Sales'!U3:U196<>"Yes"),'Medical Sales'!E3:E196)))} -> -
A78: Seminole | B78: {=SUMPRODUCT(('Medical Sales'!C3:C196="Seminole")*(LEFT('Medical Sales'!D3:D196,4)="2020")*('Medical Sales'!G3:G196>=10000)*('Medical Sales'!U3:U196<>"Yes"))} -> 1 | C78: {=IFERROR(MEDIAN(IF(('Medical Sales'!C3:C196="Seminole")*(LEFT('Medical Sales'!D3:D196,4)="2020")*('Medical Sales'!G3:G196>=10000)*('Medical Sales'!U3:U196<>"Yes"),'Medical Sales'!E3:E196)),"-")} -> 550000 | D78: {=IFERROR(MEDIAN(IF(('Medical Sales'!C3:C196="Seminole")*(LEFT('Medical Sales'!D3:D196,4)="2020")*('Medical Sales'!G3:G196>=10000)*('Medical Sales'!U3:U196<>"Yes"),'Medical Sales'!F3:F196)),"-")} -> 45.304778 | E78: {=IF(B78=0,"-",SUMPRODUCT(('Medical Sales'!C3:C196="Seminole")*(LEFT('Medical Sales'!D3:D196,4)="2020")*('Medical Sales'!G3:G196>=10000)*('Medical Sales'!U3:U196<>"Yes")*('Medical Sales'!G3:G196))/B78)} -> 12140 | F78: {=IF(B78=0,"-",MIN(IF(('Medical Sales'!C3:C196="Seminole")*(LEFT('Medical Sales'!D3:D196,4)="2020")*('Medical Sales'!G3:G196>=10000)*('Medical Sales'!U3:U196<>"Yes"),'Medical Sales'!E3:E196)))} -> 550000 | G78: {=IF(B78=0,"-",MAX(IF(('Medical Sales'!C3:C196="Seminole")*(LEFT('Medical Sales'!D3:D196,4)="2020")*('Medical Sales'!G3:G196>=10000)*('Medical Sales'!U3:U196<>"Yes"),'Medical Sales'!E3:E196)))} -> 550000
A79: Osceola | B79: {=SUMPRODUCT(('Medical Sales'!C3:C196="Osceola")*(LEFT('Medical Sales'!D3:D196,4)="2020")*('Medical Sales'!G3:G196>=10000)*('Medical Sales'!U3:U196<>"Yes"))} -> 0 | C79: {=IFERROR(MEDIAN(IF(('Medical Sales'!C3:C196="Osceola")*(LEFT('Medical Sales'!D3:D196,4)="2020")*('Medical Sales'!G3:G196>=10000)*('Medical Sales'!U3:U196<>"Yes"),'Medical Sales'!E3:E196)),"-")} -> - | D79: {=IFERROR(MEDIAN(IF(('Medical Sales'!C3:C196="Osceola")*(LEFT('Medical Sales'!D3:D196,4)="2020")*('Medical Sales'!G3:G196>=10000)*('Medical Sales'!U3:U196<>"Yes"),'Medical Sales'!F3:F196)),"-")} -> - | E79: {=IF(B79=0,"-",SUMPRODUCT(('Medical Sales'!C3:C196="Osceola")*(LEFT('Medical Sales'!D3:D196,4)="2020")*('Medical Sales'!G3:G196>=10000)*('Medical Sales'!U3:U196<>"Yes")*('Medical Sales'!G3:G196))/B79)} -> - | F79: {=IF(B79=0,"-",MIN(IF(('Medical Sales'!C3:C196="Osceola")*(LEFT('Medical Sales'!D3:D196,4)="2020")*('Medical Sales'!G3:G196>=10000)*('Medical Sales'!U3:U196<>"Yes"),'Medical Sales'!E3:E196)))} -> - | G79: {=IF(B79=0,"-",MAX(IF(('Medical Sales'!C3:C196="Osceola")*(LEFT('Medical Sales'!D3:D196,4)="2020")*('Medical Sales'!G3:G196>=10000)*('Medical Sales'!U3:U196<>"Yes"),'Medical Sales'!E3:E196)))} -> -
A80: Lake | B80: =COUNTIFS('Medical Sales'!C:C,"Lake",'Medical Sales'!D:D,"2020*",'Medical Sales'!G:G,">=10000") -> 1 | C80: {=IFERROR(MEDIAN(IF(('Medical Sales'!C3:C196="Lake")*(LEFT('Medical Sales'!D3:D196,4)="2020")*('Medical Sales'!G3:G196>=10000),'Medical Sales'!E3:E196)),"-")} -> 1340800 | D80: {=IFERROR(MEDIAN(IF(('Medical Sales'!C3:C196="Lake")*(LEFT('Medical Sales'!D3:D196,4)="2020")*('Medical Sales'!G3:G196>=10000),'Medical Sales'!F3:F196)),"-")} -> 111.71471 | E80: {=IF(B80=0,"-",SUMPRODUCT(('Medical Sales'!C3:C196="Lake")*(LEFT('Medical Sales'!D3:D196,4)="2020")*('Medical Sales'!G3:G196>=10000)*('Medical Sales'!G3:G196))/B80)} -> 12002 | F80: {=IFERROR(MIN(IF(('Medical Sales'!C3:C196="Lake")*(LEFT('Medical Sales'!D3:D196,4)="2020")*('Medical Sales'!G3:G196>=10000),'Medical Sales'!E3:E196)),"-")} -> 1340800 | G80: {=IFERROR(MAX(IF(('Medical Sales'!C3:C196="Lake")*(LEFT('Medical Sales'!D3:D196,4)="2020")*('Medical Sales'!G3:G196>=10000),'Medical Sales'!E3:E196)),"-")} -> 1340800
A82: By Category — Large Buildings (10,000+ SF)
A83: Category | B83: # Sales | C83: Total Volume | D83: Median Price | E83: Median $/SF | F83: Avg Size (SF) | G83: Max Price
A84: Medical | B84: {=SUMPRODUCT(('Medical Sales'!N3:N196="Medical")*(LEFT('Medical Sales'!D3:D196,4)="2020")*('Medical Sales'!G3:G196>=10000)*('Medical Sales'!U3:U196<>"Yes"))} -> 0 | C84: {=IF(B84=0,"-",SUMPRODUCT(('Medical Sales'!N3:N196="Medical")*(LEFT('Medical Sales'!D3:D196,4)="2020")*('Medical Sales'!G3:G196>=10000)*('Medical Sales'!U3:U196<>"Yes")*('Medical Sales'!E3:E196)))} -> - | D84: {=IFERROR(MEDIAN(IF(('Medical Sales'!N3:N196="Medical")*(LEFT('Medical Sales'!D3:D196,4)="2020")*('Medical Sales'!G3:G196>=10000)*('Medical Sales'!U3:U196<>"Yes"),'Medical Sales'!E3:E196)),"-")} -> - | E84: {=IFERROR(MEDIAN(IF(('Medical Sales'!N3:N196="Medical")*(LEFT('Medical Sales'!D3:D196,4)="2020")*('Medical Sales'!G3:G196>=10000)*('Medical Sales'!U3:U196<>"Yes"),'Medical Sales'!F3:F196)),"-")} -> - | F84: {=IF(B84=0,"-",SUMPRODUCT(('Medical Sales'!N3:N196="Medical")*(LEFT('Medical Sales'!D3:D196,4)="2020")*('Medical Sales'!G3:G196>=10000)*('Medical Sales'!U3:U196<>"Yes")*('Medical Sales'!G3:G196))/B84)} -> - | G84: {=IFERROR(MAX(IF(('Medical Sales'!N3:N196="Medical")*(LEFT('Medical Sales'!D3:D196,4)="2020")*('Medical Sales'!G3:G196>=10000)*('Medical Sales'!U3:U196<>"Yes"),'Medical Sales'!E3:E196)),"-")} -> 0
A85: Multi-Tenant Medical | B85: {=SUMPRODUCT(('Medical Sales'!N3:N196="Multi-Tenant Medical")*(LEFT('Medical Sales'!D3:D196,4)="2020")*('Medical Sales'!G3:G196>=10000)*('Medical Sales'!U3:U196<>"Yes"))} -> 0 | C85: {=IF(B85=0,"-",SUMPRODUCT(('Medical Sales'!N3:N196="Multi-Tenant Medical")*(LEFT('Medical Sales'!D3:D196,4)="2020")*('Medical Sales'!G3:G196>=10000)*('Medical Sales'!U3:U196<>"Yes")*('Medical Sales'!E3:E196)))} -> - | D85: {=IFERROR(MEDIAN(IF(('Medical Sales'!N3:N196="Multi-Tenant Medical")*(LEFT('Medical Sales'!D3:D196,4)="2020")*('Medical Sales'!G3:G196>=10000)*('Medical Sales'!U3:U196<>"Yes"),'Medical Sales'!E3:E196)),"-")} -> - | E85: {=IFERROR(MEDIAN(IF(('Medical Sales'!N3:N196="Multi-Tenant Medical")*(LEFT('Medical Sales'!D3:D196,4)="2020")*('Medical Sales'!G3:G196>=10000)*('Medical Sales'!U3:U196<>"Yes"),'Medical Sales'!F3:F196)),"-")} -> - | F85: {=IF(B85=0,"-",SUMPRODUCT(('Medical Sales'!N3:N196="Multi-Tenant Medical")*(LEFT('Medical Sales'!D3:D196,4)="2020")*('Medical Sales'!G3:G196>=10000)*('Medical Sales'!U3:U196<>"Yes")*('Medical Sales'!G3:G196))/B85)} -> - | G85: {=IFERROR(MAX(IF(('Medical Sales'!N3:N196="Multi-Tenant Medical")*(LEFT('Medical Sales'!D3:D196,4)="2020")*('Medical Sales'!G3:G196>=10000)*('Medical Sales'!U3:U196<>"Yes"),'Medical Sales'!E3:E196)),"-")} -> 0
A86: Hospitals | B86: {=SUMPRODUCT(('Medical Sales'!N3:N196="Hospitals")*(LEFT('Medical Sales'!D3:D196,4)="2020")*('Medical Sales'!G3:G196>=10000)*('Medical Sales'!U3:U196<>"Yes"))} -> 1 | C86: {=IF(B86=0,"-",SUMPRODUCT(('Medical Sales'!N3:N196="Hospitals")*(LEFT('Medical Sales'!D3:D196,4)="2020")*('Medical Sales'!G3:G196>=10000)*('Medical Sales'!U3:U196<>"Yes")*('Medical Sales'!E3:E196)))} -> 550000 | D86: {=IFERROR(MEDIAN(IF(('Medical Sales'!N3:N196="Hospitals")*(LEFT('Medical Sales'!D3:D196,4)="2020")*('Medical Sales'!G3:G196>=10000)*('Medical Sales'!U3:U196<>"Yes"),'Medical Sales'!E3:E196)),"-")} -> 550000 | E86: {=IFERROR(MEDIAN(IF(('Medical Sales'!N3:N196="Hospitals")*(LEFT('Medical Sales'!D3:D196,4)="2020")*('Medical Sales'!G3:G196>=10000)*('Medical Sales'!U3:U196<>"Yes"),'Medical Sales'!F3:F196)),"-")} -> 45.304778 | F86: {=IF(B86=0,"-",SUMPRODUCT(('Medical Sales'!N3:N196="Hospitals")*(LEFT('Medical Sales'!D3:D196,4)="2020")*('Medical Sales'!G3:G196>=10000)*('Medical Sales'!U3:U196<>"Yes")*('Medical Sales'!G3:G196))/B86)} -> 12140 | G86: {=IFERROR(MAX(IF(('Medical Sales'!N3:N196="Hospitals")*(LEFT('Medical Sales'!D3:D196,4)="2020")*('Medical Sales'!G3:G196>=10000)*('Medical Sales'!U3:U196<>"Yes"),'Medical Sales'!E3:E196)),"-")} -> 550000
A88: 📅 BUILDING AGE ANALYSIS — 2020 Sales | M88: Building Age | N88: Median $/SF | O88: # Sales
A89: Building Age | B89: # Sales | C89: Total Volume | D89: Median Price | E89: Median $/SF | F89: Avg $/SF | G89: Avg Size (SF) | H89: $/SF Premium vs Old | M89: New (0-10 yrs) | N89: =E90 -> 87.847731 | O89: =B90 -> 3
A90: New (0–10 yrs) | B90: {=SUMPRODUCT((LEFT('Medical Sales'!D3:D196,4)="2020")*('Medical Sales'!T3:T196="New")*('Medical Sales'!U3:U196<>"Yes"))} -> 3 | C90: {=SUMPRODUCT((LEFT('Medical Sales'!D3:D196,4)="2020")*('Medical Sales'!T3:T196="New")*('Medical Sales'!U3:U196<>"Yes")*('Medical Sales'!E3:E196))} -> 6630000 | D90: {=IFERROR(MEDIAN(IF((LEFT('Medical Sales'!D3:D196,4)="2020")*('Medical Sales'!T3:T196="New")*('Medical Sales'!U3:U196<>"Yes"),'Medical Sales'!E3:E196)),"-")} -> 780000 | E90: {=IFERROR(MEDIAN(IF((LEFT('Medical Sales'!D3:D196,4)="2020")*('Medical Sales'!T3:T196="New")*('Medical Sales'!U3:U196<>"Yes"),'Medical Sales'!F3:F196)),"-")} -> 87.847731 | F90: {=IF(B90=0,"-",SUMPRODUCT((LEFT('Medical Sales'!D3:D196,4)="2020")*('Medical Sales'!T3:T196="New")*('Medical Sales'!U3:U196<>"Yes")*('Medical Sales'!F3:F196))/B90)} -> 345.65748 | G90: {=IF(B90=0,"-",SUMPRODUCT((LEFT('Medical Sales'!D3:D196,4)="2020")*('Medical Sales'!T3:T196="New")*('Medical Sales'!U3:U196<>"Yes")*('Medical Sales'!G3:G196))/B90)} -> 8961 | H90: =IF(OR(E92=0,E90=0),"-",(E90-E92)/E92) -> -0.78256308 | M90: Normal (11-25 yrs) | N90: =E91 -> 570.61515 | O90: =B91 -> 2
